Workbook

Sheet Summary_Store
A1: No. | B1: Category | C1: Qty | D1: Notes | E1: HCM | F1: South stores (other than HCM) | G1: HN | H1: North stores (other than HN)
A2: 1 | B2: Number of active stores | C2: =COUNTIFS(Store_Info_VN!D:D,"Open",Store_Info_VN!K:K,"Store") + COUNTIFS(Store_Info_VN!D:D,"Open",Store_Info_VN!K:K,"Multi PC") + COUNTIFS(Store_Info_VN!D:D,"Open",Store_Info_VN!K:K,"Mono") + COUNTIFS(Store_Info_VN!D:D,"Open",Store_Info_VN!K:K,"SIS") -> 1 | E2: =COUNTIFS(Store_Info_VN!D:D,"Open",Store_Info_VN!K:K,"Store",Store_Info_VN!F:F,"Ho Chi Minh City") + COUNTIFS(Store_Info_VN!D:D,"Open",Store_Info_VN!K:K,"Mono",Store_Info_VN!F:F,"Ho Chi Minh City") + COUNTIFS(Store_Info_VN!D:D,"Open",Store_Info_VN!K:K,"SIS",Store_Info_VN!F:F,"Ho Chi Minh City") -> 1 | F2: =(COUNTIFS(Store_Info_VN!D:D,"Open",Store_Info_VN!K:K,"Store",Store_Info_VN!G:G,"South") + COUNTIFS(Store_Info_VN!D:D,"Open",Store_Info_VN!K:K,"Mono",Store_Info_VN!G:G,"South") + COUNTIFS(Store_Info_VN!D:D,"Open",Store_Info_VN!K:K,"SIS",Store_Info_VN!G:G,"South"))-E2 -> -1 | G2: =COUNTIFS(Store_Info_VN!D:D,"Open",Store_Info_VN!K:K,"Store",Store_Info_VN!F:F,"Ha Noi") + COUNTIFS(Store_Info_VN!D:D,"Open",Store_Info_VN!K:K,"Mono",Store_Info_VN!F:F,"Ha Noi") + COUNTIFS(Store_Info_VN!D:D,"Open",Store_Info_VN!K:K,"SIS",Store_Info_VN!F:F,"Ha Noi") -> 0 | H2: =(COUNTIFS(Store_Info_VN!D:D,"Open",Store_Info_VN!K:K,"Store",Store_Info_VN!G:G,"North") + COUNTIFS(Store_Info_VN!D:D,"Open",Store_Info_VN!K:K,"Mono",Store_Info_VN!G:G,"North") + COUNTIFS(Store_Info_VN!D:D,"Open",Store_Info_VN!K:K,"SIS",Store_Info_VN!G:G,"North"))-G2 -> 1
A3: =A2+1 -> 2 | B3: Number of active bazaar | C3: =COUNTIFS(Store_Info_VN!D:D,"Open",Store_Info_VN!K:K,"Bazaar") -> 14
A4: =A3+1 -> 3 | B4: Number of active events, private sales | C4: {=SUM(COUNTIFS(Store_Info_VN!D:D,"Open",Store_Info_VN!K:K,{"EVENT","PRIVATE SALE"}))} -> 1
A5: =A4+1 -> 4 | B5: Total (active) | C5: =SUM(C2:C4) -> 16
A6: =A5+1 -> 5 | B6: Existing stores that need to deploy FG-40F | C6: =COUNTIFS(Store_Info_VN!D:D,"Open",Store_Info_VN!L:L,"Need to deploy (FG-40F)") -> 27
A7: =A6+1 -> 6 | B7: Existing stores that need to deploy FG-60F | C7: =COUNTIFS(Store_Info_VN!L:L,"Need to deploy (FG-60F)") -> 0
A8: =A7+1 -> 7 | B8: Extra Details - Number of active Mono stores | C8: =COUNTIFS(Store_Info_VN!D:D,"Open",Store_Info_VN!K:K,"Store") + COUNTIFS(Store_Info_VN!D:D,"Open",Store_Info_VN!K:K,"Mono") -> 0
A9: =A8+1 -> 8 | B9: Extra Details - Number of active SIS stores | C9: =COUNTIFS(Store_Info_VN!D:D,"Open",Store_Info_VN!K:K,"Store") + COUNTIFS(Store_Info_VN!D:D,"Open",Store_Info_VN!K:K,"SIS") -> 1
A10: =A9+1 -> 9 | B10: Stores enabled O2O | C10: =COUNTIFS(Store_Info_VN!D:D,"Open",Store_Info_VN!P:P,"Yes") -> 10

Sheet Summary_Endpoint
A1: Category | B1: Total
A2: VN Office Computers | B2: =COUNTIFS(Asset_Office!J:J,"Laptop")+COUNTIFS(Asset_Office!J:J,"Desktop") -> 103
A3: Completed for VN Office Computers | B3: =COUNTIF(Asset_Office!Y:Y,"DONE") -> 90
A4: Remaining VN Office Computers to unjoin existing domain & change hostname & use OneDrive to store data | B4: =B2-B3 -> 13
A5: VN Office Bazaar Computers | B5: 5
A6: Completed for VN Office Bazaar Computers | B6: 0
A7: Remaining VN Office Bazaar Computers to unjoin existing domain & change hostname & use OneDrive to store data | B7: =B5-B6 -> 5
A8: Cambodia Office Computers | B8: 6
A9: Completed for Cambodia Office Computers | B9: 6
A10: Remaining Cambodia Office Computers to unjoin existing domain & change hostname & use OneDrive to store data | B10: =B8-B9 -> 0

Sheet Asset_Store
A1: No. | B1: Asset ID | C1: Status (formula) | D1: Assigned To (formula) | E1: Description (formula) | F1: Location | G1: Asset Description (formula) | H1: Qty | I1: Asset Type (formula) | J1: Brand | K1: Model | L1: Additional Specs | M1: S/N | N1: RAM (GB) | O1: Hard Disk (GB) | P1: Hard Disk Type | Q1: CPU | R1: Purchase Date | S1: Vendor/Supplier | T1: Note | U1: Assignment History | V1: Old Hostname | W1: Hostname | X1: AD unjoin, change hostname | Y1: Status BIGFIX | Z1: STATUS Crowdstrike | AA1: JOIN DOMAIN
B2: Template | E2: =VLOOKUP(D2,Store_Info_VN!B:P,2,0) -> #N/A | G2: =I2&" "&J2&" "&K2
A3: 1 | B3: 22VN00110001 | C3: Available | D3: KN01 | E3: =VLOOKUP(D3,Store_Info_VN!B:P,2,0) -> BIRKENSTOCK ESTELLA | F3: Store | G3: =I3&" "&J3&" "&K3 -> Desktop HP ProDesk 400 G4 DM | H3: 1 | I3: Desktop | J3: HP | K3: ProDesk 400 G4 DM | M3: 8CC90102Q1 | N3: 8 | O3: 500 | P3: HDD | Q3: 2100 MHz Core i5-8500T | V3: KN01-ADMIN | W3: KN01-ADMIN | X3: DONE | Y3: DONE | Z3: DONE
A4: =A3+1 -> 2 | B4: 22VN00110001 | C4: In Use | D4: VA14 | E4: New Balance Vincom Dong Khoi | F4: Store | G4: HP ProDesk 400 G3 DM | H4: 1 | I4: Desktop | J4: HP | K4: ProDesk 400 G3 DM | M4: 8CG8105N35 | V4: KN01
A5: =A4+1 -> 3 | B5: 22VN00110002 | C5: In Use | D5: VA16 | E5: New Balance Outlet Quang Trung | F5: Store | G5: HP ProDesk 400 G3 DM | H5: 1 | I5: Desktop | J5: HP | K5: ProDesk 400 G3 DM | M5: 8CG8105N1T
A6: 2 | B6: 22VN00110003 | C6: Available | D6: HR Intern | E6: PLANET SPORTS VINCOM DONG KHOI (closed) | F6: Store | G6: =I6&" "&J6&" "&K6 -> Desktop HP ProDesk 400 G4 DM | H6: 1 | I6: Desktop | J6: HP | K6: ProDesk 400 G4 DM | M6: 8CG8105MSL | N6: 8 | O6: 500 | P6: SSD | Q6: 2700 MHz Core i5-7500T | T6: đã thu hồi | U6: IT BACKUP đang cấp Nguyễn Bảo Du InterHR | V6: PO02-Server | W6: PO02-Server | Y6: DONE | Z6: DONE
A7: 5 | B7: 22VN00110006 | C7: Available | D7: VA02 | E7: =VLOOKUP(D7,Store_Info_VN!B:P,2,0) -> NEW BALANCE TAKASHIMAYA | F7: Store | G7: =I7&" "&J7&" "&K7 -> Laptop HP ProBook 440 14 inch G9 Notebook PC | H7: 1 | I7: Laptop | J7: HP | K7: ProBook 440 14 inch G9 Notebook PC | M7: 5CD250F9ZW | N7: 16 | O7: 487749 | P7: SSD | Q7: 2500 MHz 12th Gen Intel Core i5-1235U | T7: Cần tìm lại file scan | V7: VA02-ADMIN | W7: VA02-ADMIN | Y7: DONE | Z7: DONE
A8: 6 | C8: Available | D8: VA02 | E8: =VLOOKUP(D8,Store_Info_VN!B:P,2,0) -> NEW BALANCE TAKASHIMAYA | F8: Store | G8: =I8&" "&J8&" "&K8 -> Bill Printer Epson TM-T82III | H8: 1 | I8: Bill Printer | J8: Epson | K8: TM-T82III | M8: G22EB4602
A9: 7 | C9: Available | D9: VA02 | E9: =VLOOKUP(D9,Store_Info_VN!B:P,2,0) -> NEW BALANCE TAKASHIMAYA | F9: Store | G9: =I9&" "&J9&" "&K9 -> Scanner Datalogic QW2100 | H9: 1 | I9: Scanner | J9: Datalogic | K9: QW2100 | M9: 5CD250F9ZW
A10: 8 | C10: Available | D10: VA02 | E10: =VLOOKUP(D10,Store_Info_VN!B:P,2,0) -> NEW BALANCE TAKASHIMAYA | F10: Store | G10: =I10&" "&J10&" "&K10 -> A4 Printer Canon LBP 2900 | H10: 1 | I10: A4 Printer | J10: Canon | K10: LBP 2900 | M10: NMYA783802
A11: 9 | C11: Available | D11: VA02 | E11: =VLOOKUP(D11,Store_Info_VN!B:P,2,0) -> NEW BALANCE TAKASHIMAYA | F11: Store | G11: =I11&" "&J11&" "&K11 -> USB Kingston 32GB | H11: 1 | I11: USB | J11: Kingston | K11: 32GB
A12: 10 | B12: 22VN00110007 | C12: Available | D12: VA10 | E12: =VLOOKUP(D12,Store_Info_VN!B:P,2,0) -> NEW BALANCE LOTTE HA NOI DEPARTMENT | F12: Store | G12: ư/' | H12: 1 | I12: Laptop | J12: HP | K12: ProBook 440 14 inch G9 Notebook PC | M12: 5CD250F9QZ | N12: 16 | O12: 487757 | P12: SSD | Q12: 2500 MHz 12th Gen Intel Core i5-1235U | V12: VA10-ADMIN | W12: VA10-ADMIN | Y12: DONE | Z12: DONE
A13: 11 | C13: Available | D13: VA10 | E13: =VLOOKUP(D13,Store_Info_VN!B:P,2,0) -> NEW BALANCE LOTTE HA NOI DEPARTMENT | F13: Store | G13: =I13&" "&J13&" "&K13 -> Bill Printer Epson TM-T82III | H13: 1 | I13: Bill Printer | J13: Epson | K13: TM-T82III | M13: X7B9022786
A14: 12 | C14: Available | D14: VA10 | E14: =VLOOKUP(D14,Store_Info_VN!B:P,2,0) -> NEW BALANCE LOTTE HA NOI DEPARTMENT | F14: Store | G14: =I14&" "&J14&" "&K14 -> Scanner Datalogic QW2100 | H14: 1 | I14: Scanner | J14: Datalogic | K14: QW2100 | M14: G22F27244
A15: 13 | C15: Available | D15: VA10 | E15: =VLOOKUP(D15,Store_Info_VN!B:P,2,0) -> NEW BALANCE LOTTE HA NOI DEPARTMENT | F15: Store | G15: =I15&" "&J15&" "&K15 -> A4 Printer Canon LBP 2900 | H15: 1 | I15: A4 Printer | J15: Canon | K15: LBP 2900 | M15: NMYA782038
A16: 14 | C16: Available | D16: VA10 | E16: =VLOOKUP(D16,Store_Info_VN!B:P,2,0) -> NEW BALANCE LOTTE HA NOI DEPARTMENT | F16: Store | G16: =I16&" "&J16&" "&K16 -> USB Kingston | H16: 2 | I16: USB | J16: Kingston
A17: 15 | C17: Available | D17: VA10 | E17: =VLOOKUP(D17,Store_Info_VN!B:P,2,0) -> NEW BALANCE LOTTE HA NOI DEPARTMENT | F17: Store | G17: =I17&" "&J17&" "&K17 -> Mouse HP | H17: 1 | I17: Mouse | J17: HP
A18: 16 | C18: Available | D18: VC01 | E18: =VLOOKUP(D18,Store_Info_VN!B:P,2,0) -> CHAMPION VINCOM DONG KHOI | F18: Store | G18: =I18&" "&J18&" "&K18 -> Monitor HP V190 | H18: 1 | I18: Monitor | J18: HP | K18: V190 | M18: 1CR82307LJ | U18: Trước đó dùng cho VC01 - CHAMPION VINCOM DONG KHOI
A19: 17 | C19: Available | D19: VC01 | E19: =VLOOKUP(D19,Store_Info_VN!B:P,2,0) -> CHAMPION VINCOM DONG KHOI | F19: Store | G19: =I19&" "&J19&" "&K19 -> Bill Printer Epson TM-T82II | H19: 1 | I19: Bill Printer | J19: Epson | K19: TM-T82II | M19: TCCY014794 | U19: Trước đó dùng cho VC01 - CHAMPION VINCOM DONG KHOI
A20: 18 | C20: Available | D20: VR05 | E20: =VLOOKUP(D20,Store_Info_VN!B:P,2,0) -> ROOKIE LOTTE HA NOI DEPARTMENT | F20: Store | G20: =I20&" "&J20&" "&K20 -> Scanner Datalogic QW2100 | H20: 1 | I20: Scanner | J20: Datalogic | K20: QW2100 | M20: G18C39492 | U20: - Trước đó dùng cho VC01 - CHAMPION VINCOM DONG KHOI - Điều chuyển đến VR05
A21: 19 | C21: Available | D21: VC01 | E21: =VLOOKUP(D21,Store_Info_VN!B:P,2,0) -> CHAMPION VINCOM DONG KHOI | F21: Store | G21: =I21&" "&J21&" "&K21 -> Pole Display HP LD220 | H21: 1 | I21: Pole Display | J21: HP | K21: LD220 | M21: 2TD843AAA0 | U21: Trước đó dùng cho VC01 - CHAMPION VINCOM DONG KHOI
A22: 20 | C22: Available | D22: VC01 | E22: =VLOOKUP(D22,Store_Info_VN!B:P,2,0) -> CHAMPION VINCOM DONG KHOI | F22: Store | G22: =I22&" "&J22&" "&K22 | H22: 1 | U22: Trước đó dùng cho VC01 - CHAMPION VINCOM DONG KHOI
A23: 21 | C23: Available | D23: VC01 | E23: =VLOOKUP(D23,Store_Info_VN!B:P,2,0) -> CHAMPION VINCOM DONG KHOI | F23: Store | G23: =I23&" "&J23&" "&K23 | H23: 1 | U23: Trước đó dùng cho VC01 - CHAMPION VINCOM DONG KHOI
A24: 22
A25: 23 | B25: 22VN00000005 | C25: In Use | D25: VN03 | E25: VN03- CONVERSE TAKASHIMAYA | G25: Latitude 3520 | H25: STORE | I25: Dell | J25: Dell | K25: Latitude 3520 | M25: 8P9VKG3 | N25: 8 | O25: 256 | P25: SSD | Q25: 2200 MHz 11th Gen Intel Core i3-1115G4 @ 3.00GHz | T25: BÀN GIAO NGÀY 19-02-2024 CHO STORE CONVERSE TAKASHIMAYA (VN03) | U25: trước đây là laptop cũ của Diễm Quỳnh Accounting, ĐÃ SETUP CHO VN03 (CONVERSE TAKASHIMAYA) | W25: MMA-LAP-0005 | X25: DONE | Y25: DONE | Z25: DONE | AA25: DONE
A26: 24 | C26: Available | D26: VI02 | E26: =VLOOKUP(D26,Store_Info_VN!B:P,2,0) -> SMIGGLE TAKASHIMAYA | F26: Store | G26: =I26&" "&J26&" "&K26 -> Bill Printer Epson TM-T82III | H26: 1 | I26: Bill Printer | J26: Epson | K26: TM-T82III | M26: TCCY011121
A27: 25 | C27: Available | D27: VI02 | E27: =VLOOKUP(D27,Store_Info_VN!B:P,2,0) -> SMIGGLE TAKASHIMAYA | F27: Store | G27: =I27&" "&J27&" "&K27 -> Scanner Datalogic QW2100 | H27: 1 | I27: Scanner | J27: Datalogic | K27: QW2100 | M27: G14MA2902 | T27: THIẾU bbbg máy scan
A28: 3 | B28: 22VN00110004 | C28: In Use | D28: VA05 | E28: NEW BALANCE VINCOM THAO DIEN | F28: Store | G28: =I28&" "&J28&" "&K28 -> Desktop HP ProDesk 400 G4 DM | H28: 1 | I28: Desktop | J28: HP | K28: ProDesk 400 G4 DM | M28: 8CG8105MTN | N28: 8 | O28: 500 | P28: HDD | Q28: 2700 MHz Core i5-7500T | T28: đã thu hồi | U28: IT BACKUP | V28: PO02-POS1 | W28: PO02-POS1 | Y28: DONE | Z28: DONE
A29: 27 | C29: In Use | D29: VA03 | E29: =VLOOKUP(D29,Store_Info_VN!B:P,2,0) -> NEW BALANCE AEON HAI PHONG | F29: Store | G29: =I29&" "&J29&" "&K29 -> Monitor HP V190 | H29: 1 | I29: Monitor | J29: HP | K29: V190 | M29: 1CR82307DL | U29: - Trước đó dùng cho CHAMPION AEON HAI PHONG (VC03)
A30: 28 | C30: In Use | D30: VA03 | E30: =VLOOKUP(D30,Store_Info_VN!B:P,2,0) -> NEW BALANCE AEON HAI PHONG | F30: Store | G30: =I30&" "&J30&" "&K30 -> Bill Printer Epson TM-T82II | H30: 1 | I30: Bill Printer | J30: Epson | K30: TM-T82II | M30: TCEY007587 | U30: - Trước đó dùng cho CHAMPION AEON HAI PHONG (VC03)
A31: 29 | C31: In Use | D31: VA03 | E31: =VLOOKUP(D31,Store_Info_VN!B:P,2,0) -> NEW BALANCE AEON HAI PHONG | F31: Store | G31: =I31&" "&J31&" "&K31 -> Scanner Datalogic QW2100 | H31: 1 | I31: Scanner | J31: Datalogic | K31: QW2100 | M31: G20I34943 | U31: - Trước đó dùng cho CHAMPION AEON HAI PHONG (VC03)
A32: 30 | C32: In Use | D32: VA03 | E32: =VLOOKUP(D32,Store_Info_VN!B:P,2,0) -> NEW BALANCE AEON HAI PHONG | F32: Store | G32: =I32&" "&J32&" "&K32 -> Pole Display Topcash AL-CD1 | H32: 1 | I32: Pole Display | J32: Topcash | K32: AL-CD1 | M32: ALCD20110003 | U32: - Trước đó dùng cho CHAMPION AEON HAI PHONG (VC03)
A33: 31 | C33: Available | D33: IT | E33: Thu hồi từ New Balance Aeon Hai Phong (VA03) | F33: Store | G33: =I33&" "&J33&" "&K33 -> Cash Drawer Poscom 410 | H33: 1 | I33: Cash Drawer | J33: Poscom | K33: 410 | M33: 2020092549 | U33: - Trước đó dùng cho CHAMPION AEON HAI PHONG (VC03)
A34: 32 | C34: In Use | D34: VA03 | E34: =VLOOKUP(D34,Store_Info_VN!B:P,2,0) -> NEW BALANCE AEON HAI PHONG | F34: Store | G34: =I34&" "&J34&" "&K34 -> A4 Printer Canon LBP 2900 | H34: 1 | I34: A4 Printer | J34: Canon | K34: LBP 2900 | M34: NMYA467017 | U34: - Trước đó dùng cho CHAMPION AEON HAI PHONG (VC03)
A35: 33 | B35: 22VN00110011 | C35: In Use | D35: VA23 | E35: =VLOOKUP(D35,Store_Info_VN!B:P,2,0) -> New Balance Lotte Lieu Giai | F35: Store | G35: =I35&" "&J35&" "&K35 -> Laptop Dell Inspiron 3505 | H35: 1 | I35: Laptop | J35: Dell | K35: Inspiron 3505 | M35: HRBPK73 | N35: 6 | O35: 235 | P35: SSD | Q35: 2600 MHz Ryzen 3 3250U with Radeon Graphics | V35: VC04-ADMIN | W35: VC04-ADMIN | Y35: DONE | Z35: DONE
A36: 34 | C36: In Use | D36: VA23 | E36: =VLOOKUP(D36,Store_Info_VN!B:P,2,0) -> New Balance Lotte Lieu Giai | F36: Store | G36: =I36&" "&J36&" "&K36 -> Bill Printer Epson TM-T82III | H36: 1 | I36: Bill Printer | J36: Epson | K36: TM-T82III | M36: X7BA000883
A37: 35 | C37: In Use | D37: VA23 | E37: =VLOOKUP(D37,Store_Info_VN!B:P,2,0) -> New Balance Lotte Lieu Giai | F37: Store | G37: =I37&" "&J37&" "&K37 -> Scanner Datalogic QW2100 | H37: 1 | I37: Scanner | J37: Datalogic | K37: QW2100 | M37: G20L70107 | T37: G20L70107 - IT BACKUP đem đổi mới cho VC04 G22F27150 trước đó cấp cho store bị hư, đã thu hồi
A38: 36 | C38: In Use | D38: VA23 | E38: =VLOOKUP(D38,Store_Info_VN!B:P,2,0) -> New Balance Lotte Lieu Giai | F38: Store | G38: =I38&" "&J38&" "&K38 -> Network Switch Mercusys | H38: 1 | I38: Network Switch | J38: Mercusys | L38: 8 Port | M38: 2201552001975 | T38: STORE LÀM MẤT
A39: 37 | C39: In Use | D39: VA23 | E39: =VLOOKUP(D39,Store_Info_VN!B:P,2,0) -> New Balance Lotte Lieu Giai | F39: Store | G39: =I39&" "&J39&" "&K39 -> A4 Printer Canon LBP 3300 | H39: 1 | I39: A4 Printer | J39: Canon | K39: LBP 3300 | M39: NMYA467026
A40: 4 | B40: 22VN00110005 | C40: Spare | D40: IT BACKUP | E40: PLANET SPORTS VINCOM DONG KHOI (closed) | F40: Store | G40: =I40&" "&J40&" "&K40 -> Desktop HP ProDesk 400 G4 DM | H40: 1 | I40: Desktop | J40: HP | K40: ProDesk 400 G4 DM | M40: 8CG8105MSN | N40: 8 | O40: 500 | P40: HDD | Q40: 2700 MHz Core i5-7500T | T40: đã thu hồi | U40: IT BACKUP | V40: PO02-POS2 | W40: PO02-POS2 | Y40: DONE | Z40: DONE
A41: 39 | B41: 22VN00110013 | C41: Available | D41: VC06 | E41: =VLOOKUP(D41,Store_Info_VN!B:P,2,0) -> PLANET SPORTS GOLDCOAST NHA TRANG | F41: Store | G41: =I41&" "&J41&" "&K41 -> Laptop Dell Inspiron 3505 | H41: 1 | I41: Laptop | J41: Dell | K41: Inspiron 3505 | M41: JS90L73 | N41: 6 | O41: 227320 | P41: SSD | Q41: 2600 MHz Ryzen 3 3250U with Radeon Graphics | V41: VC06-ADMIN | W41: VC06-ADMIN | Y41: DONE | Z41: DONE
A42: 40 | C42: Available | D42: VC06 | E42: =VLOOKUP(D42,Store_Info_VN!B:P,2,0) -> PLANET SPORTS GOLDCOAST NHA TRANG | F42: Store | G42: =I42&" "&J42&" "&K42 -> Bill Printer Epson TM-T82III | H42: 1 | I42: Bill Printer | J42: Epson | K42: TM-T82III | M42: X7BA000891
A43: 41 | C43: Available | D43: VC06 | E43: =VLOOKUP(D43,Store_Info_VN!B:P,2,0) -> PLANET SPORTS GOLDCOAST NHA TRANG | F43: Store | G43: =I43&" "&J43&" "&K43 -> Scanner Datalogic QW2100 | H43: 1 | I43: Scanner | J43: Datalogic | K43: QW2100 | M43: G20L70145
A44: 42 | C44: Available | D44: VC06 | E44: =VLOOKUP(D44,Store_Info_VN!B:P,2,0) -> PLANET SPORTS GOLDCOAST NHA TRANG | F44: Store | G44: =I44&" "&J44&" "&K44 -> Network Switch Mercusys | H44: 1 | I44: Network Switch | J44: Mercusys | L44: 8 Port | M44: 201552001925 | T44: có trên bb nhung không thấy thiết bị vật lý - CHECK LẠI VS STORE
A45: 43 | C45: Available | D45: VC06 | E45: =VLOOKUP(D45,Store_Info_VN!B:P,2,0) -> PLANET SPORTS GOLDCOAST NHA TRANG | F45: Store | G45: =I45&" "&J45&" "&K45 -> A4 Printer Canon LBP 3300 | H45: 1 | I45: A4 Printer | J45: Canon | K45: LBP 3300 | M45: LQHA364224
A46: =A45+1 -> 44 | B46: 22VN00110008 | C46: In Use | D46: VA16 | E46: New Balance Outlet Quang Trung | F46: Store | G46: HP ProDesk 400 G3 DM | H46: 1 | I46: Desktop | J46: HP | K46: ProDesk 400 G3 DM | M46: 8CG8105MSQ
A47: 45 | C47: Available | D47: VC08 | E47: =VLOOKUP(D47,Store_Info_VN!B:P,2,0) -> CHAMPION AEON LONG BIEN | F47: Store | G47: =I47&" "&J47&" "&K47 -> Monitor HP V190 | H47: 1 | I47: Monitor | J47: HP | K47: V190 | M47: 1CR82307CH
A48: 46 | C48: Available | D48: VC08 | E48: =VLOOKUP(D48,Store_Info_VN!B:P,2,0) -> CHAMPION AEON LONG BIEN | F48: Store | G48: =I48&" "&J48&" "&K48 -> Bill Printer Epson TM-T82III | H48: 1 | I48: Bill Printer | J48: Epson | K48: TM-T82III | M48: X7BA003673
A49: 47 | C49: Available | D49: VC08 | E49: =VLOOKUP(D49,Store_Info_VN!B:P,2,0) -> CHAMPION AEON LONG BIEN | F49: Store | G49: =I49&" "&J49&" "&K49 -> Scanner Datalogic QW2100 | H49: 1 | I49: Scanner | J49: Datalogic | K49: QW2100 | M49: G21E85754
A50: 48 | C50: Available | D50: VC08 | E50: =VLOOKUP(D50,Store_Info_VN!B:P,2,0) -> CHAMPION AEON LONG BIEN | F50: Store | G50: =I50&" "&J50&" "&K50 -> Pole Display VFD220U | H50: 1 | I50: Pole Display | K50: VFD220U | M50: 120039
A51: 49 | C51: Available | D51: VC08 | E51: =VLOOKUP(D51,Store_Info_VN!B:P,2,0) -> CHAMPION AEON LONG BIEN | F51: Store | G51: =I51&" "&J51&" "&K51 -> Cash Drawer Antech | H51: 1 | I51: Cash Drawer | J51: Antech | M51: DGAV141220180754
A52: 50 | C52: Available | D52: VC08 | E52: =VLOOKUP(D52,Store_Info_VN!B:P,2,0) -> CHAMPION AEON LONG BIEN | F52: Store | G52: =I52&" "&J52&" "&K52 -> Network Switch Mercusys | H52: 1 | I52: Network Switch | J52: Mercusys | L52: 8 Port | M52: 2201552001923
A53: 51 | C53: Available | D53: VC08 | E53: =VLOOKUP(D53,Store_Info_VN!B:P,2,0) -> CHAMPION AEON LONG BIEN | F53: Store | G53: =I53&" "&J53&" "&K53 -> A4 Printer HP Neverstop Laser 1000w | H53: 1 | I53: A4 Printer | J53: HP | K53: Neverstop Laser 1000w | M53: CNBRP837ZY
A54: 26 | B54: 22VN00110010 | C54: Available | D54: VC03 | E54: =VLOOKUP(D54,Store_Info_VN!B:P,2,0) -> CHAMPION AEON HAI PHONG | F54: Store | G54: =I54&" "&J54&" "&K54 -> Desktop HP ProDesk 400 G3 DM | H54: 1 | I54: Desktop | J54: HP | K54: ProDesk 400 G3 DM | M54: 8CG75206VW | N54: 8 | O54: 500 | P54: SSD | Q54: 2700 MHz Core i5-7500T | T54: đã nâng cấp SSD 500 GB | U54: - Trước đó dùng cho CHAMPION AEON HAI PHONG (VC03) - Hiện tại: IT BACKUP | V54: VC03-ADMIN | W54: VC03-ADMIN | Y54: DONE | Z54: DONE
A55: 53 | C55: Available | D55: VI05 | E55: =VLOOKUP(D55,Store_Info_VN!B:P,2,0) -> SMIGGLE LOTTE HA NOI DEPARTMENT | F55: Store | G55: =I55&" "&J55&" "&K55 -> Monitor HP V193b | H55: 1 | I55: Monitor | J55: HP | K55: V193b | M55: 3CQ54013F6 | T55: ĐÃ THU HỒI , ĐIỀU CHUYỂN VI05-VR05 | U55: - Trước đó dùng cho VE01
A56: =A55+1 -> 54 | C56: Available | D56: VI05 | E56: =VLOOKUP(D56,Store_Info_VN!B:P,2,0) -> SMIGGLE LOTTE HA NOI DEPARTMENT | F56: Store | G56: =I56&" "&J56&" "&K56 -> Bill Printer Epson TM-T82II | H56: 1 | I56: Bill Printer | J56: Epson | K56: TM-T82II | M56: TCEY007558 | T56: ĐÃ THU HỒI, điều chuyển cho VI05 | U56: - Trước đó dùng cho VE01
A57: =A56+1 -> 55 | C57: Available | D57: VI05 | E57: =VLOOKUP(D57,Store_Info_VN!B:P,2,0) -> SMIGGLE LOTTE HA NOI DEPARTMENT | F57: Store | G57: =I57&" "&J57&" "&K57 -> Scanner Datalogic QW2100 | H57: 1 | I57: Scanner | J57: Datalogic | K57: QW2100 | M57: G20I34954 | T57: ĐÃ THU HỒI , ĐIỀU CHUYỂN VI05 | U57: - Trước đó dùng cho VE01
A58: =A57+1 -> 56 | G58: =I58&" "&J58&" "&K58 -> Pole Display Topcash AL-CD1 | H58: 1 | I58: Pole Display | J58: Topcash | K58: AL-CD1 | M58: ALCD20110005 | T58: ĐÃ THU HỒI | U58: - Trước đó dùng cho VE01
A59: =A58+1 -> 57 | G59: =I59&" "&J59&" "&K59 -> Cash Drawer Poscom 410 | H59: 1 | I59: Cash Drawer | J59: Poscom | K59: 410 | T59: ĐÃ THU HỒI | U59: - Trước đó dùng cho VE01
A60: 38 | B60: 22VN00110012 | C60: Available | D60: VC05 | E60: =VLOOKUP(D60,Store_Info_VN!B:P,2,0) -> CHAMPION CRESCENT MALL | F60: Store | G60: =I60&" "&J60&" "&K60 -> Desktop HP ProDesk 400 G3 DM | H60: 1 | I60: Desktop | J60: HP | K60: ProDesk 400 G3 DM | M60: 8CG75234Q7 | N60: 8 | O60: 500 | P60: HDD | Q60: 2700 MHz Core i5-7500T | V60: VC05-ADMIN | W60: VC05-ADMIN | Y60: DONE | Z60: DONE
A61: =A60+1 -> 39 | C61: Available | D61: VE03 | E61: =VLOOKUP(D61,Store_Info_VN!B:P,2,0) -> NEW ERA AEON HA DONG | F61: Store | G61: =I61&" "&J61&" "&K61 -> Bill Printer Epson TM-T82III | H61: 1 | I61: Bill Printer | J61: Epson | K61: TM-T82III | M61: X7BA004103
A62: =A61+1 -> 40 | C62: Available | D62: VE03 | E62: =VLOOKUP(D62,Store_Info_VN!B:P,2,0) -> NEW ERA AEON HA DONG | F62: Store | G62: =I62&" "&J62&" "&K62 -> Monitor Dell | H62: 1 | I62: Monitor | J62: Dell | M62: CN-098W4H---2V8M
A63: =A62+1 -> 41 | C63: Available | D63: VE03 | E63: =VLOOKUP(D63,Store_Info_VN!B:P,2,0) -> NEW ERA AEON HA DONG | F63: Store | G63: =I63&" "&J63&" "&K63 -> Scanner Datalogic QW2100 | H63: 1 | I63: Scanner | J63: Datalogic | K63: QW2100 | M63: G21E85723
A64: =A63+1 -> 42 | C64: Available | D64: VE03 | E64: =VLOOKUP(D64,Store_Info_VN!B:P,2,0) -> NEW ERA AEON HA DONG | F64: Store | G64: =I64&" "&J64&" "&K64 -> Cash Drawer Maken MK410 | H64: 1 | I64: Cash Drawer | J64: Maken | K64: MK410 | M64: MK410210300816
A65: =A64+1 -> 43 | C65: Available | D65: VE03 | E65: =VLOOKUP(D65,Store_Info_VN!B:P,2,0) -> NEW ERA AEON HA DONG | F65: Store | G65: =I65&" "&J65&" "&K65 -> Pole Display VFD220U | H65: 1 | I65: Pole Display | K65: VFD220U | M65: 120034
A66: =A65+1 -> 44 | C66: Available | D66: VE03 | E66: =VLOOKUP(D66,Store_Info_VN!B:P,2,0) -> NEW ERA AEON HA DONG | F66: Store | G66: =I66&" "&J66&" "&K66 -> Network Switch Mercusys | H66: 1 | I66: Network Switch | J66: Mercusys | L66: 8 Port | T66: 8-port Switch
A67: 44 | B67: 22VN00110014 | C67: Available | D67: VC08 | E67: =VLOOKUP(D67,Store_Info_VN!B:P,2,0) -> CHAMPION AEON LONG BIEN | F67: Store | G67: =I67&" "&J67&" "&K67 -> Desktop HP HP 280 G3 MT | H67: 1 | I67: Desktop | J67: HP | K67: HP 280 G3 MT | M67: 4CE7385WV3 | N67: 8 | O67: 1024 | P67: HDD | Q67: 3400 MHz Core i5-7500 | V67: VC08-ADMIN | W67: VC08-ADMIN | Y67: DONE | Z67: DONE
A68: =A67+1 -> 45 | C68: Available | D68: VE04 | E68: =VLOOKUP(D68,Store_Info_VN!B:P,2,0) -> NEW ERA AEON LONG BIEN | F68: Store | G68: =I68&" "&J68&" "&K68 -> Monitor HP V190 | H68: 1 | I68: Monitor | J68: HP | K68: V190 | M68: 1CR8420HDS
A69: =A68+1 -> 46 | C69: Available | D69: VE04 | E69: =VLOOKUP(D69,Store_Info_VN!B:P,2,0) -> NEW ERA AEON LONG BIEN | F69: Store | G69: =I69&" "&J69&" "&K69 -> Bill Printer Epson TM-T82III | H69: 1 | I69: Bill Printer | J69: Epson | K69: TM-T82III | M69: X7BA004104
A70: =A69+1 -> 47 | C70: Available | D70: VE04 | E70: =VLOOKUP(D70,Store_Info_VN!B:P,2,0) -> NEW ERA AEON LONG BIEN | F70: Store | G70: =I70&" "&J70&" "&K70 -> Scanner Datalogic QW2100 | H70: 1 | I70: Scanner | J70: Datalogic | K70: QW2100 | M70: G21E85821
A71: =A70+1 -> 48 | C71: Available | D71: VE04 | E71: =VLOOKUP(D71,Store_Info_VN!B:P,2,0) -> NEW ERA AEON LONG BIEN | F71: Store | G71: =I71&" "&J71&" "&K71 -> Pole Display VFD220U | H71: 1 | I71: Pole Display | K71: VFD220U | M71: 120033
A72: =A71+1 -> 49 | C72: Available | D72: VE04 | E72: =VLOOKUP(D72,Store_Info_VN!B:P,2,0) -> NEW ERA AEON LONG BIEN | F72: Store | G72: =I72&" "&J72&" "&K72 -> Cash Drawer Antech | H72: 1 | I72: Cash Drawer | J72: Antech | M72: DGAV141220180740
A73: =A72+1 -> 50 | C73: Available | D73: VE04 | E73: =VLOOKUP(D73,Store_Info_VN!B:P,2,0) -> NEW ERA AEON LONG BIEN | F73: Store | G73: =I73&" "&J73&" "&K73 -> Network Switch Mercusys | H73: 1 | I73: Network Switch | J73: Mercusys | L73: 8 Port | M73: 2201552001955
A74: =A73+1 -> 51 | B74: 22VN00110018 | C74: Available | D74: VE06 | E74: =VLOOKUP(D74,Store_Info_VN!B:P,2,0) -> NEW ERA DIAMOND PLAZA | F74: Store | G74: =I74&" "&J74&" "&K74 -> Laptop HP ProBook 440 G9 | H74: 1 | I74: Laptop | J74: HP | K74: ProBook 440 G9 | M74: 5CD250F9PD | N74: 16 | O74: 487757 | P74: SSD | Q74: 2500 MHz 12th Gen Intel Core i5-1235U | V74: VE06-ADMIN | W74: VE06-ADMIN | Y74: DONE | Z74: DONE
A75: 52 | B75: 22VN00110015 | C75: Buy by Maison | D75: KN08 | E75: =VLOOKUP(D75,Store_Info_VN!B:P,2,0) -> BIRKEN DIAMOND PLAZA | F75: Store | G75: =I75&" "&J75&" "&K75 -> Desktop HP HP ProDesk 400 G3 DM | H75: 1 | I75: Desktop | J75: HP | K75: HP ProDesk 400 G3 DM | M75: 8CG75234QC | N75: 8 | O75: 500 | P75: HDD | Q75: 2700 MHz Core i5-7500T | T75: ĐÃ THU HỒI, cần nâng SSD | U75: - Trước đó dùng cho VE01 - Hiện tại: IT BACKUP | V75: VE01-ADMIN | W75: VE01-ADMIN | Y75: DONE | Z75: DONE
A76: =A75+1 -> 53 | C76: Available | D76: VF02 | E76: =VLOOKUP(D76,Store_Info_VN!B:P,2,0) -> BIRKENSTOCK VINCOM DONG KHOI | F76: Store | G76: =I76&" "&J76&" "&K76 -> Monitor HP V190 | H76: 1 | I76: Monitor | J76: HP | K76: V190 | M76: 1CR84126GF | U76: Lúc trước dùng cho VF02 - BIRKENSTOCK VINCOM DONG KHOI Đã thu hồi
A77: =A76+1 -> 54 | C77: Available | D77: VF02 | E77: =VLOOKUP(D77,Store_Info_VN!B:P,2,0) -> BIRKENSTOCK VINCOM DONG KHOI | F77: Store | G77: =I77&" "&J77&" "&K77 -> Bill Printer Epson TM-T82II | H77: 1 | I77: Bill Printer | J77: Epson | K77: TM-T82II | M77: TCCYO11123 | U77: Lúc trước dùng cho VF02 - BIRKENSTOCK VINCOM DONG KHOI Đã thu hồi
A78: =A77+1 -> 55 | C78: Available | D78: VF02 | E78: =VLOOKUP(D78,Store_Info_VN!B:P,2,0) -> BIRKENSTOCK VINCOM DONG KHOI | F78: Store | G78: =I78&" "&J78&" "&K78 -> Scanner Datalogic QW2100 | H78: 1 | I78: Scanner | J78: Datalogic | K78: QW2100 | M78: G18C96710 | U78: Lúc trước dùng cho VF02 - BIRKENSTOCK VINCOM DONG KHOI Đã thu hồi
A79: =A78+1 -> 56 | C79: Available | D79: VF02 | E79: =VLOOKUP(D79,Store_Info_VN!B:P,2,0) -> BIRKENSTOCK VINCOM DONG KHOI | F79: Store | G79: =I79&" "&J79&" "&K79 -> Pole Display HP LD220 | H79: 1 | I79: Pole Display | J79: HP | K79: LD220 | M79: 2TD819AAEJ | U79: Lúc trước dùng cho VF02 - BIRKENSTOCK VINCOM DONG KHOI Đã thu hồi
A80: =A79+1 -> 57 | C80: Available | D80: VF02 | E80: =VLOOKUP(D80,Store_Info_VN!B:P,2,0) -> BIRKENSTOCK VINCOM DONG KHOI | F80: Store | G80: =I80&" "&J80&" "&K80 -> Cash Drawer Antech | H80: 1 | I80: Cash Drawer | J80: Antech | U80: Lúc trước dùng cho VF02 - BIRKENSTOCK VINCOM DONG KHOI Đã thu hồi
A81: =A80+1 -> 58 | C81: Available | D81: VF02 | E81: =VLOOKUP(D81,Store_Info_VN!B:P,2,0) -> BIRKENSTOCK VINCOM DONG KHOI | F81: Store | G81: =I81&" "&J81&" "&K81 -> Network Switch D-Link | H81: 1 | I81: Network Switch | J81: D-Link | L81: 24 Port | U81: Lúc trước dùng cho VF02 - BIRKENSTOCK VINCOM DONG KHOI Đã thu hồi
A82: =A81+1 -> 59 | C82: Available | D82: VF02 | E82: =VLOOKUP(D82,Store_Info_VN!B:P,2,0) -> BIRKENSTOCK VINCOM DONG KHOI | F82: Store | G82: =I82&" "&J82&" "&K82 -> Network Switch Mercusys | H82: 1 | I82: Network Switch | J82: Mercusys | L82: 8 Port | M82: 22172w5002268 | U82: Lúc trước dùng cho VF02 - BIRKENSTOCK VINCOM DONG KHOI Đã thu hồi
A83: =A82+1 -> 60 | C83: Available | D83: VF02 | E83: =VLOOKUP(D83,Store_Info_VN!B:P,2,0) -> BIRKENSTOCK VINCOM DONG KHOI | F83: Store | G83: =I83&" "&J83&" "&K83 -> A4 Printer HP LaserJet | H83: 1 | I83: A4 Printer | J83: HP | K83: LaserJet | M83: VNC3K04690 | U83: Lúc trước dùng cho VF02 - BIRKENSTOCK VINCOM DONG KHOI Đã thu hồi
A84: =A83+1 -> 61 | C84: Available | D84: Operations | E84: Operations | G84: =I84&" "&J84&" "&K84 -> Music Box MEDIA BOSE | H84: 1 | I84: Music Box | K84: MEDIA BOSE | U84: Lúc trước dùng cho VF02 - BIRKENSTOCK VINCOM DONG KHOI Đã thu hồi
A85: =A84+1 -> 62 | C85: Available | D85: VF02 | E85: =VLOOKUP(D85,Store_Info_VN!B:P,2,0) -> BIRKENSTOCK VINCOM DONG KHOI | F85: Store | G85: =I85&" "&J85&" "&K85 -> USB Hub Orico | H85: 1 | I85: USB Hub | J85: Orico | U85: Lúc trước dùng cho VF02 - BIRKENSTOCK VINCOM DONG KHOI Đã thu hồi
A86: =A85+1 -> 63 | C86: Available | D86: VF02 | E86: =VLOOKUP(D86,Store_Info_VN!B:P,2,0) -> BIRKENSTOCK VINCOM DONG KHOI | F86: Store | G86: =I86&" - "&J86&" "&K86 -> Other - Patch Panel | H86: 1 | I86: Other | K86: Patch Panel | U86: Lúc trước dùng cho VF02 - BIRKENSTOCK VINCOM DONG KHOI Đã thu hồi
A87: =A86+1 -> 64 | B87: 22VN00110020 | C87: Available | D87: VI01 | E87: =VLOOKUP(D87,Store_Info_VN!B:P,2,0) -> SMIGGLE ROBINS CRESCENT MALL | F87: Store | G87: =I87&" "&J87&" "&K87 -> Laptop Lenovo Lenovo 81FV | H87: 1 | I87: Laptop | J87: Lenovo | K87: Lenovo 81FV | M87: PF1MDA7C | N87: 8 | O87: 1075228 | P87: HDD | Q87: 2200 MHz Core i7-8750H | V87: VI01_ADMIN | W87: VI01_ADMIN | Y87: DONE | Z87: DONE
A88: =A87+1 -> 65 | B88: 22VN00110016 | C88: Available | D88: VE03 | E88: =VLOOKUP(D88,Store_Info_VN!B:P,2,0) -> NEW ERA AEON HA DONG | F88: Store | G88: =I88&" "&J88&" "&K88 -> Desktop HP HP ProDesk 400 G3 MT | H88: 1 | I88: Desktop | J88: HP | K88: HP ProDesk 400 G3 MT | M88: SGH649PK2B | N88: 8 | O88: 500 | P88: HDD | Q88: 3200 MHz Core i5-6500 | V88: VE03-ADMIN | W88: VE03-ADMIN | Y88: DONE | Z88: DONE
A89: =A88+1 -> 66 | B89: 22VN00110022 | C89: In Use | D89: VN19 VI04 | E89: CONVERSE & SMIGGLE GOLDCOAST NHA TRANG | F89: Store | G89: =I89&" "&J89&" "&K89 -> Laptop HP Dell Latitude 3520 | H89: 1 | I89: Laptop | J89: HP | K89: Dell Latitude 3520 | M89: CND53878ZC | N89: 12 | O89: 476416 | P89: SSD | Q89: 2200 MHz Core i5-5200U | T89: S/N: 61RXKS3??? HP ProBook 440 G2 đã thu hồi (CND53878ZC)??? | V89: VI04-VN19ADMIN | W89: VI04-VN19ADMIN | Y89: DONE | Z89: DONE
A90: =A89+1 -> 67 | C90: In Use | D90: VN19 VI04 | E90: CONVERSE & SMIGGLE GOLDCOAST NHA TRANG | F90: Store | G90: =I90&" "&J90&" "&K90 -> Bill Printer Epson TM-T82III | H90: 1 | I90: Bill Printer | J90: Epson | K90: TM-T82III | M90: X7BA002775
A91: =A90+1 -> 68 | C91: In Use | D91: VN19 VI04 | E91: CONVERSE & SMIGGLE GOLDCOAST NHA TRANG | F91: Store | G91: =I91&" "&J91&" "&K91 -> Scanner Datalogic QW2100 | H91: 1 | I91: Scanner | J91: Datalogic | K91: QW2100 | M91: G21M82726 | T91: KHO IT G21M82786
A92: =A91+1 -> 69 | C92: In Use | D92: VN19 VI04 | E92: CONVERSE & SMIGGLE GOLDCOAST NHA TRANG | F92: Store | G92: =I92&" "&J92&" "&K92 -> Mouse Logitech M185 | H92: 1 | I92: Mouse | J92: Logitech | K92: M185 | M92: 215LZ0428
A93: =A92+1 -> 70 | B93: 22VN00110023 | C93: Available | D93: VI06 | E93: =VLOOKUP(D93,Store_Info_VN!B:P,2,0) -> SMIGGLE VAN HANH MALL | F93: Store | G93: =I93&" "&J93&" "&K93 -> Laptop HP ProBook 440 14 inch G9 Notebook PC | H93: 1 | I93: Laptop | J93: HP | K93: ProBook 440 14 inch G9 Notebook PC | M93: 5CD2409YYT | N93: 16 | O93: 487751 | P93: SSD | Q93: 2500 MHz 12th Gen Intel Core i5-1235U | T93: 23/07/2024 bàn giao cho a Tuấn (ZV14) | V93: VI06-ADMIN | W93: VI06-ADMIN | Y93: DONE | Z93: DONE
A94: =A93+1 -> 71 | B94: 22VN00110024 | C94: Available | D94: VN01 | E94: =VLOOKUP(D94,Store_Info_VN!B:P,2,0) -> CONVERSE AEON LONG BIEN | F94: Store | G94: =I94&" "&J94&" "&K94 -> Laptop Dell Inspiron 3505 | H94: 1 | I94: Laptop | J94: Dell | K94: Inspiron 3505 | M94: GNWPK73 | N94: 6 | O94: 227319 | P94: SSD | Q94: 2600 MHz Ryzen 3 3250U with Radeon Graphics | V94: VN01-ADMIN | W94: VN01-ADMIN | Y94: DONE | Z94: DONE
A95: =A94+1 -> 72 | C95: Available | D95: VN01 | E95: =VLOOKUP(D95,Store_Info_VN!B:P,2,0) -> CONVERSE AEON LONG BIEN | F95: Store | G95: =I95&" "&J95&" "&K95 -> Bill Printer Epson TM-T82III | H95: 1 | I95: Bill Printer | J95: Epson | K95: TM-T82III | M95: X7BA000887
A96: =A95+1 -> 73 | C96: Available | D96: VN01 | E96: =VLOOKUP(D96,Store_Info_VN!B:P,2,0) -> CONVERSE AEON LONG BIEN | F96: Store | G96: =I96&" "&J96&" "&K96 -> Scanner Datalogic QW2100 | H96: 1 | I96: Scanner | J96: Datalogic | K96: QW2100 | M96: G20L70063
A97: =A96+1 -> 74 | C97: Available | D97: VN01 | E97: =VLOOKUP(D97,Store_Info_VN!B:P,2,0) -> CONVERSE AEON LONG BIEN | F97: Store | G97: =I97&" "&J97&" "&K97 -> Pole Display Topcash AL-CD1 | H97: 1 | I97: Pole Display | J97: Topcash | K97: AL-CD1 | M97: ALCD20110008 | T97: Biên bản VN01 sai serial > IN LẠI BBBG
A98: =A97+1 -> 75 | C98: Available | D98: VN01 | E98: =VLOOKUP(D98,Store_Info_VN!B:P,2,0) -> CONVERSE AEON LONG BIEN | F98: Store | G98: =I98&" "&J98&" "&K98 -> Cash Drawer Poscom 410 | H98: 1 | I98: Cash Drawer | J98: Poscom | K98: 410 | M98: 20201130040
A99: =A98+1 -> 76 | C99: Available | D99: VN01 | E99: =VLOOKUP(D99,Store_Info_VN!B:P,2,0) -> CONVERSE AEON LONG BIEN | F99: Store | G99: =I99&" "&J99&" "&K99 -> A4 Printer Canon LBP 2900 | H99: 1 | I99: A4 Printer | J99: Canon | K99: LBP 2900 | M99: NMYA467073
A100: =A99+1 -> 77 | C100: Available | D100: VN01 | E100: =VLOOKUP(D100,Store_Info_VN!B:P,2,0) -> CONVERSE AEON LONG BIEN | F100: Store | G100: =I100&" "&J100&" "&K100 -> Network Switch Mercusys | H100: 1 | I100: Network Switch | J100: Mercusys | L100: 8 Port | M100: 2201552001939
...

Sheet Asset_Office
A1: No. | B1: Asset ID | C1: Status (formula) | D1: Assigned To (formula) | E1: Description (formula) | F1: Hostname | G1: AD User (formula) | H1: Location | I1: Asset Name (formula) | J1: Asset Type (formula) | K1: Brand | L1: Model | M1: S/N | N1: RAM (GB) | O1: Hard Disk (GB) | P1: Hard Disk Type | Q1: CPU | R1: Purchase Date | S1: Vendor/Supplier | T1: Note | V1: Assignment History | W1: USB TOKEN | X1: Old Hostname | Y1: AD unjoin, change hostname | Z1: PASTE ASSET ID | AA1: Status BIGFIX | AB1: STATUS Crowdstrike | AC1: STATUS JOIN DOMAIN
A2: 1 | B2: 22VN00000001 | C2: In Use | D2: =VLOOKUP(B2,VN_Emails!B:H,4,0) -> Tiet Nha Phung | E2: =VLOOKUP(B2,VN_Emails!B:H,7,0) -> Brand Manager (Converse) | F2: AMMAVNAMC000001 | G2: =SUBSTITUTE(VLOOKUP(B2,VN_Emails!B:H,2,0),"@mapactive.vn","") -> phung.tietnha | H2: Office | I2: =J2&" "&K2&" "&L2 -> Laptop HP Latitude 7420 | J2: Laptop | K2: HP | L2: Latitude 7420 | M2: DVV62J3 | N2: 16 | O2: 512 | P2: SSD | Q2: 1700 MHz 11th Gen Intel Core i7-1165G7 @ 2.80GHz | X2: MMA-LAP-0001 | Y2: DONE | Z2: DONE | AA2: DONE | AB2: DONE | AC2: Created it.active local account
A3: =A2+1 -> 2 | B3: 22VN00000002 | C3: In Use | D3: =VLOOKUP(B3,VN_Emails!B:H,4,0) -> Doan Thien Ho An | E3: =VLOOKUP(B3,VN_Emails!B:H,7,0) -> Digital Marketing Manager | F3: AMMAVNACC000002 | G3: =SUBSTITUTE(VLOOKUP(B3,VN_Emails!B:H,2,0),"@mapactive.vn","") -> Doan.An | H3: Office | I3: =J3&" "&K3&" "&L3 -> Laptop Dell Latitude 7420 | J3: Laptop | K3: Dell | L3: Latitude 7420 | M3: 124N1J3 | N3: 16 | O3: 512 | P3: SSD | Q3: 1700 MHz 11th Gen Intel Core i7-1165G7 @ 2.80GHz | V3: DANG BH LAPTOP KO LÊN NGUỒN | X3: MMA-LAP-0002 | Y3: Need to do both | Z3: DONE | AA3: DONE | AB3: DONE
A4: =A3+1 -> 3 | B4: 22VN00000003 | C4: Available | D4: =VLOOKUP(B4,VN_Emails!B:H,4,0) -> #N/A | E4: =VLOOKUP(B4,VN_Emails!B:H,7,0) -> #N/A | F4: AMMAVNACC000003 | G4: #N/A | H4: Office | I4: =J4&" "&K4&" "&L4 -> Laptop Dell Latitude 5420 | J4: Laptop | K4: Dell | L4: Latitude 5420 | M4: 1Z8DZH3 | N4: 16 | O4: 512 | P4: SSD | Q4: 1400 MHz 11th Gen Intel Core i5-1135G7 @ 2.40GHz | T4: UPDATE NEW SSD 500GB SAMSUNG | V4: đã bh ssd vs CMCSG samsung 500GB lưu kho IT Lấy ổ cứng SSD đã bảo hành của chị Mai (M.2 SSD - Model A60 - 512GB - S/N: 23027592-050170B) để thay vào laptop Dell Latitude 7420 của chị Uyên Máy cũ chị Maya đã thu hồi 22/01/2024 , Hiếu IT đang giữ | W4: use USB token | X4: MMA-LAP-0003 | Y4: DONE | Z4: DONE | AA4: DONE | AB4: DONE
A5: =A4+1 -> 4 | B5: 22VN00000004 | C5: In Use | D5: =VLOOKUP(B5,VN_Emails!B:H,4,0) -> Nguyen Thi Thuy Mong | E5: =VLOOKUP(B5,VN_Emails!B:H,7,0) -> Senior Brand Marketing Manager | F5: AMMAVNACC000004 | G5: =SUBSTITUTE(VLOOKUP(B5,VN_Emails!B:H,2,0),"@mapactive.vn","") -> mong.nguyenthithuy | H5: Office | I5: =J5&" "&K5&" "&L5 -> Laptop Dell Latitude 5430 | J5: Laptop | K5: Dell | L5: Latitude 5430 | M5: 42X2SQ3 | N5: 8 | O5: 512 | P5: SSD | Q5: 2500 MHz 12th Gen Intel Core i5-1235U | V5: Máy của Danh thỉnh thoảng không lên màn hình | X5: MMA-LAP-0004 | Y5: DONE | Z5: DONE | AA5: DONE | AB5: DONE
A6: =A5+1 -> 5 | B6: 22VN00000006 | C6: In Use | D6: =VLOOKUP(B6,VN_Emails!B:H,4,0) -> Le Hong Bao Chau | E6: =VLOOKUP(B6,VN_Emails!B:H,7,0) -> Marketing Admin | F6: AMMAVNACC000006 | G6: =SUBSTITUTE(VLOOKUP(B6,VN_Emails!B:H,2,0),"@mapactive.vn","") -> chau.lehongbao | H6: Office | I6: =J6&" "&K6&" "&L6 -> Laptop Dell Latitude 3520 | J6: Laptop | K6: Dell | L6: Latitude 3520 | M6: 5R4JGL3 | N6: 8 | O6: 256 | P6: SSD | Q6: 1400 MHz 11th Gen Intel Core i5-1135G7 @ 2.40GHz | V6: old laptop Nguyen Hoang Anh Thy Accounting, IT thu hồi 21-02-2024 | X6: AMMAVNACC000006 | Y6: DONE | Z6: DONE | AA6: DONE | AB6: DONE
A7: =A6+1 -> 6 | B7: 22VN00000007 | C7: In Use | D7: =VLOOKUP(B7,VN_Emails!B:H,4,0) -> #N/A | E7: =VLOOKUP(B7,VN_Emails!B:H,7,0) -> #N/A | F7: AMMAVNACCC000007 | G7: =SUBSTITUTE(VLOOKUP(B7,VN_Emails!B:H,2,0),"@mapactive.vn","") -> #N/A | H7: Office | I7: =J7&" "&K7&" "&L7 -> Laptop Dell Latitude 3420 | J7: Laptop | K7: Dell | L7: Latitude 3420 | M7: 65G48S3 | N7: 16 | O7: 512 | P7: SSD | Q7: 1400 MHz 11th Gen Intel Core i5-1135G7 @ 2.40GHz | X7: MMA-LAP-0007 | Y7: DONE | Z7: DONE | AA7: DONE | AB7: DONE
A8: =A7+1 -> 7 | B8: 22VN00000008 | C8: Available | D8: =VLOOKUP(B8,VN_Emails!B:H,4,0) -> #N/A | E8: =VLOOKUP(B8,VN_Emails!B:H,7,0) -> #N/A | F8: AMMAVNACC000008 | G8: =SUBSTITUTE(VLOOKUP(B8,VN_Emails!B:H,2,0),"@mapactive.vn","") -> #N/A | H8: Office | I8: =J8&" "&K8&" "&L8 -> Laptop Dell Latitude 3520 | J8: Laptop | K8: Dell | L8: Latitude 3520 | M8: 2P8VKG3 | N8: 8 | O8: 512 | P8: SSD | Q8: 1400 MHz 11th Gen Intel Core i3-1135G7 @ 2.40GHz | W8: use USB token | X8: MMA-LAP-0008 | Y8: DONE | Z8: DONE | AA8: DONE | AB8: DONE
A9: =A8+1 -> 8 | B9: 22VN00000009 | C9: In Use | D9: =VLOOKUP(B9,VN_Emails!B:H,4,0) -> Le Cam Linh | E9: =VLOOKUP(B9,VN_Emails!B:H,7,0) -> Shipping Supervisor | F9: AMMAVNLOC000009 | G9: =SUBSTITUTE(VLOOKUP(B9,VN_Emails!B:H,2,0),"@mapactive.vn","") -> linh.lecam | H9: Office | I9: =J9&" "&K9&" "&L9 -> Laptop Dell Latitude 5430 | J9: Laptop | K9: Dell | L9: Latitude 5430 | M9: 1583SQ3 | N9: 20 | O9: 512 | P9: SSD | Q9: 2500 MHz 12th Gen Intel Core i5-1235U | X9: MMA-LAP-0009 | Y9: DONE | AA9: DONE | AB9: DONE
A10: =A9+1 -> 9 | B10: 22VN00000010 | C10: Available | D10: =VLOOKUP(B10,VN_Emails!B:H,4,0) -> #N/A | E10: =VLOOKUP(B10,VN_Emails!B:H,7,0) -> #N/A | F10: AMMAVNROC000010 | G10: =SUBSTITUTE(VLOOKUP(B10,VN_Emails!B:H,2,0),"@mapactive.vn","") -> #N/A | H10: Office | I10: =J10&" "&K10&" "&L10 -> Laptop Dell Latitude 3520 | J10: Laptop | K10: Dell | L10: Latitude 3520 | M10: 4Q9VKG3 | N10: 8 | O10: 256 | P10: SSD | Q10: 2200 MHz 11th Gen Intel Core i3-1115G4 @ 3.00GHz | V10: Máy Mỹ TRang cũ | X10: MMA-LAP-0010 | Y10: DONE | Z10: DONE | AA10: DONE | AB10: DONE
A11: =A10+1 -> 10 | B11: 22VN00000011 | C11: Available | D11: =VLOOKUP(B11,VN_Emails!B:H,4,0) -> #N/A | E11: =VLOOKUP(B11,VN_Emails!B:H,7,0) -> #N/A | F11: AMMAVNMDC000011 | G11: =SUBSTITUTE(VLOOKUP(B11,VN_Emails!B:H,2,0),"@mapactive.vn","") -> #N/A | H11: Office | I11: =J11&" "&K11&" "&L11 -> Laptop Dell Latitude 5430 | J11: Laptop | K11: Dell | L11: Latitude 5430 | M11: F083SQ3 | N11: 16 | O11: 512 | P11: SSD | Q11: 2500 MHz 12th Gen Intel Core i5-1235U | V11: SỬ DỤNG MÁY 5430 CỦA LƯU GIANG CẨM VÂN(VICKY) ĐÃ THAY SSD BỊ HƯ TỪ CMC (LẦN 1) CHỜ CỨU DATA TỪ SÓNG NAM SAU ĐÓ BH SSD VS CMC(SAU TẾT) CMC ĐÃ GỬI LẠI SSD MỚI NGÀY 08/03/2024 | X11: MMA-LAP-0011 | Y11: DONE | Z11: DONE | AA11: DONE | AB11: DONE
A12: =A11+1 -> 11 | B12: 22VN00000012 | C12: Available | D12: =VLOOKUP(B12,VN_Emails!B:H,4,0) -> #N/A | E12: =VLOOKUP(B12,VN_Emails!B:H,7,0) -> #N/A | G12: =SUBSTITUTE(VLOOKUP(B12,VN_Emails!B:H,2,0),"@mapactive.vn","") -> #N/A | H12: Office | I12: =J12&" "&K12&" "&L12 -> Laptop Dell Latitude 3520 | J12: Laptop | K12: Dell | L12: Latitude 3520 | M12: BR9VKG3 | N12: 8 | O12: 256 | P12: SSD | Q12: 2200 MHz 11th Gen Intel Core i3-1115G4 @ 3.00GHz | T12: Máy lỗi loa user binh.ngotieu 16/05/24, Cấp tạm cho Lan Vy Cấp ZV16 26/08/2024 | X12: MMA-LAP-0012 | Y12: DONE | Z12: DONE | AA12: DONE | AB12: DONE
A13: =A12+1 -> 12 | B13: 22VN00000013 | C13: In Use | D13: =VLOOKUP(B13,VN_Emails!B:H,4,0) -> Tran Thi Yen Nhi | E13: =VLOOKUP(B13,VN_Emails!B:H,7,0) -> Payroll & Em. Servieces Executive | F13: AMMAVNHRC000013 | G13: =SUBSTITUTE(VLOOKUP(B13,VN_Emails!B:H,2,0),"@mapactive.vn","") -> nhi.tranthiyen | H13: Office | I13: =J13&" "&K13&" "&L13 -> Laptop HP Pavilion 15-eg0xxx | J13: Laptop | K13: HP | L13: Pavilion 15-eg0xxx | M13: 5CD1294NHX | N13: 8 | O13: 512 | P13: SSD | Q13: 2400 MHz 11th Gen Intel Core i5-1135G7 @ 2.40GHz | W13: use USB token | X13: MMA-LAP-0013 | Y13: DONE | Z13: DONE | AA13: DONE | AB13: DONE
A14: =A13+1 -> 13 | B14: 22VN00000014 | C14: In Use | D14: =VLOOKUP(B14,VN_Emails!B:H,4,0) -> Ni Ksormahhko | E14: =VLOOKUP(B14,VN_Emails!B:H,7,0) -> Procurement Executive | F14: AMMAVNPUC000014 | G14: =SUBSTITUTE(VLOOKUP(B14,VN_Emails!B:H,2,0),"@mapactive.vn","") -> ni.ksormahhko | H14: Office | I14: =J14&" "&K14&" "&L14 -> Laptop Dell Latitude 3520 | J14: Laptop | K14: Dell | L14: Latitude 3520 | M14: BKY5FX3 | N14: 8 | O14: 256 | P14: SSD | Q14: 11TH Gen Intel ® Core™ i5-1135G7 @2.40Ghz | X14: MMA-LAP-0014 | Y14: DONE | Z14: DONE | AA14: DONE | AB14: DONE
A15: =A14+1 -> 14 | B15: 22VN00000015 | C15: In Use | D15: =VLOOKUP(B15,VN_Emails!B:H,4,0) -> Huynh Tuan Nhan | E15: =VLOOKUP(B15,VN_Emails!B:H,7,0) -> SCM Manager | F15: AMMAVNLOC000015 | G15: =SUBSTITUTE(VLOOKUP(B15,VN_Emails!B:H,2,0),"@mapactive.vn","") -> nhan.huynhtuan | H15: Office | I15: =J15&" "&K15&" "&L15 -> Laptop Dell Latitude 5430 | J15: Laptop | K15: Dell | L15: Latitude 5430 | M15: 13D4SQ3 | N15: 16 | O15: 512 | P15: SSD | Q15: 2500 MHz 12th Gen Intel Core i5-1235U | X15: MMA-LAP-0015 | Y15: DONE | Z15: DONE | AA15: DONE | AB15: DONE
A16: =A15+1 -> 15 | B16: 22VN00000016 | C16: Available | D16: =VLOOKUP(B16,VN_Emails!B:H,4,0) -> #N/A | E16: =VLOOKUP(B16,VN_Emails!B:H,7,0) -> #N/A | F16: AMMAVNLOC000016 | G16: =SUBSTITUTE(VLOOKUP(B16,VN_Emails!B:H,2,0),"@mapactive.vn","") -> #N/A | H16: Office | I16: =J16&" "&K16&" "&L16 -> Laptop Dell Latitude 3520 | J16: Laptop | K16: Dell | L16: Latitude 3520 | M16: 99C2LG3 | N16: 12 | O16: 512 | P16: SSD | Q16: 2200 MHz 11th Gen Intel Core i3-1115G4 @ 3.00GHz | T16: Nâng 4gb Ram và 256GB SSD | X16: MMA-LAP-0016 | Y16: DONE | Z16: DONE | AA16: DONE | AB16: DONE
A17: =A16+1 -> 16 | B17: 22VN00000017 | C17: Available | D17: =VLOOKUP(B17,VN_Emails!B:H,4,0) -> #N/A | E17: =VLOOKUP(B17,VN_Emails!B:H,7,0) -> #N/A | F17: AMMAVNWHC000017 | G17: =SUBSTITUTE(VLOOKUP(B17,VN_Emails!B:H,2,0),"@mapactive.vn","") -> #N/A | H17: Office | I17: =J17&" "&K17&" "&L17 -> Laptop Dell Latitude 3520 | J17: Laptop | K17: Dell | L17: Latitude 3520 | M17: JP8VKG3 | N17: 16 | O17: 256 | P17: SSD | Q17: 2200 MHz 11th Gen Intel Core i3-1115G4 @ 3.00GHz | X17: MMA-LAP-0017 | Y17: DONE | Z17: DONE | AA17: DONE | AB17: DONE
A18: =A17+1 -> 17 | B18: 22VN00000018 | C18: In Use | D18: =VLOOKUP(B18,VN_Emails!B:H,4,0) -> Dang Thanh Nam | E18: =VLOOKUP(B18,VN_Emails!B:H,7,0) -> Warehouse and Distribution Supervisor | F18: AMMAVNWHC000018 | G18: =SUBSTITUTE(VLOOKUP(B18,VN_Emails!B:H,2,0),"@mapactive.vn","") -> nam.dangthanh | H18: Office | I18: =J18&" "&K18&" "&L18 -> Laptop Dell Latitude 3520 | J18: Laptop | K18: Dell | L18: Latitude 3520 | M18: JR9VKG3 | N18: 8 | O18: 256 | P18: SSD | Q18: 2200 MHz 11th Gen Intel Core i3-1115G4 @ 3.00GHz | X18: MMA-LAP-0018 | Y18: DONE | Z18: DONE | AA18: DONE | AB18: DONE
A19: =A18+1 -> 18 | B19: 22VN00000019 | C19: Available | E19: =VLOOKUP(B19,VN_Emails!B:H,7,0) -> #N/A | F19: AMMAVNLOC000019 | G19: =SUBSTITUTE(VLOOKUP(B19,VN_Emails!B:H,2,0),"@mapactive.vn","") -> #N/A | H19: Office | I19: =J19&" "&K19&" "&L19 -> Laptop Dell Latitude 3520 | J19: Laptop | K19: Dell | L19: Latitude 3520 | M19: FQ8VKG3 | N19: 8 | O19: 256 | P19: SSD | Q19: 2200 MHz 11th Gen Intel Core i3-1115G4 @ 3.00GHz | X19: MMA-LAP-0019 | Y19: DONE | Z19: DONE | AA19: DONE | AB19: DONE
A20: =A19+1 -> 19 | B20: 22VN00000020 | C20: In Use | D20: Quan Thanh Them | E20: =VLOOKUP(B20,VN_Emails!B:H,7,0) -> COE Manager | F20: AMMAVNCEC000020 | G20: =SUBSTITUTE(VLOOKUP(B20,VN_Emails!B:H,2,0),"@mapactive.vn","") -> them.quanthanh | H20: Office | I20: =J20&" "&K20&" "&L20 -> Laptop Dell Latitude 5430 | J20: Laptop | K20: Dell | L20: Latitude 5430 | M20: 5BD4SQ3 | N20: 16 | O20: 512 | P20: SSD | Q20: 2500 MHz 12th Gen Intel Core i5-1235U | X20: MMA-LAP-0020 | Y20: DONE | Z20: DONE | AA20: DONE | AB20: DONE
A21: =A20+1 -> 20 | B21: 22VN00000021 | C21: In Use | D21: =VLOOKUP(B21,VN_Emails!B:H,4,0) -> Nguyen Ngoc Xuan Duyen | E21: =VLOOKUP(B21,VN_Emails!B:H,7,0) -> COE Officer | F21: AMMAVNCEC000021 | G21: =SUBSTITUTE(VLOOKUP(B21,VN_Emails!B:H,2,0),"@mapactive.vn","") -> duyen.nguyenngocxuan | H21: Office | I21: =J21&" "&K21&" "&L21 -> Laptop Dell Latitude 3520 | J21: Laptop | K21: Dell | L21: Latitude 3520 | M21: BTN0BG3 | N21: 8 | O21: 256 | P21: SSD | Q21: 2200 MHz 11th Gen Intel Core i3-1115G4 @ 3.00GHz | X21: MMA-LAP-0021 | Y21: DONE | Z21: DONE | AA21: DONE | AB21: DONE
A22: =A21+1 -> 21 | B22: 22VN00000022 | C22: In Use | D22: =VLOOKUP(B22,VN_Emails!B:H,4,0) -> Nguyen Quyet Thang | E22: =VLOOKUP(B22,VN_Emails!B:H,7,0) -> COE Officer | F22: AMMAVNCEC000022 | G22: =SUBSTITUTE(VLOOKUP(B22,VN_Emails!B:H,2,0),"@mapactive.vn","") -> thang.nguyenquyet | H22: Office | I22: =J22&" "&K22&" "&L22 -> Laptop Dell Latitude 3520 | J22: Laptop | K22: Dell | L22: Latitude 3520 | M22: DP8VKG3 | N22: 8 | O22: 256 | P22: SSD | Q22: 2200 MHz 11th Gen Intel Core i3-1115G4 @ 3.00GHz | V22: LE MINH KHANG OLD LAPTOP (COE Officer) resigned 29-01-2024 - 25/03/2024 handover for Tạ Quỳnh Trang -16/07/2024 handover for Trần Hồ Duy Tân | X22: MMA-LAP-0022 | Y22: DONE | Z22: DONE | AA22: DONE | AB22: DONE
A23: =A22+1 -> 22 | B23: 22VN00000023 | C23: In Use | D23: =VLOOKUP(B23,VN_Emails!B:H,4,0) -> Nguyen Bao Du | E23: =VLOOKUP(B23,VN_Emails!B:H,7,0) -> HR Internship | F23: AMMAVNCEC000023 | G23: =SUBSTITUTE(VLOOKUP(B23,VN_Emails!B:H,2,0),"@mapactive.vn","") -> du.nguyenbao | H23: Office | I23: =J23&" "&K23&" "&L23 -> Laptop Dell Latitude 3520 | J23: Laptop | K23: Dell | L23: Latitude 3520 | M23: 6S4JGL3 | N23: 8 | O23: 256 | P23: SSD | Q23: 1400 MHz 11th Gen Intel Core i5-1135G7 @ 2.40GHz | V23: - Tran Dang Anh Khoa (COE Officer) resigned - Cấp tạm cho DƯƠNG QUANG MINH TUẤN THAY cho HỒ HẢI ĐĂNG AM IT ĐÃ THU HỒI 30-01-24 | W23: DISABLE | X23: MMA-LAP-0023 | Y23: DONE | Z23: DONE | AA23: DONE | AB23: DONE | AC23: DONE
A24: =A23+1 -> 23 | B24: 22VN00000024 | C24: Available | D24: =VLOOKUP(B24,VN_Emails!B:H,4,0) -> #N/A | E24: =VLOOKUP(B24,VN_Emails!B:H,7,0) -> #N/A | F24: AMMAVNICC000024 | G24: =SUBSTITUTE(VLOOKUP(B24,VN_Emails!B:H,2,0),"@mapactive.vn","") -> #N/A | H24: Office | I24: =J24&" "&K24&" "&L24 -> Laptop Dell Latitude 3520 | J24: Laptop | K24: Dell | L24: Latitude 3520 | M24: 4R9VKG3 | N24: 8 | O24: 256 | P24: SSD | Q24: 2200 MHz 11th Gen Intel Core i3-1115G4 @ 3.00GHz | X24: MMA-LAP-0024 | Y24: DONE | Z24: DONE | AA24: DONE | AB24: DONE
A25: =A24+1 -> 24 | B25: 22VN00000025 | C25: In Use | D25: =VLOOKUP(B25,VN_Emails!B:H,4,0) -> Luong Huu Quan | E25: =VLOOKUP(B25,VN_Emails!B:H,7,0) -> IT Infrastructure & Operations Supervisor | F25: AMMAVNITC000025 | G25: =SUBSTITUTE(VLOOKUP(B25,VN_Emails!B:H,2,0),"@mapactive.vn","") -> quan.luonghuu | H25: Office | I25: =J25&" "&K25&" "&L25 -> Laptop Dell Latitude 5430 | J25: Laptop | K25: Dell | L25: Latitude 5430 | M25: FGF3SQ3 | N25: 16 | O25: 512 | P25: SSD | Q25: 2500 MHz 12th Gen Intel Core i5-1235U | X25: MMA-LAP-0025 | Y25: DONE | Z25: DONE | AA25: DONE | AB25: DONE
A26: =A25+1 -> 25 | B26: 22VN00000026 | C26: Available | D26: IT BACKUP | E26: =VLOOKUP(B26,VN_Emails!B:H,7,0) -> #N/A | F26: AMMAVNITC000026 | G26: =SUBSTITUTE(VLOOKUP(B26,VN_Emails!B:H,2,0),"@mapactive.vn","") -> #N/A | H26: Office | I26: =J26&" "&K26&" "&L26 -> Laptop HP ProBook 440 G4 | J26: Laptop | K26: HP | L26: ProBook 440 G4 | M26: 5CD73626Y5 | N26: 16 | O26: 256 | P26: SSD | Q26: 2700 MHz Core i5-7200U | T26: anh.nguyenphamduy resigned 20/05/2024 | V26: -Dat.tranquoc (IT Officer) resigned 11/3/2024 | X26: MMA-LAP-0026 | Y26: DONE | Z26: DONE | AA26: DONE | AB26: DONE | AC26: DONE
A27: =A26+1 -> 26 | B27: 22VN00000027 | C27: In Use | D27: =VLOOKUP(B27,VN_Emails!B:H,4,0) -> Huynh My Danh | E27: =VLOOKUP(B27,VN_Emails!B:H,7,0) -> FP&A Supervisor | F27: AMMAVNMRC000027 | G27: =SUBSTITUTE(VLOOKUP(B27,VN_Emails!B:H,2,0),"@mapactive.vn","") -> danh.huynhmy | H27: Office | I27: =J27&" "&K27&" "&L27 -> Laptop Dell Latitude 5420 | J27: Laptop | K27: Dell | L27: Latitude 5420 | M27: HRQCZH3 | N27: 8 | O27: 512 | P27: SSD | Q27: 1400 MHz 11th Gen Intel Core i5-1135G7 @ 2.40GHz | X27: MMA-LAP-0027 | Y27: DONE | Z27: DONE | AA27: DONE | AB27: DONE
A28: =A27+1 -> 27 | B28: 22VN00000028 | C28: In Use | D28: =VLOOKUP(B28,VN_Emails!B:H,4,0) -> Nghiem Thi Hong Van | E28: =VLOOKUP(B28,VN_Emails!B:H,7,0) -> Senior Merchandise | F28: AMMAVNMDCC000028 | G28: =SUBSTITUTE(VLOOKUP(B28,VN_Emails!B:H,2,0),"@mapactive.vn","") -> van.nghiemthihong | H28: Office | I28: =J28&" "&K28&" "&L28 -> Laptop Dell Latitude 3520 | J28: Laptop | K28: Dell | L28: Latitude 3520 | M28: GN8VKG3 | N28: 12 | O28: 256 | P28: SSD | Q28: 2200 MHz 11th Gen Intel Core i3-1115G4 @ 3.00GHz | T28: BÀN GIAO CHO Nghiêm Thị Hồng Vân – Senior Merchandise – Brand Department – On board 15/10/2023 (nâng 4gb Ram) | V28: MÁY CŨ LÊ TRẦN THIÊN MINH | X28: MMA-LAP-0028 | Y28: DONE | Z28: DONE | AA28: DONE | AB28: DONE
A29: =A28+1 -> 28 | B29: 22VN00000029 | C29: In Use | D29: VA04-ADMIN | E29: =VLOOKUP(B29,VN_Emails!B:H,7,0) -> #N/A | F29: VA04-ADMIN | G29: =SUBSTITUTE(VLOOKUP(B29,VN_Emails!B:H,2,0),"@mapactive.vn","") -> #N/A | H29: Office | I29: =J29&" "&K29&" "&L29 -> Laptop Dell Latitude 3520 | J29: Laptop | K29: Dell | L29: Latitude 3520 | M29: 1P8VKG3 | N29: 8 | O29: 256 | P29: SSD | Q29: 2200 MHz 11th Gen Intel Core i3-1115G4 @ 3.00GHz | T29: Máy cũ Minh (sracecrow) | V29: Pham Thi Bao Tram (MKT) handover Feb-29-2024 Old hostname: AMMAVNMRC000029 | X29: MMA-LAP-0029 | Y29: DONE | Z29: DONE | AA29: DONE | AB29: DONE
A30: =A29+1 -> 29 | B30: 22VN00000030 | C30: Available | E30: =VLOOKUP(B30,VN_Emails!B:H,7,0) -> #N/A | F30: AMMAVNMRC000030 | G30: =SUBSTITUTE(VLOOKUP(B30,VN_Emails!B:H,2,0),"@mapactive.vn","") -> #N/A | H30: Office | I30: =J30&" "&K30&" "&L30 -> Laptop Lenovo Thinkpad X280 | J30: Laptop | K30: Lenovo | L30: Thinkpad X280 | M30: PC133K78 | N30: 8 | O30: 256 | P30: SSD | Q30: 1800 MHz Core i5-8250U | T30: - Replaced keyboard on 20-Aug-2023 cấp cho :Nguyen Thao My 27/11/2023 (replace Phan Thi Thuy Tien) | V30: - Phan Thị Thủy Tiên đã thôi việc ngày 06/10/23 - Huỳnh Thị Bích Ngân – thôi việc ngày 13/10/2023 | X30: MMA-LAP-0030 | Y30: DONE | Z30: DONE | AA30: DONE | AB30: DONE | AC30: DONE
A31: =A30+1 -> 30 | B31: 22VN00000031 | C31: Available | D31: =VLOOKUP(B31,VN_Emails!B:H,4,0) -> #N/A | E31: =VLOOKUP(B31,VN_Emails!B:H,7,0) -> #N/A | F31: AMMAVNMDC000031 | G31: =SUBSTITUTE(VLOOKUP(B31,VN_Emails!B:H,2,0),"@mapactive.vn","") -> #N/A | H31: Office | I31: =J31&" "&K31&" "&L31 -> Laptop Dell Latitude 5420 | J31: Laptop | K31: Dell | L31: Latitude 5420 | M31: 4DBCZH3 | N31: 8 | O31: 512 | P31: SSD\ | Q31: 1400 MHz 11th Gen Intel Core i5-1135G7 @ 2.40GHz | X31: MMA-LAP-0031 | Y31: DONE | Z31: DONE | AA31: DONE | AB31: DONE
A32: =A31+1 -> 31 | B32: 22VN00000032 | C32: In Use | D32: =VLOOKUP(B32,VN_Emails!B:H,4,0) -> Vu Xuan Uyen | E32: =VLOOKUP(B32,VN_Emails!B:H,7,0) -> Marketing officer | F32: AMMAVNLEC000032 | G32: =SUBSTITUTE(VLOOKUP(B32,VN_Emails!B:H,2,0),"@mapactive.vn","") -> uyen.vuxuan | H32: Office | I32: =J32&" "&K32&" "&L32 -> Laptop Dell Latitude 3420 | J32: Laptop | K32: Dell | L32: Latitude 3420 | M32: 6GV7R93 | N32: 8 | O32: 640 | P32: HDD (512 GB) SSD (128 GB) | Q32: 1400 MHz 11th Gen Intel Core i5-1135G7 @ 2.40GHz | T32: Quỳnh MD Bàn giao trả máy ngày 24/08/2023 > Chuyển sang cho Le Thi Kim Hồng (Legal) sử dụng ngày 11/09/2023 | W32: use USB token | X32: MMA-LAP-0032 | Y32: DONE | Z32: DONE | AA32: DONE | AB32: DONE
A33: =A32+1 -> 32 | B33: 22VN00000033 | C33: Available | D33: =VLOOKUP(B33,VN_Emails!B:H,4,0) -> #N/A | E33: =VLOOKUP(B33,VN_Emails!B:H,7,0) -> #N/A | F33: AMMAVNMDC000033 | G33: =SUBSTITUTE(VLOOKUP(B33,VN_Emails!B:H,2,0),"@mapactive.vn","") -> #N/A | H33: Office | I33: =J33&" "&K33&" "&L33 -> Laptop Dell Latitude 3520 | J33: Laptop | K33: Dell | L33: Latitude 3520 | M33: 9P8VKG3 | N33: 8 | O33: 256 | P33: SSD | Q33: 2200 MHz 11th Gen Intel Core i3-1115G4 @ 3.00GHz | X33: MMA-LAP-0033 | Y33: DONE | Z33: DONE | AA33: DONE | AB33: DONE
A34: =A33+1 -> 33 | B34: 22VN00000034 | C34: In Use | D34: =VLOOKUP(B34,VN_Emails!B:H,4,0) -> Tran A giang | E34: =VLOOKUP(B34,VN_Emails!B:H,7,0) -> Intern | F34: AMMAVNMDC000034 | G34: =SUBSTITUTE(VLOOKUP(B34,VN_Emails!B:H,2,0),"@mapactive.vn","") -> giang.trana | H34: Office | I34: =J34&" "&K34&" "&L34 -> Laptop Dell Latitude 3520 | J34: Laptop | K34: Dell | L34: Latitude 3520 | M34: DGBJGL3 | N34: 8 | O34: 256 | P34: SSD | Q34: 1400 MHz 11th Gen Intel Core i5-1135G7 @ 2.40GHz | X34: MMA-LAP-0034 | Y34: DONE | Z34: DONE | AA34: DONE | AB34: DONE
A35: =A34+1 -> 34 | B35: 22VN00000035 | C35: In Use | D35: =VLOOKUP(B35,VN_Emails!B:H,4,0) -> Dang Thi Thanh Tam | E35: =VLOOKUP(B35,VN_Emails!B:H,7,0) -> Brand Manager (NB, Crocs) | F35: AMMAVNMDC000035 | G35: =SUBSTITUTE(VLOOKUP(B35,VN_Emails!B:H,2,0),"@mapactive.vn","") -> tam.dangthithanh | H35: Office | I35: =J35&" "&K35&" "&L35 -> Laptop Dell Latitude 5420 | J35: Laptop | K35: Dell | L35: Latitude 5420 | M35: 4CBCZH3 | N35: 12 | O35: 512 | P35: SSD | Q35: 1400 MHz 11th Gen Intel Core i5-1135G7 @ 2.40GHz | X35: MMA-LAP-0035 | Y35: DONE | Z35: DONE | AA35: DONE | AB35: DONE
A36: =A35+1 -> 35 | B36: 22VN00000036 | C36: Reserved | D36: KN10 bán cho Maison | E36: =VLOOKUP(B36,VN_Emails!B:H,7,0) -> #N/A | F36: AMMAVNMDC000036 | G36: =SUBSTITUTE(VLOOKUP(B36,VN_Emails!B:H,2,0),"@mapactive.vn","") -> #N/A | H36: Office | I36: =J36&" "&K36&" "&L36 -> Laptop Lenovo Ideapad 5-15ITL05(82FG00M5VN) | J36: Laptop | K36: Lenovo | L36: Ideapad 5-15ITL05(82FG00M5VN) | M36: PF2Q30RQ | N36: 8 | O36: 512 | P36: SSD | Q36: 2400 MHz 11th Gen Intel Core i5-1135G7 @ 2.40GHz | T36: - Old laptop of Pham My Tu - Cần cài lại Windows | V36: - Old laptop of Pham My Tu | X36: MMA-LAP-0036 | Y36: DONE | Z36: DONE | AA36: DONE | AB36: DONE
A37: =A36+1 -> 36 | B37: 22VN00000037 | C37: In Use | D37: =VLOOKUP(B37,VN_Emails!B:H,4,0) -> Nguyen Phuoc Thanh | E37: =VLOOKUP(B37,VN_Emails!B:H,7,0) -> Merchandiser | F37: AMMAVNMDC000037 | G37: =SUBSTITUTE(VLOOKUP(B37,VN_Emails!B:H,2,0),"@mapactive.vn","") -> thanh.nguyenphuoc | H37: Office | I37: =J37&" "&K37&" "&L37 -> Laptop Dell Latitude 3520 | J37: Laptop | K37: Dell | L37: Latitude 3520 | M37: 6Q7JGL3 | N37: 12 | O37: 512 | P37: SSD | Q37: 1400 MHz 11th Gen Intel Core i5-1135G7 @ 2.40GHz | X37: MMA-LAP-0037 | Y37: DONE | Z37: DONE | AA37: DONE | AB37: DONE
A38: =A37+1 -> 37 | B38: 22VN00000038 | C38: In Use | D38: =VLOOKUP(B38,VN_Emails!B:H,4,0) -> Ngo Thi Bich Tram | E38: =VLOOKUP(B38,VN_Emails!B:H,7,0) -> Shipping Officer | F38: AMMAVNMDC000038 | G38: =SUBSTITUTE(VLOOKUP(B38,VN_Emails!B:H,2,0),"@mapactive.vn","") -> tram.ngothibich | H38: Office | I38: =J38&" "&K38&" "&L38 -> Laptop Dell Latitude 5430 | J38: Laptop | K38: Dell | L38: Latitude 5430 | M38: 4TS3SQ3 | N38: 16 | O38: 512 | P38: SSD | Q38: 2500 MHz 12th Gen Intel Core i5-1235U | V38: Máy của TRƯƠNG HỒNG HƯƠNG BÀN GIAO (HIếu IT giữ) | X38: MMA-LAP-0038 | Y38: DONE | Z38: DONE | AA38: DONE | AB38: DONE
A39: ost | B39: 22VN00000039 | C39: In Use | D39: =VLOOKUP(B39,VN_Emails!B:H,4,0) -> Le Ngoc Bich Tram | E39: =VLOOKUP(B39,VN_Emails!B:H,7,0) -> Marketing Supervisor (Foot Locker) | F39: AMMAVNIT000039 | G39: =SUBSTITUTE(VLOOKUP(B39,VN_Emails!B:H,2,0),"@mapactive.vn","") -> tram.lengocbich | H39: Office | I39: =J39&" "&K39&" "&L39 -> Laptop Dell Latitude 3520 | J39: Laptop | K39: Dell | L39: Latitude 3520 | M39: HGBJGL3 | N39: 20 | O39: 256+512 | P39: SSD | Q39: 1400 MHz 11th Gen Intel Core i5-1135G7 @ 2.40GHz | V39: linh.thainhat resigned 24/04/2024 | X39: MMA-LAP-0039 | Y39: DONE | Z39: DONE | AA39: DONE | AB39: DONE
A40: =Asset_Store!A435+1 -> 413 | B40: 22VN00000041 | C40: In Use | D40: =VLOOKUP(B40,VN_Emails!B:H,4,0) -> Nguyen Thi Tuyet Nhung | E40: =VLOOKUP(B40,VN_Emails!B:H,7,0) -> Senior Merchandise | F40: AMMAVNBPC000041 | G40: =SUBSTITUTE(VLOOKUP(B40,VN_Emails!B:H,2,0),"@mapactive.vn","") -> nhung.nguyenthituyet | H40: Office | I40: =J40&" "&K40&" "&L40 -> Laptop Dell Latitude 5430 | J40: Laptop | K40: Dell | L40: Latitude 5430 | M40: GB23SQ3 | N40: 16 | O40: 512 | P40: SSD | Q40: 2500 MHz 12th Gen Intel Core i5-1235U | T40: User giang.nguyenthiquynh bàn giao ngày 18/08/2023 | V40: IT nhận máy bh ssd lỗi ngày 06/02/24(cmc)> BH SAU TẾT đã bh xong bàn giao user ngày 29/02/24 | W40: DISABLE | X40: MMA-LAP-0041 | Y40: DONE | Z40: DONE | AA40: DONE | AB40: DONE | AC40: DONE
A41: =A40+1 -> 414 | B41: 22VN00000042 | C41: In Use | D41: =VLOOKUP(B41,VN_Emails!B:H,4,0) -> Tran Duy Dien | E41: =VLOOKUP(B41,VN_Emails!B:H,7,0) -> Inventory Control | F41: AMMAVNICC000042 | G41: =SUBSTITUTE(VLOOKUP(B41,VN_Emails!B:H,2,0),"@mapactive.vn","") -> dien.tranduy | H41: Office | I41: =J41&" "&K41&" "&L41 -> Laptop Dell Latitude 3520 | J41: Laptop | K41: Dell | L41: Latitude 3520 | M41: J94JGL3 | N41: 8 | O41: 256 | P41: SSD | Q41: 1400 MHz 11th Gen Intel Core i5-1135G7 @ 2.40GHz | X41: MMA-LAP-0042 | Y41: DONE | Z41: DONE | AA41: DONE | AB41: DONE
A42: =A41+1 -> 415 | B42: 22VN00000043 | C42: In Use | D42: Nguyen Thi Minh Thu | E42: =VLOOKUP(B42,VN_Emails!B:H,7,0) -> #N/A | F42: AMMAVNITC000043 | G42: =SUBSTITUTE(VLOOKUP(B42,VN_Emails!B:H,2,0),"@mapactive.vn","") -> #N/A | H42: Office | I42: =J42&" "&K42&" "&L42 -> Laptop Dell Latitude 3520 | J42: Laptop | K42: Dell | L42: Latitude 3520 | M42: 8F6JGL3 | N42: 8 | O42: 256 | P42: SSD | Q42: 1400 MHz 11th Gen Intel Core i5-1135G7 @ 2.40GHz | T42: Hiếu IT giữ | V42: .TRẦN QUỐC THIÊN HƯƠNG (May) left on 26 Sep 2023 .Anh Hiếu đang giữ | X42: MMA-LAP-0043 | Y42: DONE | Z42: DONE | AA42: DONE | AB42: DONE
A43: =A42+1 -> 416 | B43: 22VN00000044 | C43: In Use | D43: =VLOOKUP(B43,VN_Emails!B:H,4,0) -> Tran Ngoc Doan Trinh | E43: =VLOOKUP(B43,VN_Emails!B:H,7,0) -> Senior Merchandise | F43: AMMAVNMPC000044 | G43: =SUBSTITUTE(VLOOKUP(B43,VN_Emails!B:H,2,0),"@mapactive.vn","") -> trinh.tranngocdoan | H43: Office | I43: =J43&" "&K43&" "&L43 -> Laptop Dell Latitude 3520 | J43: Laptop | K43: Dell | L43: Latitude 3520 | M43: BGBJGL3 | N43: 16 | O43: 256 | P43: SSD | Q43: 1400 MHz 11th Gen Intel Core i5-1135G7 @ 2.40GHz | X43: MMA-LAP-0044 | Y43: DONE | Z43: DONE | AA43: DONE | AB43: DONE
A44: =A43+1 -> 417 | B44: 22VN00000045 | C44: Available | D44: =VLOOKUP(B44,VN_Emails!B:H,4,0) -> #N/A | E44: =VLOOKUP(B44,VN_Emails!B:H,7,0) -> #N/A | F44: AMMAVNOPC000045 | G44: =SUBSTITUTE(VLOOKUP(B44,VN_Emails!B:H,2,0),"@mapactive.vn","") -> #N/A | H44: Office | I44: =J44&" "&K44&" "&L44 -> Laptop Dell Latitude 7490 | J44: Laptop | K44: Dell | L44: Latitude 7490 | M44: 8DBRMV2 | N44: 16 | O44: 256 | P44: SSD | Q44: 1900 MHz Core i5-8350U | T44: 30/08/2023 Anh Trí OP bàn giao máy ,setup cho nhân viên mới 1. Võ Thị Hoàng Ánh Xuân – Operations Executive – Operations Department – On board 19/10/2023 | V44: - Trí OM (bàn giao cho IT ngày 30/08/2023 | X44: MMA-LAP-0045 | Y44: DONE | Z44: DONE | AA44: DONE | AB44: DONE
A45: =A44+1 -> 418 | B45: 22VN00000046 | C45: Available | D45: =VLOOKUP(B45,VN_Emails!B:H,4,0) -> #N/A | E45: =VLOOKUP(B45,VN_Emails!B:H,7,0) -> #N/A | F45: AMMAVNMDC000046 | G45: =SUBSTITUTE(VLOOKUP(B45,VN_Emails!B:H,2,0),"@mapactive.vn","") -> #N/A | H45: Office | I45: =J45&" "&K45&" "&L45 -> Laptop HP Pavilion 15-eg0xxx | J45: Laptop | K45: HP | L45: Pavilion 15-eg0xxx | M45: 5CD108K0PN | N45: 12 | O45: 256 | P45: SSD | Q45: 3000 MHz 11th Gen Intel Core i3-1115G4 @ 3.00GHz | T45: máy cũ Đăng | X45: MMA-LAP-0046 | Y45: DONE | Z45: DONE | AA45: DONE | AB45: DONE
A46: =A45+1 -> 419 | B46: 22VN00000047 | C46: In Use | D46: =VLOOKUP(B46,VN_Emails!B:H,4,0) -> Co Anh Tuan | E46: =VLOOKUP(B46,VN_Emails!B:H,7,0) -> Area Manager (South) | F46: AMMAVNOPC000047 | G46: =SUBSTITUTE(VLOOKUP(B46,VN_Emails!B:H,2,0),"@mapactive.vn","") -> Tuan.Coanh | H46: Office | I46: =J46&" "&K46&" "&L46 -> Laptop Dell Latitude 5420 | J46: Laptop | K46: Dell | L46: Latitude 5420 | M46: 1BXCZH3 | N46: 16 | O46: 512 | P46: SSD | Q46: 1400 MHz 11th Gen Intel Core i5-1135G7 @ 2.40GHz | T46: Máy HỒ HẢI ĐĂNG BÀN GIAO NGÀY 14/11/23 | W46: DISABLE | X46: MMA-LAP-0047 | Y46: Need to do both | AA46: DONE | AB46: DONE | AC46: DONE
A47: =A46+1 -> 420 | B47: 22VN00000048 | C47: In Use | D47: IT BACKUP | E47: =VLOOKUP(B47,VN_Emails!B:H,7,0) -> #N/A | F47: AMMAVNITC000048 change to ZV37-ADMIN | G47: =SUBSTITUTE(VLOOKUP(B47,VN_Emails!B:H,2,0),"@mapactive.vn","") -> #N/A | H47: Office | I47: =J47&" "&K47&" "&L47 -> Laptop Lenovo ThinkPad E490 | J47: Laptop | K47: Lenovo | L47: ThinkPad E490 | M47: PF1JT4Q6 | N47: 8 | O47: 500 | P47: SSD | Q47: 1800 MHz Core i5-8265U | T47: - Máy cũ của Quỳnh AM HN, IT ĐÃ THAY SSD 500GB - 13-Nov-2023: gửi đi sửa USB, bản lề, phím change hostname to zv35 | V47: Máy của Quỳnh Am bị hư ổ cứng nên trả máy về cho IT, CHO TUYỀN MD MƯỢN SỬ DỤNG TẠM | X47: MMA-LAP-0048 | Y47: DONE | Z47: DONE | AA47: DONE | AB47: DONE
A48: =A47+1 -> 421 | B48: 22VN00000049 | C48: Available | D48: =VLOOKUP(B48,VN_Emails!B:H,4,0) -> #N/A | E48: =VLOOKUP(B48,VN_Emails!B:H,7,0) -> #N/A | F48: AMMAVNMDC000049 | G48: =SUBSTITUTE(VLOOKUP(B48,VN_Emails!B:H,2,0),"@mapactive.vn","") -> #N/A | H48: Office | I48: =J48&" "&K48&" "&L48 -> Laptop Dell Latitude 3520 | J48: Laptop | K48: Dell | L48: Latitude 3520 | M48: 6R4JGL3 | N48: 8 | O48: 256 | P48: SSD | Q48: 1400 MHz 11th Gen Intel Core i5-1135G7 @ 2.40GHz | X48: MMA-LAP-0049 | Y48: DONE | Z48: DONE | AA48: DONE | AB48: DONE
A49: =A48+1 -> 422 | B49: 22VN00000050 | C49: In Use | D49: =VLOOKUP(B49,VN_Emails!B:H,4,0) -> Duong Quang Minh Tuan | E49: =VLOOKUP(B49,VN_Emails!B:H,7,0) -> Area Manager (South) | F49: AMMAVNITC000050 | G49: =SUBSTITUTE(VLOOKUP(B49,VN_Emails!B:H,2,0),"@mapactive.vn","") -> tuan.duongquangminh | H49: Office | I49: =J49&" "&K49&" "&L49 -> Laptop Dell Latitude 5430 | J49: Laptop | K49: Dell | L49: Latitude 5430 | M49: 9NN2SQ3 | N49: 16 | O49: 512 | P49: SSD | Q49: 2500 MHz 12th Gen Intel Core i5-1235U | T49: Đã bảo hành, thay SSD và cài Win 11 & update driver full | V49: THOI HUU NGHIA (PnD) OLD LAPTOP Thu hồi laptop 3520 và bàn giao laptop 5430 của Nghĩa PJ cho Dương Quang Minh Tuấn Op | X49: MMA-LAP-0050 | Y49: DONE | Z49: DONE | AA49: DONE | AB49: DONE
A50: =A49+1 -> 423 | B50: 22VN00000051 | C50: In Use | D50: =VLOOKUP(B50,VN_Emails!B:H,4,0) -> Nguyen Thi Huynh Mai | E50: =VLOOKUP(B50,VN_Emails!B:H,7,0) -> Finance, Tax & Accounting Manager | F50: AMMAVNACC000051 | G50: =SUBSTITUTE(VLOOKUP(B50,VN_Emails!B:H,2,0),"@mapactive.vn","") -> mai.nguyenthihuynh | H50: Office | I50: =J50&" "&K50&" "&L50 -> Laptop Dell Latitude 5420 | J50: Laptop | K50: Dell | L50: Latitude 5420 | M50: 66XN2F3 | N50: 16 | O50: 1024 | P50: SSD | Q50: 1400 MHz 11th Gen Intel Core i5-1135G7 @ 2.40GHz | T50: Đã cài lại win 10 và bàn giao cho chị Maya | V50: Huynh Ngoc Son old laptop (reserved for Ms. Maya) | X50: MMA-LAP-0051 | Y50: DONE | Z50: DONE | AA50: DONE | AB50: DONE
A51: =A50+1 -> 424 | B51: 22VN00000052 | C51: In Use | D51: =VLOOKUP(B51,VN_Emails!B:H,4,0) -> Vo Thi Hoang Anh Xuan | E51: Laptop Quynh AM (resigned) | F51: AMMAVNOPC000075 | G51: =SUBSTITUTE(VLOOKUP(B51,VN_Emails!B:H,2,0),"@mapactive.vn","") -> xuan.vothihoanganh | H51: Office | I51: =J51&" "&K51&" "&L51 -> Laptop Dell Latitude 5430 | J51: Laptop | K51: Dell | L51: Latitude 5430 | M51: 2NS0HW3 | N51: 16 | O51: 512 | P51: SSD | Q51: 2500 MHz 12th Gen Intel Core i5-1235U | V51: Quynh.nguyennhu resigned | X51: MMA-LAP-0075 | Y51: DONE | AA51: DONE | AB51: DONE
A52: =A51+1 -> 425 | B52: 22VN00000053 | C52: In Use | D52: =VLOOKUP(B52,VN_Emails!B:H,4,0) -> Vo Lam Minh Dat | E52: =VLOOKUP(B52,VN_Emails!B:H,7,0) -> Area Manager (South) | F52: AMMAVNWSC000053 | G52: =SUBSTITUTE(VLOOKUP(B52,VN_Emails!B:H,2,0),"@mapactive.vn","") -> dat.volamminh | H52: Office | I52: =J52&" "&K52&" "&L52 -> Laptop Dell Latitude 5430 | J52: Laptop | K52: Dell | L52: Latitude 5430 | M52: 4BH2SQ3 | N52: 16 | O52: 512 | P52: SSD | Q52: 2500 MHz 12th Gen Intel Core i5-1235U | X52: MMA-LAP-0053 | Y52: DONE | AA52: DONE | AB52: DONE
A53: =A52+1 -> 426 | B53: 22VN00000054 | C53: Available | D53: =VLOOKUP(B53,VN_Emails!B:H,4,0) -> #N/A | E53: =VLOOKUP(B53,VN_Emails!B:H,7,0) -> #N/A | F53: AMMAVNWSC000054 | G53: =SUBSTITUTE(VLOOKUP(B53,VN_Emails!B:H,2,0),"@mapactive.vn","") -> #N/A | H53: Office | I53: =J53&" "&K53&" "&L53 -> Laptop Dell Latitude 3520 | J53: Laptop | K53: Dell | L53: Latitude 3520 | M53: DQ9VKG3 | N53: 8 | O53: 256 | P53: SSD | Q53: 2200 MHz 11th Gen Intel Core i3-1115G4 @ 3.00GHz | X53: MMA-LAP-0054 | Y53: DONE | AA53: DONE | AB53: DONE
A54: =A53+1 -> 427 | B54: 22VN00000055 | C54: Available | D54: =VLOOKUP(B54,VN_Emails!B:H,4,0) -> #N/A | E54: =VLOOKUP(B54,VN_Emails!B:H,7,0) -> #N/A | F54: AMMAVNWSC000055 | G54: =SUBSTITUTE(VLOOKUP(B54,VN_Emails!B:H,2,0),"@mapactive.vn","") -> #N/A | H54: Office | I54: =J54&" "&K54&" "&L54 -> Laptop Dell Latitude 3520 | J54: Laptop | K54: Dell | L54: Latitude 3520 | M54: FR8VKG3 | N54: 8 | O54: 256 | P54: SSD | Q54: 2200 MHz 11th Gen Intel Core i3-1115G4 @ 3.00GHz | X54: MMA-LAP-0055 | Y54: DONE | AA54: DONE | AB54: DONE
A55: =A54+1 -> 428 | B55: 22VN00000056 | C55: Available | D55: =VLOOKUP(B55,VN_Emails!B:H,4,0) -> #N/A | E55: =VLOOKUP(B55,VN_Emails!B:H,7,0) -> #N/A | F55: AMMAVNWSC000056 | G55: =SUBSTITUTE(VLOOKUP(B55,VN_Emails!B:H,2,0),"@mapactive.vn","") -> #N/A | H55: Office | I55: =J55&" "&K55&" "&L55 -> Laptop Dell Latitude 3520 | J55: Laptop | K55: Dell | L55: Latitude 3520 | M55: CR8VKG3 | N55: 8 | O55: 256 | P55: SSD | Q55: 2200 MHz 11th Gen Intel Core i3-1115G4 @ 3.00GHz | X55: MMA-LAP-0056 | Y55: DONE | AA55: DONE | AB55: DONE
A56: =A55+1 -> 429 | B56: 22VN00000057 | C56: Available | D56: =VLOOKUP(B56,VN_Emails!B:H,4,0) -> #N/A | E56: =VLOOKUP(B56,VN_Emails!B:H,7,0) -> #N/A | F56: AMMAVNWSC000057 | G56: =SUBSTITUTE(VLOOKUP(B56,VN_Emails!B:H,2,0),"@mapactive.vn","") -> #N/A | H56: Office | I56: =J56&" "&K56&" "&L56 -> Laptop Dell Latitude 3520 | J56: Laptop | K56: Dell | L56: Latitude 3520 | M56: 2R9VKG3 | N56: 8 | O56: 256 | P56: SSD | Q56: 2200 MHz 11th Gen Intel Core i3-1115G4 @ 3.00GHz | X56: MMA-LAP-0057 | Y56: DONE | AA56: DONE | AB56: DONE
A57: =A56+1 -> 430 | B57: 22VN00000058 | C57: Available | F57: AMMAVNECC000058 | G57: =SUBSTITUTE(VLOOKUP(B57,VN_Emails!B:H,2,0),"@mapactive.vn","") -> #N/A | H57: Office | I57: =J57&" "&K57&" "&L57 -> Laptop Dell Latitude 5420 | J57: Laptop | K57: Dell | L57: Latitude 5420 | M57: C3KCZH3 | N57: 16 | O57: 512 | P57: SSD | Q57: 1400 MHz 11th Gen Intel Core i5-1135G7 @ 2.40GHz | X57: MMA-LAP-0058 | Y57: DONE | Z57: DONE | AA57: DONE | AB57: DONE
A58: =A57+1 -> 431 | B58: 22VN00000059 | C58: In Use | D58: =VLOOKUP(B58,VN_Emails!B:H,4,0) -> Nguyen My Binh | E58: Digital Commercial Manager | F58: AMMAVNECC000115 | G58: =SUBSTITUTE(VLOOKUP(B58,VN_Emails!B:H,2,0),"@mapactive.vn","") -> binh.nguyenmy | H58: Office | I58: =J58&" "&K58&" "&L58 -> Laptop Dell Latitude 5420 | J58: Laptop | K58: Dell | L58: Latitude 5420 | M58: DGGDZH3 | N58: 16 | O58: 512 | P58: SSD | Q58: 1400 MHz 11th Gen Intel Core i5-1135G7 @ 2.40GHz | T58: Anh hieu.trantrung bàn giao máy ngày 31/08/2023 ngoc.nguyenduyen Máy lỗi xuất hdmi 23/4/2024 | X58: MMA-LAP-0059 | Y58: DONE | Z58: DONE | AA58: DONE | AB58: DONE
A59: =A58+1 -> 432 | B59: 22VN00000060 | C59: In Use | D59: Foot Locker Suppervisior(NGuyen Si Anh) | E59: Foot Locker Suppervisior | F59: AMMAVNOPC000060 | G59: =SUBSTITUTE(VLOOKUP(B59,VN_Emails!B:H,2,0),"@mapactive.vn","") -> anh.nguyensi | H59: Office | I59: =J59&" "&K59&" "&L59 -> Laptop Lenovo Thinkpad X280 | J59: Laptop | K59: Lenovo | L59: Thinkpad X280 | M59: PC0UQCVY | N59: 8 | O59: 256 | P59: SSD | Q59: 1800 MHz Core i5-8250U | X59: MMA-LAP-0060 | Y59: DONE | AA59: DONE | AB59: DONE | AC59: DONE
A60: =A59+1 -> 433 | B60: 22VN00000061 | C60: In Use | D60: =VLOOKUP(B60,VN_Emails!B:H,4,0) -> Le Ngoc My Linh | E60: =VLOOKUP(B60,VN_Emails!B:H,7,0) -> Senior Merchandise | F60: AMMAVNMDC000061 | G60: =SUBSTITUTE(VLOOKUP(B60,VN_Emails!B:H,2,0),"@mapactive.vn","") -> linh.lengocmy | H60: Office | I60: =J60&" "&K60&" "&L60 -> Laptop Dell Latitude 3520 | J60: Laptop | K60: Dell | L60: Latitude 3520 | M60: 3KZCKG3 | N60: 8 | O60: 256 | P60: SSD | Q60: 1400 MHz 11th Gen Intel Core i5-1135G7 @ 2.40GHz | X60: MMA-LAP-0061 | Y60: DONE | Z60: DONE | AA60: DONE | AB60: DONE
A61: =A60+1 -> 434 | B61: 22VN00000062 | C61: In Use | D61: =VLOOKUP(B61,VN_Emails!B:H,4,0) -> Ngo Tieu Binh | E61: =VLOOKUP(B61,VN_Emails!B:H,7,0) -> HR Executive | F61: AMMAVNPDC000062 | G61: =SUBSTITUTE(VLOOKUP(B61,VN_Emails!B:H,2,0),"@mapactive.vn","") -> binh.ngotieu | H61: Office | I61: =J61&" "&K61&" "&L61 -> Laptop Dell Latitude 3520 | J61: Laptop | K61: Dell | L61: Latitude 3520 | M61: 71GCGG3 | N61: 16 | O61: 256 | P61: SSD | Q61: 1400 MHz 11th Gen Intel Core i5-1135G7 @ 2.40GHz | T61: loan.nguyenhoang@mapactive.vn resigned 10/5/24 | X61: MMA-LAP-0062 | Y61: DONE | Z61: DONE | AA61: DONE | AB61: DONE
A62: =A61+1 -> 435 | B62: 22VN00000063 | C62: In Use | D62: =VLOOKUP(B62,VN_Emails!B:H,4,0) -> Ta Quynh Trang | E62: =VLOOKUP(B62,VN_Emails!B:H,7,0) -> COE Officer | F62: AMMAVNCEC000063 | G62: =SUBSTITUTE(VLOOKUP(B62,VN_Emails!B:H,2,0),"@mapactive.vn","") -> trang.taquynh | H62: Office | I62: =J62&" "&K62&" "&L62 -> Laptop Dell Latitude 3520 | J62: Laptop | K62: Dell | L62: Latitude 3520 | M62: 9JYF7S3 | N62: 8 | O62: 256 | P62: SSD | Q62: 1400 MHz 11th Gen Intel Core i5-1135G7 @ 2.40GHz | X62: MMA-LAP-0063 | Y62: DONE | Z62: DONE | AA62: DONE | AB62: DONE
A63: =A62+1 -> 436 | B63: 22VN00000064 | C63: In Use | D63: =VLOOKUP(B63,VN_Emails!B:H,4,0) -> Vo Ngoc Thanh Ngan | E63: =VLOOKUP(B63,VN_Emails!B:H,7,0) -> Intern | F63: AMMAVNOPC000064 | G63: =SUBSTITUTE(VLOOKUP(B63,VN_Emails!B:H,2,0),"@mapactive.vn","") -> ngan.vongocthanh | H63: Office | I63: =J63&" "&K63&" "&L63 -> Laptop Dell Latitude 5430 | J63: Laptop | K63: Dell | L63: Latitude 5430 | M63: B8972T3 | N63: 16 | O63: 512 | P63: SSD | Q63: 2500 MHz 12th Gen Intel Core i5-1235U | T63: Hiếu IT giữ, hư touchpad | V63: Nguyễn Thị Hải Đường off 23/06/2023 , Trần Thị Kim Tuyết off 14/06/2024 | X63: MMA-LAP-0064 | Y63: DONE | AA63: DONE | AB63: DONE
A64: =A63+1 -> 437 | B64: 22VN00000065 | C64: In Use | D64: =VLOOKUP(B64,VN_Emails!B:H,4,0) -> Nguyen Phuong Lan | E64: =VLOOKUP(B64,VN_Emails!B:H,7,0) -> Legal Manager | F64: AMMAVNLEC000065 | G64: =SUBSTITUTE(VLOOKUP(B64,VN_Emails!B:H,2,0),"@mapactive.vn","") -> lan.nguyenphuong | H64: Office | I64: =J64&" "&K64&" "&L64 -> Laptop Dell Latitude 5430 | J64: Laptop | K64: Dell | L64: Latitude 5430 | M64: 42V72T3 | N64: 16 | O64: 512 | P64: SSD | Q64: 2500 MHz 12th Gen Intel Core i5-1235U | W64: use USB token | X64: MMA-LAP-0065 | Y64: DONE | Z64: DONE | AA64: DONE | AB64: DONE
A65: =A64+1 -> 438 | B65: 22VN00000066 | C65: In Use | D65: =VLOOKUP(B65,VN_Emails!B:H,4,0) -> Duong Thi Bao Tram | E65: =VLOOKUP(B65,VN_Emails!B:H,7,0) -> Wholesale Admin | F65: AMMAVNLOC000066 | G65: =SUBSTITUTE(VLOOKUP(B65,VN_Emails!B:H,2,0),"@mapactive.vn","") -> tram.duongthibao | H65: Office | I65: =J65&" "&K65&" "&L65 -> Laptop Dell Latitude 3520 | J65: Laptop | K65: Dell | L65: Latitude 3520 | M65: JWZF7S3 | N65: 8 | O65: 256 | P65: SSD | Q65: 1400 MHz 11th Gen Intel Core i5-1135G7 @ 2.40GHz | X65: MMA-LAP-0066 | Y65: DONE | Z65: DONE | AA65: DONE | AB65: DONE
A66: =A65+1 -> 439 | B66: 22VN00000067 | C66: In Use | D66: =VLOOKUP(B66,VN_Emails!B:H,4,0) -> Le Ngoc Bao Minh | E66: =VLOOKUP(B66,VN_Emails!B:H,7,0) -> Risk Management & Business Process | F66: AMMAVNMDC000067 | G66: =SUBSTITUTE(VLOOKUP(B66,VN_Emails!B:H,2,0),"@mapactive.vn","") -> minh.lengocbao | H66: Office | I66: =J66&" "&K66&" "&L66 -> Laptop HP ProBook 440 G9 | J66: Laptop | K66: HP | L66: ProBook 440 G9 | M66: 5CD250F9YL | N66: 16 | O66: 512 | P66: SSD | Q66: 2500 MHz 12th Gen Intel Core i5-1235U | X66: MMA-LAP-0067 | Y66: DONE | Z66: DONE | AA66: DONE | AB66: DONE | AC66: DONE
A67: =A52+1 -> 426 | B67: 22VN00000068 | C67: Available | D67: =VLOOKUP(B67,VN_Emails!B:H,4,0) -> #N/A | E67: =VLOOKUP(B67,VN_Emails!B:H,7,0) -> #N/A | F67: AMMAVNMPC000068 | G67: =SUBSTITUTE(VLOOKUP(B67,VN_Emails!B:H,2,0),"@mapactive.vn","") -> #N/A | H67: Office | I67: =J67&" "&K67&" "&L67 -> Laptop Dell Latitude 3520 | J67: Laptop | K67: Dell | L67: Latitude 3520 | M67: 6SYF7S3 | N67: 8 | O67: 256 | P67: SSD | Q67: 1400 MHz 11th Gen Intel Core i5-1135G7 @ 2.40GHz | T67: - 13/5/24 Vo Thi Hoang Anh Xuan OPSCCTV - Cấp cho Vân sale(máy chị ấy bị hở bản lề) | V67: - Tran Thi Toan My reassigned - 13/5/24 Vo Thi Hoang Anh Xuan OPSCCTV | X67: MMA-LAP-0068 | Y67: DONE | Z67: DONE | AA67: DONE | AB67: DONE
A68: =A82+1 -> #REF! | B68: 22VN00000069 | C68: Available | D68: =VLOOKUP(B68,VN_Emails!B:H,4,0) -> #N/A | E68: =VLOOKUP(B68,VN_Emails!B:H,7,0) -> #N/A | F68: AMMAVNITC000069 | G68: =SUBSTITUTE(VLOOKUP(B68,VN_Emails!B:H,2,0),"@mapactive.vn","") -> #N/A | H68: Office | I68: =J68&" "&K68&" "&L68 -> Laptop Dell Latitude 3520 | J68: Laptop | K68: Dell | L68: Latitude 3520 | M68: 3DYF7S3 | N68: 12 | O68: 256 | P68: SSD | Q68: 1400 MHz 11th Gen Intel Core i5-1135G7 @ 2.40GHz | X68: MMA-LAP-0069 | Y68: DONE | Z68: DONE | AA68: DONE | AB68: DONE
A69: =A68+1 -> #VALUE! | B69: 22VN00000070 | C69: In Use | D69: =VLOOKUP(B69,VN_Emails!B:H,4,0) -> Nguyen Thi Qui | E69: =VLOOKUP(B69,VN_Emails!B:H,7,0) -> General Accountant UFO | F69: AMMAVNACC000070 | G69: =SUBSTITUTE(VLOOKUP(B69,VN_Emails!B:H,2,0),"@mapactive.vn","") -> qui.nguyenthi | H69: Office | I69: =J69&" "&K69&" "&L69 -> Laptop Dell Latitude 5430 | J69: Laptop | K69: Dell | L69: Latitude 5430 | M69: H3NVHW3 | N69: 16 | O69: 512 | P69: SSD | Q69: 2500 MHz 12th Gen Intel Core i5-1235U | W69: use USB token | X69: MMA-LAP-0070 | Y69: DONE | Z69: DONE | AA69: DONE | AB69: DONE
A70: =A69+1 -> #REF! | B70: 22VN00000071 | C70: In Use | D70: =VLOOKUP(B70,VN_Emails!B:H,4,0) -> Dao Duc Huy | E70: =VLOOKUP(B70,VN_Emails!B:H,7,0) -> Area Manager (South) | F70: AMMAVNITC000071 | G70: =SUBSTITUTE(VLOOKUP(B70,VN_Emails!B:H,2,0),"@mapactive.vn","") -> Huy.daoduc | H70: Office | I70: =J70&" "&K70&" "&L70 -> Laptop Dell Latitude 5430 | J70: Laptop | K70: Dell | L70: Latitude 5430 | M70: BJ972T3 | N70: 16 | O70: 512 | P70: SSD | Q70: 2500 MHz 12th Gen Intel Core i5-1235U | T70: Máy của a AN(IT) Đổi ổ cứng vs XX81 (Máy A huy) | X70: MMA-LAP-0071 | Y70: DONE | Z70: DONE | AA70: DONE | AB70: DONE
A71: =A70+1 -> #REF! | B71: 22VN00000072 | C71: In Use | D71: =VLOOKUP(B71,VN_Emails!B:H,4,0) -> Dao Thi Hong Le | E71: =VLOOKUP(B71,VN_Emails!B:H,7,0) -> Training Assistant Manager | F71: AMMAVNTAC000072 | G71: =SUBSTITUTE(VLOOKUP(B71,VN_Emails!B:H,2,0),"@mapactive.vn","") -> le.daothihong | H71: Office | I71: =J71&" "&K71&" "&L71 -> Laptop Dell Latitude 5430 | J71: Laptop | K71: Dell | L71: Latitude 5430 | M71: 1KHVHW3 | N71: 16 | O71: 512 | P71: SSD | Q71: 2500 MHz 12th Gen Intel Core i5-1235U | X71: MMA-LAP-0072 | Y71: DONE | Z71: DONE | AA71: DONE | AB71: DONE
A72: =A71+1 -> #REF! | B72: 22VN00000073 | C72: In Use | D72: =VLOOKUP(B72,VN_Emails!B:H,4,0) -> Nguyen Quoc Huy | E72: =VLOOKUP(B72,VN_Emails!B:H,7,0) -> Visual Merchandise Supervisor | F72: AMMAVNMDC000073 | G72: =SUBSTITUTE(VLOOKUP(B72,VN_Emails!B:H,2,0),"@mapactive.vn","") -> huy.nguyenquoc | H72: Office | I72: =J72&" "&K72&" "&L72 -> Laptop Dell Latitude 5430 | J72: Laptop | K72: Dell | L72: Latitude 5430 | M72: 7X82HW3 | N72: 16 | O72: 512 | P72: SSD | Q72: 2500 MHz 12th Gen Intel Core i5-1235U | X72: MMA-LAP-0073 | Y72: DONE | Z72: DONE | AA72: DONE | AB72: DONE
A73: =A72+1 -> #REF! | B73: 22VN00000074 | C73: In Use | D73: =VLOOKUP(B73,VN_Emails!B:H,4,0) -> #N/A | E73: =VLOOKUP(B73,VN_Emails!B:H,7,0) -> #N/A | F73: AMMAVNMRC000074 | G73: =SUBSTITUTE(VLOOKUP(B73,VN_Emails!B:H,2,0),"@mapactive.vn","") -> #N/A | H73: Office | I73: =J73&" "&K73&" "&L73 -> Laptop Lenovo Thinkpad X280 | J73: Laptop | K73: Lenovo | L73: Thinkpad X280 | M73: PC0VT5R5 | N73: 8 | O73: 256 | P73: SSD | Q73: INTEL (R) CORE (TM) I5-8250U 1.60GHZ (8CPUS) | T73: Sóng Nam nhận máy về kiểm tra và báo giá chi phí sửa màn hình bị giật 29-01-2024 | V73: - Pham Thi My Dung quit job 02/10/2023 -Lê Ngọc Bích Trâm – Marketing Supervisor – Marketing Department (Foot Locker) – On board 20/10/2023 > Gửi sóng nam sửa màn hình bị giật khung hình 29-01-24> done | X73: MMA-LAP-0074 | Y73: DONE | Z73: DONE | AA73: DONE | AB73: DONE
A74: =A73+1 -> #REF! | B74: 22VN00000075 | C74: Available | D74: =VLOOKUP(B74,VN_Emails!B:H,4,0) -> #N/A | E74: =VLOOKUP(B74,VN_Emails!B:H,7,0) -> #N/A | F74: AMMAVNPDC000052 | G74: =SUBSTITUTE(VLOOKUP(B74,VN_Emails!B:H,2,0),"@mapactive.vn","") -> #N/A | H74: Office | I74: =J74&" "&K74&" "&L74 -> Laptop Dell Latitude 5430 | J74: Laptop | K74: Dell | L74: Latitude 5430 | M74: 61N8RQ3 | N74: 16 | O74: 512 | P74: SSD | Q74: 2500 MHz 12th Gen Intel Core i5-1235U | T74: 19/04/2024 tra.truongvantin resigned | V74: tra.truongvantin | X74: MMA-LAP-0052 | Y74: DONE | Z74: DONE | AA74: DONE | AB74: DONE
A75: =A74+1 -> 421 | B75: 22VN00000076 | C75: In Use | D75: =VLOOKUP(B75,VN_Emails!B:H,4,0) -> Le Thi Anh Tuyet | E75: =VLOOKUP(B75,VN_Emails!B:H,7,0) -> Tax & Accounting Assistant Manager | F75: AMMAVNECC000076 | G75: =SUBSTITUTE(VLOOKUP(B75,VN_Emails!B:H,2,0),"@mapactive.vn","") -> tuyet.lethianh | H75: Office | I75: =J75&" "&K75&" "&L75 -> Laptop Dell Latitude 5430 | J75: Laptop | K75: Dell | L75: Latitude 5430 | M75: CXJ8VV3 | N75: 16 | O75: 512 | P75: SSD | Q75: 2500 MHz 12th Gen Intel Core i5-1235U | X75: MMA-LAP-0076 | Y75: DONE | Z75: DONE | AA75: DONE | AB75: DONE
A76: =A75+1 -> #REF! | B76: 22VN00000077 | C76: In Use | D76: Tran Vu Kim Chi | E76: =VLOOKUP(B76,VN_Emails!B:H,7,0) -> Brand Division Manager (Foot Locker) | F76: AMMAVNMDC000077 | G76: =SUBSTITUTE(VLOOKUP(B76,VN_Emails!B:H,2,0),"@mapactive.vn","") -> chi.tranvukim | H76: Office | I76: =J76&" "&K76&" "&L76 -> Laptop Dell Latitude 5430 | J76: Laptop | K76: Dell | L76: Latitude 5430 | M76: 6MS0HW3 | N76: 16 | O76: 512 | P76: SSD | Q76: 2500 MHz 12th Gen Intel Core i5-1235U | V76: laptop cũ Nguyễn Đỗ Hiền đã bàn giaocho IT ngay7/02/14 Cho Trần Vũ Kim Chi Mượn máy ngày 07/02/2024 | X76: MMA-LAP-0077 | Y76: DONE | Z76: DONE | AA76: DONE | AB76: DONE
A77: =A76+1 -> #REF! | B77: 22VN00000079 | C77: In Use | D77: =VLOOKUP(B77,VN_Emails!B:H,4,0) -> Le Thanh Duyen | E77: =VLOOKUP(B77,VN_Emails!B:H,7,0) -> Graphic Designer (Foot Locker) | F77: AMMAVNGDD000079 | G77: =SUBSTITUTE(VLOOKUP(B77,VN_Emails!B:H,2,0),"@mapactive.vn","") -> duyen.lethanh | H77: Office | I77: =J77&" "&K77&" "&L77 -> Desktop HP Pavilion 590-p0xxx | J77: Desktop | K77: HP | L77: Pavilion 590-p0xxx | M77: 8CG824CV0T | N77: 8 | O77: 1512 | P77: HDD (1 TB) SSD (512 GB) | Q77: 2800 MHz Core i5-8400 HDD 1TB-SSD 240GB | V77: - NGUYỄN NGỌC LAN ANH (Sophie) - Lê Thanh Duyên | X77: MMA-DES-0001 | Y77: DONE | Z77: DONE | AA77: DONE | AB77: DONE
A78: =A77+1 -> 422 | B78: 22VN00000078 | C78: In Use | D78: =VLOOKUP(B78,VN_Emails!B:H,4,0) -> Nguyen Ngoc Lan Anh | E78: =VLOOKUP(B78,VN_Emails!B:H,7,0) -> Graphic Designer | F78: AMMAVNGDC000078 | G78: =SUBSTITUTE(VLOOKUP(B78,VN_Emails!B:H,2,0),"@mapactive.vn","") -> anh.nguyenngoclan | H78: Office | I78: =J78&" "&K78&" "&L78 -> Laptop Dell G15 5520 | J78: Laptop | K78: Dell | L78: G15 5520 | M78: 9R2B9T3 | N78: 32 | O78: 512 | P78: SSD | Q78: 12TH GEN INTEL CORE I7-12700H(20CPU)2.3GHZ SSD512GB-GEFORCE GTX 3060 | X78: MMA-LAP-0078 | Y78: DONE | Z78: DONE | AA78: DONE | AB78: DONE
A79: =A78+1 -> #REF! | B79: 22VN00000080 | C79: In Use | D79: =VLOOKUP(B79,VN_Emails!B:H,4,0) -> Nguyen Thanh Anh Thu | E79: =VLOOKUP(B79,VN_Emails!B:H,7,0) -> Visual Merchandise Manager | F79: AMMAVNMDC000080 | G79: =SUBSTITUTE(VLOOKUP(B79,VN_Emails!B:H,2,0),"@mapactive.vn","") -> thu.nguyenthanhanh | H79: Office | I79: =J79&" "&K79&" "&L79 -> Laptop Dell G15 5520 | J79: Laptop | K79: Dell | L79: G15 5520 | M79: FLQ85R3 | N79: 16 | O79: 1000 | P79: SSD | Q79: 12TH GEN INTEL CORE I7-12700H(20CPU)2.3GHZ SSD512GB-GEFORCE GTX 2050TI | X79: MMA-LAP-0079 | Y79: DONE | Z79: DONE | AA79: DONE | AB79: DONE
A80: =A79+1 -> #REF! | B80: 22VN00000081 | C80: Available | D80: =VLOOKUP(B80,VN_Emails!B:H,4,0) -> #N/A | E80: =VLOOKUP(B80,VN_Emails!B:H,7,0) -> #N/A | F80: AMMAVNOPC000081 | G80: =SUBSTITUTE(VLOOKUP(B80,VN_Emails!B:H,2,0),"@mapactive.vn","") -> #N/A | H80: Office | I80: =J80&" "&K80&" "&L80 -> Laptop Dell Latitude 5430 | J80: Laptop | K80: Dell | L80: Latitude 5430 | M80: F598VV3 | N80: 16 | O80: 512 | P80: SSD | Q80: 2500 MHz 12th Gen Intel Core i5-1235U | V80: Hư swap với máy a an(71) | X80: MMA-LAP-0080 | Y80: DONE | Z80: DONE | AA80: DONE | AB80: DONE
A81: =A80+1 -> #REF! | B81: 22VN00000082 | C81: Available | E81: =VLOOKUP(B81,VN_Emails!B:H,7,0) -> #N/A | F81: AMMAVNMDC000082 | G81: =SUBSTITUTE(VLOOKUP(B81,VN_Emails!B:H,2,0),"@mapactive.vn","") -> #N/A | H81: Office | I81: =J81&" "&K81&" "&L81 -> Laptop Dell Latitude 3520 | J81: Laptop | K81: Dell | L81: Latitude 3520 | M81: DL0G7S3 | N81: 8 | O81: 512 | P81: SSD | Q81: 11TH Gen Intel ® Core™ i5-1135G7 @2.40Ghz | X81: MMA-LAP-0081 | Y81: DONE | Z81: DONE | AA81: DONE | AB81: DONE | AD81: Plan as the last resort for NB Diamond (faulty HDD)
A82: =A80+1 -> #REF! | B82: 22VN00000083 | C82: Available | D82: =VLOOKUP(B82,VN_Emails!B:H,4,0) -> #N/A | E82: =VLOOKUP(B82,VN_Emails!B:H,7,0) -> #N/A | F82: AMMAVNMPC000083 | G82: =SUBSTITUTE(VLOOKUP(B82,VN_Emails!B:H,2,0),"@mapactive.vn","") -> #N/A | H82: Office | I82: =J82&" "&K82&" "&L82 -> Laptop Dell Latitude 3520 | J82: Laptop | K82: Dell | L82: Latitude 3520 | M82: 5YSSKS3 | N82: 8 | O82: 256 | P82: SSD | Q82: 3000 MHz 11th Gen Intel Core i3-1115G4 @ 3.00GHz | T82: nhung.nguyenthituyet resigned | X82: MMA-LAP-0082 | Y82: DONE | Z82: DONE | AA82: DONE | AB82: DONE
A83: =A82+1 -> #REF! | B83: 22VN00000084 | C83: Available | D83: =VLOOKUP(B83,VN_Emails!B:H,4,0) -> #N/A | E83: =VLOOKUP(B83,VN_Emails!B:H,7,0) -> #N/A | F83: AMMAVNTAC000084 | G83: =SUBSTITUTE(VLOOKUP(B83,VN_Emails!B:H,2,0),"@mapactive.vn","") -> #N/A | H83: Office | I83: =J83&" "&K83&" "&L83 -> Laptop Dell Latitude 3520 | J83: Laptop | K83: Dell | L83: Latitude 3520 | M83: BXSSKS3 | N83: 8 | O83: 256 | P83: SSD | Q83: 3000 MHz 11th Gen Intel Core i3-1115G4 @ 3.00GHz | T83: Luong resigned | X83: MMA-LAP-0083 | Y83: DONE | Z83: DONE | AA83: DONE | AB83: DONE
A84: =#REF!+1 -> #REF! | B84: 22VN00000086 | C84: In Use | D84: Nguyen Ha Phuong Uyen | E84: Nguyen Nhu Quynh (Brand Manager Bata) old laptop | F84: AMMAVNMDC000086 | G84: =SUBSTITUTE(VLOOKUP(B84,VN_Emails!B:H,2,0),"@mapactive.vn","") -> uyen.nguyenhaphuong | H84: Office | I84: =J84&" "&K84&" "&L84 -> Laptop Dell Latitude 5430 | J84: Laptop | K84: Dell | L84: Latitude 5430 | M84: 4084RV3 | N84: 16 | O84: 512 | P84: SSD | Q84: 12th Gen Intel(R) Core(TM) i5-1235U[Cores 12 | T84: Đang cấp tạm cho chị Uyên ngày 18/03/2024 | V84: 31/01/2024 Nguyen Nhu Quynh (Brand Manager Bata) resigned | X84: MMA-LAP-0085 | Y84: DONE | Z84: DONE | AA84: DONE | AB84: DONE
A85: =A84+1 -> #REF! | B85: 22VN00000087 | C85: Available | D85: Tran Thanh Nguyen | E85: =VLOOKUP(B85,VN_Emails!B:H,7,0) -> #N/A | F85: AMMAVNMDC000087 | G85: tran.nguyen | H85: Office | I85: =J85&" "&K85&" "&L85 -> Laptop Dell Latitude 3520 | J85: Laptop | K85: Dell | L85: Latitude 3520 | M85: 2XSSKS3 | N85: 8 | O85: 256 | P85: SSD | Q85: 3000 MHz 11th Gen Intel Core i3-1115G4 @ 3.00GHz | X85: MMA-LAP-0086 | Y85: DONE | Z85: DONE | AA85: DONE | AB85: DONE
A86: =A85+1 -> #REF! | B86: 22VN00110003 | C86: Available | E86: =VLOOKUP(B86,VN_Emails!B:H,7,0) -> #N/A | F86: AMMAVNHRD000088 | G86: =SUBSTITUTE(VLOOKUP(B86,VN_Emails!B:H,2,0),"@mapactive.vn","") -> #N/A | H86: Office | I86: =J86&" "&K86&" "&L86 -> Desktop HP ProDesk 400 G3 Mini | J86: Desktop | K86: HP | L86: ProDesk 400 G3 Mini | M86: 8CG8105MSL | N86: 8 | O86: 500 | P86: SSD | Q86: Intel (R) CORE (TM) I5-7500T.2.7GHZ (4CPUS) | Y86: DONE | Z86: DONE | AA86: DONE | AB86: DONE
A87: =A86+1 -> #REF! | B87: 22VN00000089 | C87: Available | D87: Accounting Intern | E87: Accounting Intern (Le Nhi) | F87: AMMAVNACD000089 | H87: Office | I87: =J87&" "&K87&" "&L87 -> Desktop HP ProDesk 400 G3 Mini | J87: Desktop | K87: HP | L87: ProDesk 400 G3 Mini | M87: 8CG75234Q1 | N87: 8 | O87: 500 | P87: SSD | Q87: Intel (R) CORE (TM) I5-7500T.2.7GHZ (4CPUS) | T87: 25/02/2024 bàn giao intern accounting | V87: - Trước đó cấp cho Accounting Intern | Y87: DONE | Z87: DONE | AA87: DONE | AB87: DONE
A88: =Asset_Store!#REF!+1 -> #REF! | B88: 22VN00000091 | C88: Available | E88: Marketing intern | F88: AMMAVNITC000091 | G88: =SUBSTITUTE(VLOOKUP(B88,VN_Emails!B:H,2,0),"@mapactive.vn","") -> #N/A | H88: Office | I88: =J88&" "&K88&" "&L88 -> Laptop Lenovo Thinkpad X280 | J88: Laptop | K88: Lenovo | L88: Thinkpad X280 | M88: PC0VT5RC | N88: 8 | O88: 256 | P88: SSD | Q88: 1800 MHz Core i5-8250U | V88: - Ni HR old laptop, CẤP TẠM CHO NGHIÊM THỊ HỒNG VÂN NGÀY 07/02/24 đã trả IT lưu kho | Y88: DONE | Z88: DONE | AA88: DONE | AB88: DONE
A89: =A88+1 -> #REF! | B89: 22VN00000092 | C89: Available | D89: =VLOOKUP(B89,VN_Emails!B:H,4,0) -> #N/A | E89: =VLOOKUP(B89,VN_Emails!B:H,7,0) -> #N/A | F89: AMMAVNMDC000092 | G89: =SUBSTITUTE(VLOOKUP(B89,VN_Emails!B:H,2,0),"@mapactive.vn","") -> #N/A | H89: Office | I89: =J89&" "&K89&" "&L89 -> Laptop Dell Latitude 5430 | J89: Laptop | K89: Dell | L89: Latitude 5430 | M89: 1GHVHW3 | N89: 16 | O89: 512 | P89: SSD | Q89: 1400 MHz 11th Gen Intel Core i5-1135G7 @ 2.40GHz | Y89: DONE | Z89: DONE | AA89: DONE | AB89: DONE
A90: =A89+1 -> #REF! | B90: 22VN00000093 | C90: In Use | D90: IT (PC-PRINTER) | E90: PC for color printing | F90: AMMAVNITD000093 | H90: Office | I90: =J90&" "&K90&" "&L90 -> Desktop DeLUX | J90: Desktop | K90: DeLUX | M90: DH67VR | N90: 16 | O90: 1024 | P90: HDD | Q90: INTEL (R) CORE (TM) I5-2400.3.1GHZ (8CPUS) | Y90: DONE | Z90: DONE | AA90: DONE | AB90: DONE
A91: =A90+1 -> #REF! | B91: 22VN00000094 | C91: In Use | D91: =VLOOKUP(B91,VN_Emails!B:H,4,0) -> Ngo Anh Tuan | E91: =VLOOKUP(B91,VN_Emails!B:H,7,0) -> Senior Wholesaler | F91: AMMAVNOPC000094 | G91: =SUBSTITUTE(VLOOKUP(B91,VN_Emails!B:H,2,0),"@mapactive.vn","") -> tuan.ngoanh | H91: Office | I91: =J91&" "&K91&" "&L91 -> Laptop Dell Latitude 5430 | J91: Laptop | K91: Dell | L91: Latitude 5430 | M91: 9ZHQRV3 | N91: 16 | O91: 512 | P91: SSD | Q91: 2500 MHz 12th Gen Intel Core i5-1235U | T91: Máy cũ của Thy.nguyenhoanganh 05/Dec/2024 bàn giao cho Intern Accounting\ | V91: minh.letranthien@mapactive.vn resigned thy.nguyenhoanganh resigned chi Mai giữ máy | Y91: DONE | Z91: DONE | AA91: DONE | AB91: DONE
A92: =A91+1 -> #REF! | B92: 22VN00000095 | C92: Available | D92: IT Backup | E92: Inter MKT Nguyễn Hồng Thị Minh Bình | F92: AMMAVNITC000095 | G92: =SUBSTITUTE(VLOOKUP(B92,VN_Emails!B:H,2,0),"@mapactive.vn","") -> #N/A | H92: Office | I92: =J92&" "&K92&" "&L92 -> Laptop Lenovo Thinkpad X280 | J92: Laptop | K92: Lenovo | L92: Thinkpad X280 | M92: PC0VSNY2 | N92: 8 | O92: 256 | P92: SSD | Q92: INTEL® CORE ™I5-8250u CPU 1.60 GhZ | T92: - 13-Nov-2023: gửi đi sửa USB, bản lề, phím - Đã sửa xong | V92: Laptop Tran Thu Huyen (AM Hai Phong) - dùng cho Supervisor Store VC03 & VE01 CHAMPION & NewEra AEON MALL HẢI PHÒNG | Y92: DONE | Z92: DONE | AA92: DONE | AB92: DONE
A93: =A92+1 -> #REF! | B93: 22VN00000096 | C93: In Use | D93: VN06-ADMIN | E93: LAPTOP OLD VANHUYNHTU TRINH | F93: VN06-ADMIN | G93: =SUBSTITUTE(VLOOKUP(B93,VN_Emails!B:H,2,0),"@mapactive.vn","") -> #N/A | H93: Office | I93: =J93&" "&K93&" "&L93 -> Laptop Lenovo Thinkpad X280 | J93: Laptop | K93: Lenovo | L93: Thinkpad X280 | M93: PC12PNNM | N93: 8 | O93: 256 | P93: SSD | Q93: INTEL® CORE ™I5-8250u CPU 1.60 GhZ | T93: CẦN NÂNG CẤP RAM ,laptop cũ VANHUYNHTU TRINH , bàn giao cho Nguyen Thi Phuong Dung ngày 23/11/2023, thu hồi lại ngày 01/03/2024>ITbackup | V93: LAPTOP CŨ TÚ TRINH ACC Cấp cho Dung Marketing | Y93: DONE | Z93: DONE | AA93: DONE | AB93: DONE | AC93: DONE
A94: =A93+1 -> #REF! | B94: 22VN00000097 | C94: In Use | D94: =VLOOKUP(B94,VN_Emails!B:H,4,0) -> Luu Giang Cam Van | E94: New 5430 Laptop provide Tran Vu Kim Chi – Brand Division Manager (Foot Locker) | F94: AMMAVNHRC000097 | G94: =SUBSTITUTE(VLOOKUP(B94,VN_Emails!B:H,2,0),"@mapactive.vn","") -> van.luugiangcam | H94: Office | I94: =J94&" "&K94&" "&L94 -> Laptop Dell Latitude 5430 | J94: Laptop | K94: Dell | L94: Latitude 5430 | M94: B1K8VV3 | N94: 16 | O94: 512 | P94: SSD | Q94: 2500 MHz 12th Gen Intel Core i5-1235U | V94: THAY CHO VICKY (HR), TRƯỚC ĐÓ MUA CHO TRẦN VŨ KIM CHI (BRND MANAGER ) | Z94: DONE | AA94: DONE | AB94: DONE | AC94: DONE
A95: =A94+1 -> #REF! | B95: 22VN00000098 | C95: In Use | D95: Mai Nguyen Diem Quynh | E95: =VLOOKUP(B95,VN_Emails!B:H,7,0) -> Payable Accountant | F95: AMMAVNACC000098 | G95: =SUBSTITUTE(VLOOKUP(B95,VN_Emails!B:H,2,0),"@mapactive.vn","") -> quynh.mainguyendiem | H95: Office | I95: =J95&" "&K95&" "&L95 -> Laptop Dell Latitude 3420 | J95: Laptop | K95: Dell | L95: Latitude 3420 | M95: F650FX3 | N95: 16 | O95: 512 | P95: SSD | Q95: 1400 MHz 11th Gen Intel Core i5-1135G7 @ 2.40GHz | T95: Lô 6 Laptop swap mua hàng với Cambodia | V95: Replace the old laptop of Quynh.mainguyendiem
A96: =A95+1 -> #REF! | B96: 22VN00000099 | C96: In Use | D96: =VLOOKUP(B96,VN_Emails!B:H,4,0) -> Thoi Huu Nghia | E96: new laptop 3420 provide Thoi Huu Nghia( Project team) | F96: AMMAVNPDC000099 | G96: =SUBSTITUTE(VLOOKUP(B96,VN_Emails!B:H,2,0),"@mapactive.vn","") -> nghia.thoihuu | H96: Office | I96: =J96&" "&K96&" "&L96 -> Laptop Dell Latitude 3420 | J96: Laptop | K96: Dell | L96: Latitude 3420 | M96: 2R20FX3 | N96: 16 | O96: 512 | P96: SSD | Q96: 1400 MHz 11th Gen Intel Core i5-1135G7 @ 2.40GHz | T96: Lô 6 Laptop swap mua hàng với Cambodia | V96: Swap old laptop of NGHIA.THOIHUU
A97: =A96+1 -> #REF! | B97: 22VN00000100 | C97: In Use | D97: =VLOOKUP(B97,VN_Emails!B:H,4,0) -> Huynh Ngoc Son | E97: Huynh Ngoc Son (Project Supervisor) | F97: AMMAVNPDC000100 | G97: =SUBSTITUTE(VLOOKUP(B97,VN_Emails!B:H,2,0),"@mapactive.vn","") -> son.huynhngoc | H97: Office | I97: =J97&" "&K97&" "&L97 -> Laptop Dell Latitude 3420 | J97: Laptop | K97: Dell | L97: Latitude 3420 | M97: JJNZDX3 | N97: 16 | O97: 512 | P97: SSD | Q97: 1400 MHz 11th Gen Intel Core i5-1135G7 @ 2.40GHz | T97: Lô 6 Laptop swap mua hàng với Cambodia | V97: SWAP OLD LAPTOP OF SON.HUYNHNGOC
A98: =A97+1 -> #REF! | B98: 22VN00000101 | C98: In Use | D98: =VLOOKUP(B98,VN_Emails!B:H,4,0) -> Pham My Tu | E98: =VLOOKUP(B98,VN_Emails!B:H,7,0) -> Senior Merchandise | F98: AMMAVNMDC000101 | G98: =SUBSTITUTE(VLOOKUP(B98,VN_Emails!B:H,2,0),"@mapactive.vn","") -> tu.phammy | H98: Office | I98: =J98&" "&K98&" "&L98 -> Laptop Dell Latitude 3420 | J98: Laptop | K98: Dell | L98: Latitude 3420 | M98: 2Q20FX3 | N98: 16 | O98: 512 | P98: SSD | Q98: 1400 MHz 11th Gen Intel Core i5-1135G7 @ 2.40GHz | T98: Lô 6 Laptop swap mua hàng với Cambodia | V98: Swap old laptop of Pham My Tu
A99: =A98+1 -> #REF! | B99: 22VN00000102 | C99: In Use | D99: =VLOOKUP(B99,VN_Emails!B:H,4,0) -> Nguyen Nam Thang | E99: =VLOOKUP(B99,VN_Emails!B:H,7,0) -> Senior Wholesaler | F99: AMMAVNITC000102 | G99: =SUBSTITUTE(VLOOKUP(B99,VN_Emails!B:H,2,0),"@mapactive.vn","") -> thang.nguyennam | H99: Office | I99: =J99&" "&K99&" "&L99 -> Laptop Dell Latitude 3420 | J99: Laptop | K99: Dell | L99: Latitude 3420 | M99: CY40FX3 | N99: 16 | O99: 512 | P99: SSD | Q99: 1400 MHz 11th Gen Intel Core i5-1135G7 @ 2.40GHz | T99: Lô 6 Laptop swap mua hàng với Cambodia
A100: =A99+1 -> #REF! | B100: 22VN00000103 | C100: In Use | D100: =VLOOKUP(B100,VN_Emails!B:H,4,0) -> Vo Thuy Minh Tuyen | E100: =VLOOKUP(B100,VN_Emails!B:H,7,0) -> Senior Merchandise | F100: AMMAVNLOC000103 | G100: =SUBSTITUTE(VLOOKUP(B100,VN_Emails!B:H,2,0),"@mapactive.vn","") -> tuyen.vothuyminh | H100: Office | I100: =J100&" "&K100&" "&L100 -> Laptop Dell Latitude 3420 | J100: Laptop | K100: Dell | L100: Latitude 3420 | M100: 69LXDX3 | N100: 16 | O100: 512 | P100: SSD | Q100: 1400 MHz 11th Gen Intel Core i5-1135G7 @ 2.40GHz | T100: Lô 6 Laptop swap mua hàng với Cambodia | V100: Lô 6 Laptop swap mua hàng với Cambodia swap laptop of Nguyen Hoang Anh Thy
...

Sheet VN_Emails
A1: No. | B1: Assigned Asset | C1: Email Address | D1: Full Name | E1: Display Name | F1: English Name | G1: Department | H1: JOB TITLE | I1: O365 license | J1: Country | K1: Type | L1: Onboarding Date | M1: Request email | N1: Purchasing Request | O1: Laptop model | P1: Laptop delivery | Q1: Handover to user | R1: Notes | S1: MAP Level
A2: 1 | B2: 22VN00000086 | C2: uyen.nguyenhaphuong@mapactive.vn | D2: Nguyễn Hà Phượng Uyên | E2: Nguyen Ha Phuong Uyen | F2: Dory | G2: BOD (Finance) | H2: General Manager & Finance Controller | I2: E3 | J2: VN | K2: Office | S2: Senior General Manager
A3: 2 | B3: 22VN00000001 | C3: phung.tietnha@mapactive.vn | D3: Tiết Nhã Phụng | E3: Tiet Nha Phung | H3: Brand Manager (Converse) | I3: E3 | J3: VN | K3: Office | S3: Senior Manager
A4: 3 | B4: 22VN00000035 | C4: tam.dangthithanh@mapactive.vn | D4: Đặng Thị Thanh Tâm | E4: Dang Thi Thanh Tam | F4: Tansy | H4: Brand Manager (NB, Crocs) | I4: E3 | J4: VN | K4: Office | S4: Senior Manager
A5: 4 | B5: 22VN00000097 | C5: van.luugiangcam@mapactive.vn | D5: Lưu Giang Cẩm Vân | E5: Luu Giang Cam Van | F5: Vicky | H5: HR & Admin Manager | I5: E3 | J5: VN | K5: Office | S5: Manager
A6: 5 | B6: 22VN00000020 | C6: them.quanthanh@mapactive.vn | D6: Quan Thanh Thềm | E6: Quan Thanh Them | H6: COE Manager | I6: E3 | J6: VN | K6: Office | S6: Manager
A7: 6 | B7: 22VN00000099 | C7: nghia.thoihuu@mapactive.vn | D7: Thới Hũu Nghĩa | E7: Thoi Huu Nghia | H7: Senior Project Manager | I7: E3 | J7: VN | K7: Office | S7: Senior Manager
A8: 7 | B8: 22VN00000103 | C8: tuyen.vothuyminh@mapactive.vn | D8: Võ Thụy Minh Tuyền | E8: Vo Thuy Minh Tuyen | H8: Senior Merchandise | I8: E3 | J8: VN | K8: Office | S8: Associate Manager
A9: 8 | B9: 22VN00000101 | C9: tu.phammy@mapactive.vn | D9: Phạm Mỹ Tú | E9: Pham My Tu | H9: Senior Merchandise | I9: E3 | J9: VN | K9: Office | S9: Associate Manager
A10: 9 | B10: 22VN00000037 | C10: thanh.nguyenphuoc@mapactive.vn | D10: Nguyễn Phước Thạnh | E10: Nguyen Phuoc Thanh | H10: Merchandiser | I10: E3 | J10: VN | K10: Office | S10: Senior Executive
A11: 10 | B11: 22VN00000009 | C11: linh.lecam@mapactive.vn | D11: Lê Cẩm Linh | E11: Le Cam Linh | H11: Shipping Supervisor | I11: E3 | J11: VN | K11: Office | S11: Senior Executive
A12: 11 | B12: 22VN00000038 | C12: tram.ngothibich@mapactive.vn | D12: Ngô Thị Bích Trâm | E12: Ngo Thi Bich Tram | H12: Shipping Officer | I12: E3 | J12: VN | K12: Office | S12: Senior Associate
A13: 12 | B13: 22VN00000076 | C13: tuyet.lethianh@mapactive.vn | D13: Lê Thị Ánh Tuyết | E13: Le Thi Anh Tuyet | H13: Tax & Accounting Assistant Manager | I13: E3 | J13: VN | K13: Office | S13: Senior Associate
A14: 13 | B14: 22VN00000094 | C14: tuan.ngoanh@mapactive.vn | D14: Ngô Anh Tuấn | E14: Ngo Anh Tuan | H14: Senior Wholesaler | I14: E3 | J14: VN | K14: Office | S14: Executive
A15: 14 | B15: 22VN00000102 | C15: thang.nguyennam@mapactive.vn | D15: Nguyễn Nam Thắng | E15: Nguyen Nam Thang | H15: Senior Wholesaler | I15: E3 | J15: VN | K15: Office | S15: Executive
A16: 15 | B16: 22VN00000018 | C16: nam.dangthanh@mapactive.vn | D16: Đặng Thành Nam | E16: Dang Thanh Nam | H16: Warehouse and Distribution Supervisor | I16: E3 | J16: VN | K16: Office | S16: Senior Executive
A17: 16 | B17: 22VN00000098 | C17: quynh.mainguyendiem@mapactive.vn | D17: Mai Nguyễn Diễm Quỳnh | E17: Mai Nguyen Diem Quynh | H17: Payable Accountant | I17: E3 | J17: VN | K17: Office | S17: Senior Associate
... A24: 24 | B24: 22VN00000066 | C24: tram.duongthibao@mapactive.vn | D24: Dương Thị Bảo Trâm | E24: Duong Thi Bao Tram | H24: Wholesale Admin | I24: E3 | J24: VN | K24: Office | S24: Associate
A25: 25 | B25: 22VN00000078 | C25: anh.nguyenngoclan@mapactive.vn | D25: Nguyễn Ngọc Lan Anh | E25: Nguyen Ngoc Lan Anh | F25: Sophie | H25: Graphic Designer | I25: E3 | J25: VN | K25: Office | S25: Senior Executive
A26: 26 | B26: 22VN00000044 | C26: trinh.tranngocdoan@mapactive.vn | D26: Trần Ngọc Đoan Trinh | E26: Tran Ngoc Doan Trinh | H26: Senior Merchandise | I26: E3 | J26: VN | K26: Office | S26: Senior Manager
A27: 27 | B27: 22VN00000061 | C27: linh.lengocmy@mapactive.vn | D27: Lê Ngoc Mỹ Linh | E27: Le Ngoc My Linh | H27: Senior Merchandise | I27: E3 | J27: VN | K27: Office | L27: 44958
A28: 28 | B28: 22VN00000013 | C28: nhi.tranthiyen@mapactive.vn | D28: Trần Thị Yến Nhi | E28: Tran Thi Yen Nhi | H28: Payroll & Em. Servieces Executive | I28: E3 | J28: VN | K28: Office | S28: Senior Associate
A29: 29 | B29: 22VN00000014 | C29: ni.ksormahhko@mapactive.vn | D29: Ksormahhko NI | E29: Ni Ksormahhko | H29: Procurement Executive | I29: E3 | J29: VN | K29: Office | S29: Senior Associate
A30: 30 | B30: 22VN00000065 | C30: lan.nguyenphuong@mapactive.vn | D30: Nguyễn Phương Lan | E30: Nguyen Phuong Lan | G30: Legal | H30: Legal Manager | I30: E3 | J30: VN | K30: Office | L30: 44991 | M30: Done | N30: Done | O30: 5430 | P30: Done | Q30: Done
A31: 31 | B31: 22VN00000106 | C31: syed.umairhassan@mapactive.vn | D31: Syed Umair Hassan | E31: Syed Umair Hassan | G31: BOD (Merchandise) | H31: GM Merchandise | I31: E3 | J31: VN | K31: Office | L31: 45005 | M31: Done | Q31: Done | R31: Using the HP Laptop of Birkenstock Diamond Plaza
A32: 32 | B32: 22VN00000025 | C32: quan.luonghuu@mapactive.vn | D32: Lương Hữu Quân | E32: Luong Huu Quan | G32: IT | H32: IT Infrastructure & Operations Supervisor | I32: E3 | J32: VN | K32: Office | L32: 45012 | M32: Done | N32: Done | O32: 3520 | P32: Done | Q32: Done
A33: 33 | B33: 22VN00000015 | C33: nhan.huynhtuan@mapactive.vn | D33: Huỳnh Tuấn Nhân | E33: Huynh Tuan Nhan | G33: SCM | H33: SCM Manager | I33: E3 | J33: VN | K33: Office | L33: 45019 | M33: Done | N33: No need | O33: No need | P33: No need | R33: Re-use the laptop of ngoc.voleminh
A34: 34 | B34: 22VN00000004 | C34: mong.nguyenthithuy@mapactive.vn | D34: Nguyễn Thị Thúy Mộng | E34: Nguyen Thi Thuy Mong | G34: Merchandise | H34: Senior Brand Marketing Manager | I34: E3 | J34: VN | K34: Office | L34: 45026 | M34: Done | N34: Done | O34: 5430 | R34: Foot Locker
A35: 35 | B35: 22VN00000070 | C35: qui.nguyenthi@mapactive.vn | D35: Nguyễn Thị Quí | E35: Nguyen Thi Qui | G35: Accounting | H35: General Accountant UFO | I35: E3 | J35: VN | K35: Office | L35: 45054 | M35: Done | N35: No need | O35: No need | R35: Re-use Nguyễn Trí Độ' Laptop
A36: 36 | B36: 22VN00000072 | C36: le.daothihong@mapactive.vn | D36: Đào Thị Hồng Lê | E36: Dao Thi Hong Le | G36: Training | H36: Training Assistant Manager | I36: E3 | J36: VN | K36: Office | L36: 45069 | M36: Done | N36: done | O36: 5430
A37: 37 | B37: 22VN00000042 | C37: dien.tranduy@mapactive.vn | D37: Trần Duy Điền | E37: Tran Duy Dien | G37: COE Department | H37: Inventory Control | I37: E3 | J37: VN | K37: Office | L37: 45078 | M37: Done | N37: No need | O37: 3520
A38: 38 | B38: 22VN00000080 | C38: thu.nguyenthanhanh@mapactive.vn | D38: Nguyễn Thanh Anh Thư | E38: Nguyen Thanh Anh Thu | G38: Marketing Department | H38: Visual Merchandise Manager | I38: E3 | J38: VN | K38: Office | L38: 45083 | M38: Done | N38: Done | O38: 5430
A39: 39 | B39: 22VN00000071 | C39: Huy.daoduc@mapactive.vn | D39: Đào Đức Huy | E39: Dao Duc Huy | G39: Operations Department | H39: Area Manager (South) | I39: E3 | J39: VN | K39: Office | L39: 45110 | M39: Done | N39: Done | O39: 5430
A40: 40 | B40: 22VN00000023 | C40: du.nguyenbao@mapactive.vn | D40: Nguyễn Bảo Du | E40: Nguyen Bao Du | G40: HR Department | H40: HR Internship | I40: None | J40: VN | K40: Office | L40: 45139 | M40: No need | N40: Done | O40: Mini PC
A41: 41 | B41: 22VN00000079 | C41: duyen.lethanh@mapactive.vn | D41: Lê Thanh Duyên | E41: Le Thanh Duyen | G41: Marketing Department | H41: Graphic Designer (Foot Locker) | I41: E3 | J41: VN | K41: Office | L41: 45146 | M41: Done | N41: No need | R41: Re-use Vũ Xuân Sơn
A42: 42 | B42: 22VN00000104 | C42: ngoc.nguyenduyen@mapactive.vn | D42: Nguyễn Duyên Ngọc | E42: Nguyen Duyen Ngoc | G42: Business Development | H42: Business Development Manager | I42: E3 | J42: VN | K42: Office | L42: 45174 | M42: Done | N42: No need | O42: 5430 | P42: Done | Q42: Done | R42: Thay anh Hiếu BD (hieu.trantrung)last day ngày 31/08 dùng lại laptop | S42: Business Development Manager
A43: 43 | B43: 22VN00000028 | C43: van.nghiemthihong@mapactive.vn | D43: Nghiêm Thị Hồng Vân | E43: Nghiem Thi Hong Van | G43: Brand Department | H43: Senior Merchandise | I43: E3 | J43: VN | K43: Office | L43: 45214
A44: 44 | B44: 22VN00000052 | C44: xuan.vothihoanganh@mapactive.vn | D44: Võ Thị Hoàng Ánh Xuân | E44: Vo Thi Hoang Anh Xuan | G44: Operations | H44: Operations Executive | I44: E3 | J44: VN | K44: Office | L44: 45218 | M44: None | N44: No need | O44: 7490 | R44: Dùng lại máy ĐẶNG QUỐC TRÍ (OP)
A45: 45 | B45: 22VN00000039 | C45: tram.lengocbich@mapactive.vn | D45: Lê Ngọc BÍch Trâm | E45: Le Ngoc Bich Tram | G45: Marketing Department (Foot Locker) | H45: Marketing Supervisor (Foot Locker) | I45: E3 | J45: VN | K45: Office | L45: 45219 | M45: Done | N45: No need | O45: x280 | Q45: Done | R45: Replace Phạm Thị Mỹ Dung
A46: 46 | B46: 22VN00000051 | C46: mai.nguyenthihuynh@mapactive.vn | D46: Nguyễn Thị Huỳnh Mai | E46: Nguyen Thi Huynh Mai | F46: Maya | H46: Finance, Tax & Accounting Manager | I46: E3 | J46: VN | K46: Office | Q46: Done | R46: laptop cũ của Huỳnh Ngọc Sơn (team Project)
A47: 47 | B47: 22VN00000050 | C47: tuan.duongquangminh@mapactive.vn | D47: Dương Quang Minh Tuấn | E47: Duong Quang Minh Tuan | G47: Retail Operations Department | H47: Area Manager (South) | I47: E3 | J47: VN | K47: Office | L47: 45229 | N47: No need
A48: 48 | B48: 22VN00000053 | C48: dat.volamminh@mapactive.vn | D48: Võ Lâm Minh Đạt | E48: Vo Lam Minh Dat | G48: Retail Operations Department | H48: Area Manager (South) | I48: E3 | J48: VN | K48: Office | L48: 45243 | M48: HR requested | N48: no need | O48: 5420 | R48: (Re-use Dang's Laptop)
A49: 49 | B49: 22VN00000067 | C49: minh.lengocbao@mapactive.vn | D49: Lê Ngọc Bảo Minh | E49: Le Ngoc Bao Minh | G49: Internal Audit & Business Process Assistant Manager | H49: Risk Management & Business Process | I49: E3 | J49: VN | K49: Office | L49: 45245 | M49: HR requested | N49: no need | O49: 5430
A50: 50 | B50: 22VN00000060 | C50: anh.nguyensi@mapactive.vn | D50: Nguyễn Sĩ Anh | E50: Nguyen Si Anh | G50: Operation | H50: Acting Area Manager (North Side) | I50: E3 | J50: VN | K50: Office | L50: 45273 | M50: HR requested | N50: no need | O50: 5430 | R50: Re-use Phùng Như Quỳnh's Laptop
A51: 51 | B51: 22VN00000077 | C51: chi.tranvukim@mapactive.vn | D51: Trần Vũ Kim Chi | E51: Tran Vu Kim Chi | F51: Christine | G51: Brand | H51: Brand Division Manager (Foot Locker) | I51: E3 | J51: VN | K51: Office | L51: 45293 | M51: Done | O51: 5430 | R51: Will re-used Vicky's laptop
A52: 52 | B52: 22VN00000063 | C52: trang.taquynh@mapactive.vn | D52: Tạ Quỳnh Trang | E52: Ta Quynh Trang | G52: COE Department | H52: COE Officer | I52: E3 | J52: VN | K52: Office | L52: 45376 | M52: Done | R52: Re-use laptop Le Minh Khang
A53: 53 | B53: 22VN00000032 | C53: uyen.vuxuan@mapactive.vn | D53: Vũ Xuân Uyên | E53: Vu Xuan Uyen | G53: Marketing | H53: Marketing officer | I53: F3 | J53: VN | K53: Office | L53: 45384 | M53: Done
A54: 54 | C54: minh.vanduc@mapactive.vn | D54: Văn Đức Minh | E54: Van Duc Minh | F54: Quavo | G54: IT | H54: IT | I54: F3 | J54: VN | K54: Office | L54: 45448 | M54: Done
A55: 55 | B55: 22VN00000052 | C55: nhung.nguyenthihong01@mapactive.vn | D55: Nguyễn Thị Hồng Nhung | E55: Nguyen Thi Hong Nhung | G55: Operation | H55: Area Manager (North) | I55: E3 | J55: VN | K55: Office | L55: 45467 | M55: Done
A56: 56 | B56: 22VN00000006 | C56: chau.lehongbao@mapactive.vn | D56: Lê Hồng Bảo Châu | E56: Le Hong Bao Chau | G56: Marketing | H56: Marketing Admin | I56: E3 | J56: VN | K56: Office | L56: 45482 | M56: Done
A57: 59 | B57: 22VN00000059 | C57: binh.nguyenmy@mapactive.vn | D57: Nguyễn Mỹ Bình | E57: Nguyen My Binh | G57: E-COMMERCE | H57: Digital Commercial Manager | I57: E3 | J57: VN | K57: Office | L57: 45796 | M57: Done | R57: Re-use laptop
A58: 61 | B58: 22VN00000064 | C58: ngan.vongocthanh@mapactive.vn | D58: Vo Ngoc Thanh Ngan | E58: Vo Ngoc Thanh Ngan | G58: Brand | H58: Intern | I58: E3 | J58: VN | K58: Office | L58: 45796 | M58: Done
A59: 63 | B59: 22VN00000105 | C59: uyen.nguyenhaphuong@mapactive.vn | D59: Nguyễn Hà Phượng Uyên | E59: Nguyen Ha Phuong Uyen | F59: Dory | G59: BOD (Finance) | H59: General Manager & Finance Controller | I59: E3 | J59: VN | K59: Office | S59: Senior General Manager
A60: 64 | B60: 22VN00000041 | C60: nhung.nguyenthituyet@mapactive.vn | D60: Nguyễn Thị Tyết Nhung | E60: Nguyen Thi Tuyet Nhung | G60: Brand | H60: Senior Merchandise | I60: E3 | J60: VN | K60: Office | L60: 45880 | M60: Done
A61: 65 | B61: 22VN00000034 | C61: giang.trana@mapactive.vn | D61: Trần A Giang | E61: Tran A giang | G61: Intern | H61: Intern | I61: F3 | J61: VN | K61: Office | L61: 45880
A62: 67 | B62: 22VN00000002 | C62: Doan.An@mapactive.vn | D62: Đoàn Thiên Hồ An | E62: Doan Thien Ho An | G62: E-COMMERCE | H62: Digital Marketing Manager | I62: E3 | J62: VN | K62: Office | L62: 45964 | M62: Done
A63: 68 | B63: 22VN00000047 | C63: Tuan.Coanh@mapactive.vn | D63: Co Anh Tuấn | E63: Co Anh Tuan | G63: Operation | H63: Area Manager (South)
A64: 69
A65: 70
A66: 71
A72: 1 | C72: thu.pham@mapactive.vn | D72: Phạm Nguyễn Minh Thư | E72: Pham Nguyen Minh Thu | G72: DSV | H72: Logs Coordinator DSV VN | J72: VN | K72: Warehouse
A73: 2 | C73: quan.vu@mapactive.vn | D73: Vũ Thái Quân | E73: Vu Thai Quan | G73: DSV | H73: OPS Manager DSV VN | I73: E3 | J73: VN | K73: Warehouse
A74: 3 | C74: ngoc.ngo@mapactive.vn | D74: Ngô Lê Bảo Ngọc | E74: Ngo Leo Bao Ngoc | G74: DSV | H74: Logs Coordinator DSV VN | J74: VN | K74: Warehouse
A75: 4 | C75: nguyen.thieu@mapactive.vn | D75: Nguyễn Gia Thiều | E75: Thieu Gia Nguyen | G75: DSV | H75: Logs Coordinator DSV VN | J75: VN | K75: Warehouse
A76: 5 | C76: mma.it@mapactive.vn | D76: MMA IT Vietnam | E76: MMA IT Vietnam | G76: IT | I76: E1 | J76: VN | K76: Shared | R76: IT shared email account for licensing (Owner: IT)
A77: 6 | C77: footlocker.vietnam@mapactive.vn | D77: Foot Locker Vietnam | E77: Foot Locker Vietnam | G77: Brand | I77: E1 | J77: VN | K77: Shared | R77: Foot Locker email for register with Ecom platforms (Owner: Brand - FL)
A78: 7 | C78: HR.Recruitment@mapactive.vn | D78: HR Recruitment | E78: HR Recruitment | G78: HR | I78: E1 | J78: VN | K78: Shared | R78: HR shared email account for recruitment, receive CV from candidates (Owner: HR)
A79: 8 | C79: dung.nguyenthiphuong@mapactive.vn | D79: Nguyễn Thị Phương Dung | E79: Nguyen Thị Phuong Dung | G79: Marketing Department | H79: Marketing Supervisor | I79: E3 | J79: VN | K79: Office | L79: 45240 | M79: HR requested | N79: no need | O79: 3520
A80: 9 | C80: mma.hotline@mapactive.vn | D80: MMA HOTLINE | E80: MMA HOTLINE | G80: HR | I80: E1 | J80: VN | K80: Shared
A81: 10 | C81: mac.hotline@mapactive.kh | D81: MAC HOTLINE | E81: MAC HOTLINE | G81: HR | I81: E1 | J81: KH | K81: Shared
A82: 11 | C82: mma.hotline@mapactive.vn | D82: Lưu Giang Cẩm Vân | E82: Luu Giang Cam Van | F82: Vicky | H82: HR & Admin Manager | I82: F3 | J82: VN | K82: Office | L82: 45250
A83: 12 | C83: mac.hotline@mapactive.kh | E83: TO HO | H83: HR & Admin Manager | I83: F3 | J83: KH | K83: Office | L83: 45250

Sheet Office_Resigned
A1: Disable Email | B1: No. | C1: Assigned Asset | D1: Email Address | E1: Full Name | F1: Display Name | G1: English Name | H1: Department | I1: JOB TITLE | J1: O365 license | K1: Country | L1: Type | M1: Onboarding Date (dd/mm/yy) | N1: Request email | O1: Purchasing Request | P1: Laptop model | Q1: Laptop delivery | R1: Handover to user | S1: Notes | T1: MAP Level
A3: Request ITSD, IT Server Operation on 23 Feb 2023 (Ticket : WO0000000107284) | B3: 1 | D3: alun.hughes@mapactive.vn | F3: Alun Hughes | J3: Exchange Online Kiosk
A4: Need to check with anh Nhân Log | B4: =B3+1 -> 2 | D4: loan.lethikim@mapactive.vn | I4: Shipping Executive | J4: E3 | M4: 15/02/2023 | N4: Done | P4: 3520 | Q4: Done | R4: Done | S4: đã nghỉ việc
A5: Done | B5: =B4+1 -> 3 | D5: ngoc.voleminh@mapactive.vn | I5: Logistics Manager | J5: E3 | S5: đã nghỉ việc | T5: Manager
A6: Done | B6: =B5+1 -> 4 | D6: trung.lehominh@mapactive.vn | E6: Lê Hồ Minh Trung | F6: Le Ho Minh Trung | H6: Digital | I6: Digital Commercial Senior Manager | J6: E3 | K6: VN | M6: 03/04/2023 | N6: Done | O6: Done | P6: 5430 | S6: đã nghỉ việc
A7: Done | B7: =B6+1 -> 5 | D7: tram.nguyhuynhmai@mapactive.vn | E7: Ngụy Huỳnh Mai Trâm | F7: Nguy Huynh Mai Tram | H7: Logistic | I7: Logistic Admin | J7: E3 | K7: VN | M7: 14/04/2023 | S7: đã nghỉ việc | T7: Associate
A8: Done | B8: =B7+1 -> 6 | D8: nhung.nguyenhong@mapactive.vn | E8: Nguyễn Hồng Nhung | F8: Nguyen Hong Nhung | H8: Training | I8: Training Assistant Manager | J8: E3 | K8: VN | M8: 14/04/2023 | S8: đã nghỉ việc | T8: Associate Manager
A9: Done | B9: =B8+1 -> 7 | D9: ha.dangthivan@mapactive.vn | E9: Đặng Thị Vân Hà | F9: Dang Thi Van Ha | H9: Merchandise | I9: Merchandise | K9: VN | M9: 14/04/2023 | S9: đã nghỉ việc
A10: Done | B10: =B9+1 -> 8 | D10: hau.lenguyentrung@mapactive.vn | E10: Lê Nguyễn Trung Hậu | F10: Le Nguyen Trung Hau | H10: Merchandise | I10: Visual Merchandise Supervisor | K10: VN | M10: 17/04/2023 | N10: Done | O10: Done | P10: 5430 (swap for Henry) | S10: đã nghỉ việc
A11: Done | B11: =B10+1 -> 9 | D11: do.nguyentri@mapactive.vn | E11: Nguyễn Trí Độ | F11: Nguyen Tri Do | H11: Accounting | I11: General Accounting | J11: E3 | K11: VN | M11: 03/04/2023 | N11: Done | O11: Done | P11: 5430 | S11: đã nghỉ việc
A12: Done | B12: =B11+1 -> 10 | D12: nghia.letrong@mapactive.vn | E12: Lê Trọng Nghĩa | F12: Le Trong Nghia | H12: Training | I12: Training Assistant Manager | K12: VN | M12: 24/04/2023 | N12: Done | O12: Done | P12: Re use Laptop Chị Nhung | Q12: Re use Laptop Chị Nhung | S12: đã nghỉ việc
A13: Done | B13: =B12+1 -> 11 | D13: duong.nguyenthihai@mapactive.vn | I13: Internal Audit & Business Process Assistant Manager | J13: E3 | K13: VN | M13: 01/03/2023 | N13: Done | O13: Done | P13: 5430 | Q13: Done | R13: Done | S13: đã nghỉ việc
A14: Done | B14: =B13+1 -> 12 | D14: thuy.dangtranthu@mapactive.vn | I14: Marketing Executive | J14: E3 | K14: VN | M14: 14/07/2023 | N14: Done | O14: Done | P14: 3520 | S14: Disable email after 09/2023 | T14: Executive
A15: Done | B15: =B14+1 -> 13 | D15: son.vuxuan@mapactive.vn | E15: Vũ Xuân Sơn | F15: Vu Xuan Son | H15: Marketing Department | I15: Graphic Designer (Foot Locker) | K15: vn | M15: 15/06/2023 | N15: Done | O15: Done | S15: đã nghỉ việc
A16: Need to keep until end of Oct-2023 | B16: =B15+1 -> 14 | D16: giang.nguyenthiquynh@map.co.id | I16: Merchandiser | J16: E3 | K16: VN | S16: đã nghỉ việc | T16: Senior Executive
A17: Done | B17: =B16+1 -> 15 | D17: hieu.trantrung@mapactive.vn | I17: Business Development Manager | J17: E3 | K17: VN | S17: đã nghỉ việc | T17: Manager
A18: Need to keep until Ms Uyên Confirm | B18: =B17+1 -> 16 | D18: tri.dangquoc@mapactive.vn | I18: Retail Operations Manager | J18: E3 | K18: VN | S18: đã nghỉ việc | T18: Manager
A19: Can revoke license | B19: =B18+1 -> 17 | D19: hoang.phanbao@mapactive.vn | E19: Phan Bảo Hoàng | F19: Phan Bao Hoang | I19: Area Manager (South) | J19: E3 | K19: VN | S19: đã nghỉ việc | T19: Associate Manager
A20: Done | B20: =B19+1 -> 18 | D20: quynh.tranthilam@mapactive.vn | E20: Tran Thi Lâm Quỳnh | F20: Tran Thi lam Quynh | I20: Senior Merchandise | J20: E3 | K20: VN | S20: đã nghỉ việc | T20: Associate Manager
A21: Done | B21: =B20+1 -> 19 | D21: huong.tranquocthien@mapactive.vn | F21: Tran Quoc Thien Huong | I21: Senior Merchandise Planning Manager | J21: E3 | K21: VN | T21: Senior Manager
A22: Need to keep until Kelvin confirm (Oct-2023) | B22: =B21+1 -> 20 | D22: tien.phanthithuy@mapactive.vn | E22: Phan Thị Thủy Tiên | F22: Phan Thi Thuy Tiên | H22: Marketing | I22: Marketing officer | J22: E3 | K22: VN | M22: 8/5/2023 | N22: Done | O22: No need | P22: No need | S22: re-use Le Nguyen Trung Hau's Laptop
A23: done | B23: =B22+1 -> 21 | D23: vothea.iem@map.co.id | E23: Iem Vothea | F23: Iem Vothea | H23: Accounting | I23: Assistant Accountant Manager | J23: E3 | K23: KH | N23: Done | Q23: Done
A24: done | B24: =B23+1 -> 22 | D24: khoa.trandanganh@mapactive.vn | F24: Tran Dang Anh Khoa | I24: COE Officer | J24: E3 | K24: VN | T24: Associate
B25: 1 | D25: dung.phamthimy@mapactive.vn | E25: Phạm Thị Mỹ Dung | F25: Pham Thi My Dung | H25: Marketing Department | I25: Marketing Supervisor | J25: E3 | K25: VN | L25: `` | M25: 23/06/2023 | N25: Done | O25: Done | P25: 3520
A26: Done | B26: 2 | D26: ngan.huynhthibich@mpactive.vn | E26: Huỳnh Thị Bích Ngân | F26: Huynh Thi Bich Ngan | H26: Marketing Department | I26: Marketing Executive | J26: E3 | K26: VN | L26: Office | M26: 45270 | N26: Done | O26: No need | P26: x280 | R26: Done | S26: đã nghỉ việc 13/10/2023
A27: Waiting when HR Complete proccess resign | B27: 3 | C27: 22VN00000085 | D27: hieu.nguyenvutrung@mapactive.vn | E27: Nguyễn Vũ Trung Hiếu | F27: Nguyen Vu Trung Hieu | H27: Marketing Department | I27: Marketing Supervisor | J27: E3 | K27: VN | L27: Office | M27: 45140 | N27: Done | O27: Done | P27: 3520 | Q27: Done | R27: Done
A28: Done | B28: 4 | C28: 22VN00000047 | D28: dang.hohai@mapactive.vn | E28: Hồ Hải Đăng | F28: Ho Hai Dang | I28: Area Manager (South) | J28: E3 | K28: VN | L28: Office
A29: Done | B29: 5 | C29: 22VN00000075 | D29: quynh.phungnhu@mapactive.vn | E29: Phùng Như Quỳnh | F29: Phung Nhu Quynh | I29: Area Manager (North) | J29: E3 | K29: VN | L29: Office
A30: Need to keep until we have replacement | B30: 6 | C30: 22VN00000038 | D30: Trương Hồng Hương | E30: Truong Hong Huong | F30: Jolie | H30: Brand Manager (Birkenstock) | I30: E3 | J30: VN | K30: Office | S30: Senior Manager
A31: Done | B31: 7 | C31: 22VN00000086 | D31: quynh.nguyennhu@mapactive.vn | E31: Nguyễn Như Quỳnh | F31: Nguyen Nhu Quynh | H31: Brand Department | I31: Brand Manager (Bata) | J31: E3 | K31: VN | L31: Office | M31: 45152 | N31: Done | O31: Done | P31: 5430 | S31: BM for Bata, New Era
A32: Done | B32: 22 | C32: 22VN00000029 | D32: Tram.phamthibao@mapactive.vn | E32: Phạm Thị Bảo Trâm | F32: Pham Thi Bao Tram | I32: Marketing officer | J32: E3 | K32: VN | L32: Office | T32: Associate
B33: 11 | C33: 22VN00000026 | D33: dat.tranquoc@mapactive.vn | E33: Trần Quốc Đạt | F33: Tran Quoc Dat | I33: IT Officer | J33: E3 | K33: VN | L33: Office | T33: Senior Associate
A34: Done | C34: 22VN00000049 | D34: phong.phanhoai@mapactive.vn | E34: Phan Hoài Phong | F34: Phan Hoai Phong | H34: Marketing Department | I34: Visual Merchandise Executive | J34: E3 | K34: VN | L34: Office | M34: 45078 | N34: Done | O34: No need | P34: 3520
A35: Done | C35: 22VN00000068 | D35: my.tranthitoan@mapactive.vn | E35: Trần Thị Toàn Mỹ | F35: Tran Thi Toan My | I35: Senior Planning Merchandise | J35: E3 | K35: VN | L35: Office | M35: 45012 | N35: Done | O35: Done | P35: 3520 | Q35: Done | R35: Done
B36: =Office_Resigned!A57+1 -> 19 | C36: 22VN00000052 | D36: tra.truongvantin@mapactive.vn | E36: Trương Văn tín Trà | F36: Truong Van Tin Tra | I36: Project Supervisor | J36: E3 | K36: VN | L36: Office | T36: Senior Executive
B37: 32 | C37: 22VN00000040 | D37: tien.trantrung@mapactive.vn | E37: Trần Trung Tiến | F37: Tran Trung Tien | H37: Merchandise | I37: Senior Merchandise | J37: E3 | K37: VN | L37: Office | M37: 45012 | N37: Done | O37: No need | P37: 3520 | Q37: No need | R37: Done | S37: Replace Diệp team Ms. Jolie will resign on 10/04. Provide temporary MiniPC to use
B38: =Office_Resigned!A64+1 -> 20 | C38: 22VN00000009 | D38: hoa.mailecam@mapactive.vn | E38: Mai Lê Cẩm Hòa | F38: Mai Le Cam Hoa | G38: Mia | I38: Retail Admin Executive | J38: E3 | K38: VN | L38: Office | T38: Senior Executive
B39: =Office_Resigned!B45+1 -> #VALUE! | C39: 22VN00000094 | D39: minh.letranthien@mapactive.vn | E39: Lê Trần Thiên Minh | F39: Le Tran Thien Minh | H39: Operations Department | I39: Retail Operations Division Manager | J39: E3 | K39: VN | L39: Office | M39: 45136 | N39: Done | O39: Done | P39: 5430
B40: =VN_Emails!A26+1 -> 27 | C40: 22VN00000039 | D40: linh.thainhat@mapactive.vn | E40: Thái Nhật Linh | F40: Thai Nhat Linh | I40: Merchandiser | J40: E3 | K40: VN | L40: Office | T40: Senior Executive
B41: =Office_Resigned!A48+1 -> 21 | C41: 22VN00000062 | D41: loan.nguyenhoang@mapactive.vn | E41: Nguyễn Hoàng Loan | F41: Nguyen Hoang Loan | I41: Project Supervisor | J41: E3 | K41: VN | L41: Office | M41: 44984 | N41: Done | O41: Done | P41: 3520 | Q41: Done | R41: Done
A42: Done | B42: =VN_Emails!#REF!+1 -> #REF! | D42: it.vn@mapactive.vn | E42: Nguyễn Phạm Duy Anh | F42: Nguyen Pham Duy Anh | H42: IT | I42: IT Officer | J42: F3 | K42: VN | L42: Office | M42: 45383 | N42: Done
B43: 22VN00000077 | C43: hien.nguyendo@mapactive.vn | D43: Nguyễn Đỗ Hiền | E43: Nguyen Do Hien | G43: Brand | H43: Merchandise Manager (Foot Locker) | I43: E3 | J43: VN | K43: Office | L43: 45075 | M43: Done | N43: done | O43: 5430
A44: Already disable email account and revoke lic | B44: 22VN00000084 | C44: huan.lenam@mapactive.vn | D44: Lê Nam Huân | E44: Le Nam Huan | G44: Training Department | H44: Training Executive | I44: E3 | J44: VN | K44: Office | L44: 45118 | M44: Done | N44: Done | O44: 3520
B45: 22VN00000083 | C45: nhung.nguyenthituyet@mapactive.vn | D45: Nguyễn Thị Tuyết Nhung | E45: Nguyen Thi Tuyet Nhung | G45: Planning Department | H45: Senior Merchandise Planning | I45: E3 | J45: VN | K45: Office | L45: 45124 | M45: Done | N45: Done | O45: 3520
A46: =Office_Resigned!A47+1 -> 44 | B46: 22VN00000064 | C46: Tuyet.tranthikim@mapactive.vn | D46: Trần Thị Kim Tuyết | E46: Tran Thi kim Tuyet | G46: Operations Department | H46: Retail Operations Division Manager (Foot Locker) | I46: E3 | J46: VN | K46: Office | L46: 45180 | M46: Done | N46: Done | O46: 5430 | P46: Done | Q46: Done
A47: =VN_Emails!A42+1 -> 43 | B47: 22VN00000090 | D47: Hoàng Thân Bảo Phúc | E47: Hoang Than Bao Phuc | G47: Marketing Department | H47: Marketing intern | I47: None | J47: VN | K47: Office | L47: 45176 | M47: None | N47: No need | O47: Mini PC
A48: =Office_Resigned!A64+1 -> 20 | C48: uyen.vuthuy@mapactive.vn | D48: Vũ Thùy Uyên | E48: Vu Thuy Uyen | H48: COE Officer | I48: E3 | J48: VN | K48: Office | L48: 44980 | M48: Done | N48: Done | O48: 3520 | P48: Done | Q48: Done
A49: =VN_Emails!A28+1 -> 29 | B49: 22VN00000010 | C49: trang.huynhthimy@mapactive.vn | D49: Huỳnh Thị Mỹ Trang | E49: Huynh Thi My Trang | H49: Retail Admin | I49: E3 | J49: VN | K49: Office | S49: Associate
A50: =VN_Emails!A33+1 -> 34 | B50: 22VN00000071 | C50: an.nguyenhuu@mapactive.vn | D50: Nguyễn Hữu An | E50: Nguyen Huu An | G50: IT | H50: IT Application & Analytic Associate Manager | I50: E3 | J50: VN | K50: Office | L50: 45026 | M50: Done | N50: Done | O50: 5430
A51: =Office_Resigned!A57+1 -> 19 | B51: 22VN00000025 | C51: hieu.phamtrung@mapactive.vn | D51: Phạm Trung Hiếu | E51: Pham Trung Hieu | H51: IT Infrastructure & Operations Manager | I51: E3 | J51: VN | K51: Office | S51: Manager
A52: =VN_Emails!A41+1 -> 42 | B52: 22VN00000087 | C52: dung.huynhkim@mapactive.vn | D52: Huỳnh Kim Dung | E52: Huynh Kim Dung | F52: Zoe | G52: Brand Department | H52: Senior Merchandise | I52: E3 | J52: VN | K52: Office | L52: 45159 | M52: Done | N52: Done | O52: 3520 | P52: Done | Q52: Done
A53: =VN_Emails!A54+1 -> 55 | B53: 22VN00000084 | C53: luong.lactuan@mapactive.vn | D53: Lạc Tuấn Lương | E53: Lac Tuan Luong | G53: Training Department | H53: Training Assistant | I53: F3 | J53: VN | K53: Office | L53: 45453 | M53: Done
A54: 19 | B54: 22VN00000066 | C54: tram.nguyenthibich@mapactive.vn | D54: Nguyễn Thị Bích Trâm | E54: Nguyen Thi Bich Tram | G54: SCM | H54: Shipping Officer | I54: E3 | J54: VN | K54: Office | L54: 44986 | M54: Done | N54: Done | O54: 3520 | P54: Done | Q54: Done | R54: Re-use the laptop of Lê Thị Kim Loan – Shipping Executive – On board 15/02/2023 but resigned about 2 days later
A55: =VN_Emails!#REF!+1 -> #REF! | B55: 22VN00000010 | C55: vy.huynhnguyenlan@mapactive.vn | D55: Huỳnh Nguyễn Lan Vy | E55: Huynh Nguyen Lan Vy | G55: Finance | H55: Accountant | I55: E3 | J55: VN | K55: Office | L55: 45484 | M55: Done
A56: =VN_Emails!A20+1 -> 21 | B56: 22VN00000068 | C56: van.phungboi@mapactive.vn | D56: Phùng Bội Vân | E56: Phung Boi Van | H56: Sales Online | I56: E3 | J56: VN | K56: Office | L56: 45596 | S56: Associate
A57: 18 | B57: 22VN00000094 | C57: thy.nguyenhoanganh@mapactive.vn | D57: Nguyễn Hoàng Anh Thy | E57: Nguyen Hoang Anh Thy | H57: Payable Accountant | I57: E3 | J57: VN | K57: Office | L57: 45597 | S57: Associate
A58: 19 | B58: 22VN00000095 | C58: binh.nguyenthihongminh | D58: Nguyen Thi Hong Minh Binh | E58: Nguyen Thi Hong Minh Binh | G58: MKT | H58: MKT | I58: F3 | J58: VN | K58: Office | L58: 45590
A59: 1 | B59: 22VN00000001 | C59: darryl.peacock@mapactive.vn | D59: Peacock Darryl James | E59: Peacock Darryl James | F59: Darryl | G59: BOD | H59: Country Manager | I59: E3 | J59: VN | K59: Office | S59: Vice President
A60: =VN_Emails!A81+1 -> 11 | B60: 22VN00000030 | C60: my.nguyenthao@mapactive.vn | D60: Nguyễn Thảo My | E60: Nguyen Thao My | G60: Marketing | H60: Marketing Executive | I60: E3 | J60: VN | K60: Office | L60: 45257 | M60: HR requested | N60: no need | O60: x280 | R60: re-use laptop Phan Thi Thuy Tien (AMMAVNITC000030)
A61: 26 | B61: 22VN00000082 | C61: duy.lehuynh@mapactive.vn | D61: Lê Huỳnh Duy | G61: Merchandise Department | H61: Senior Merchandiser (Foot Locker) | I61: E3 | J61: VN | K61: Office | L61: 45110 | M61: Done | N61: Done | O61: 3520
B62: 22VN00000095 | C62: tam.minh@mapactive.vn | D62: Võ Minh Tâm | E62: Vo Minh Tam | G62: Graphic Design Freelance | H62: Marketing | I62: F3 | J62: VN | K62: Office | L62: 45624 | M62: Done | N62: Done | O62: x280
A63: 25 | B63: 22VN00000003 | C63: trang.khongthithuy@mapactive.vn | D63: Khổng Thị Thùy Trang | E63: Khong Thi Thuy Trang | G63: Brand Department | H63: Senior Merchandise | I63: E3 | J63: VN | K63: Office | L63: 45110 | M63: Done | N63: Done
A64: =Office_Resigned!A57+1 -> 19 | B64: 22VN00000053 | C64: nam.vonguyenhoang@mapactive.vn | D64: Võ Nguyễn Hoàng Nam | E64: Vo Nguyen Hoang Nam | H64: Wholesale Associate Manager | I64: E3 | J64: VN | K64: Office | S64: Associate Manager
A65: 3 | B65: 22VN00000027 | C65: khen.hoanghong@mapactive.vn | D65: Hoàng Hồng Khen | E65: Hoang Hong Khen | F65: Kevin | H65: Marketing Communications Manager | I65: E3 | J65: VN | K65: Office | S65: Manager
A66: 28 | B66: 22VN00000032 | C66: Hong.lethikim@mapactive.vn | D66: Lê Thị Kim Hồng | E66: Le Thi Kim Hong | G66: Legal Department | H66: Legal Officer | I66: E3 | J66: VN | K66: Office | L66: 45180 | M66: Done | N66: No need | O66: 3420 | P66: Done | Q66: Done | R66: Dùng lại máy Trần Thị Lâm Quỳnh (MD)
A67: 45 | B67: 22VN00000022 | C67: coe.vn@mapactive.vn | D67: Trần Hồ Duy Tân | E67: Tran Ho Duy Tan | G67: COE | H67: COE Collaborator | I67: F3 | J67: VN | K67: Office | M67: Done
A68: 47 | B68: 22VN00000095 | C68: tam.minh@mapactive.vn | D68: Võ Minh Tâm | E68: Vo Minh Tam | G68: Graphic Design Freelance | H68: Marketing | I68: F3 | J68: VN | K68: Office | L68: 45601 | M68: Done
A69: =A68+1 -> 48 | B69: 22VN00000076 | C69: minh.vuba@mapactive.vn | D69: Vũ Bá Minh | E69: Vu Ba Minh | G69: Digital Department | H69: Digital Commercial Manager | I69: E3 | J69: VN | K69: Office | L69: 45075 | M69: Done | N69: done | O69: 5430
A70: 5 | B70: 22VN00000058 | C70: dai.lamhoangphuoc@mapactive.vn | D70: Lâm Hoàng Phước Đại | E70: Lam Hoang Phuoc Dai | H70: Digital Marketing Manager | I70: E3 | J70: VN | K70: Office | S70: Manager
A71: 69 | B71: 22VN00000009 | C71: hien.lethithu@mapactive.vn | D71: Lê Thị Thu Hiền | E71: Le Thi Thu Hien | G71: Finance | I71: F3 | J71: VN | K71: Office | L71: 45404 | M71: Done
A72: 63 | C72: linh.hoangdieu@mapactive.vn | D72: Hoàng Diệu Linh | E72: Hoang Dieu Linh | G72: Operation | H72: Acting Area Manager (North Side) | I72: E3 | J72: VN | K72: Office | L72: 45273 | M72: Done | N72: no need | O72: Need to check | R72: Need to check
A73: 27 | B73: 22VN00000034 | C73: my.nguyenthituyet@mapactive.vn | D73: Nguyễn Thị Tuyết My | E73: Nguyen Thi Tuyet My | H73: Merchandiser | I73: E3 | J73: VN | K73: Office | S73: Senior Executive
A74: 34 | B74: 22VN00000017 | C74: bao.nguyenthanh@mapactive.vn | D74: Nguyễn Thanh Bảo | E74: Nguyen Thanh Bao | G74: Logistic | H74: Warehouse & Distribution Officer | I74: E3 | J74: VN | K74: Office | L74: 45015 | M74: Done | N74: No need | O74: No need | P74: No need | Q74: Done | R74: Replace Ngụy Huỳnh Mai Trâm will resign on 14/04/2023. Provide temporary MiniPC to use
A75: 60 | B75: 22VN00000023 | C75: thai.huynhquang@map.co.id | D75: Huynh Quang Thai | E75: Huynh Quang Thai | G75: HR | H75: Intern | I75: F3 | J75: VN | K75: Office | L75: 45810 | M75: Done
A76: 57 | B76: 22VN00000011 | C76: Ngoc.nguyenbao@mapactive.vn | D76: Nguyễn Bảo Ngọc | E76: Nguyen Bao Ngoc | F76: Kelly | G76: Operation | H76: Division Operation Manager | I76: E3 | J76: VN | K76: Office | L76: 45509 | M76: Done
A77: 18 | B77: 22VN00000007 | C77: trinh.vanhuynhtu@mapactive.vn | D77: Văn Huỳnh Tú Trinh | E77: Van Huynh Tu Trinh | H77: Receivable Accountant | I77: E3 | J77: VN | K77: Office | S77: Associate
A78: 58 | B78: 22VN00000043 | C78: thu.nguyenthiminh@mapactive.vn | D78: Nguyễn Thị Minh Thư | E78: Nguyen Thi Minh Thu | G78: Brand | H78: Planning | I78: E3 | J78: VN | K78: Office | L78: 45558 | M78: Done
A79: 66 | B79: 22VN00000074 | C79: hai.nguyenthanh@mapactive.vn | D79: Nguyễn Thanh Hải | E79: Nguyen Thanh Hai | G79: Intern | H79: Intern | I79: F3 | J79: VN | K79: Office | L79: 45880
A80: 57 | B80: 22VN00000011 | C80: Ngoc.nguyenbao@mapactive.vn | D80: Nguyễn Bảo Ngọc | E80: Nguyen Bao Ngoc | F80: Kelly | G80: Operation | H80: Division Operation Manager | I80: E3 | J80: VN | K80: Office | L80: 45509 | M80: Done

Sheet Brand Code
A1: No. | B1: Brand Name | C1: Brand Code
A2: 1 | B2: Birkenstock | C2: BCK
A3: =A2+1 -> 2 | B3: Converse | C3: CON
A4: =A3+1 -> 3 | B4: Champion | C4: CMP
A5: =A4+1 -> 4 | B5: Foot Locker | C5: VO
A6: =A5+1 -> 5 | B6: New Balance | C6: NB
A7: =A6+1 -> 6 | B7: New Era | C7: NRA
A8: =A7+1 -> 7 | B8: Rookie | C8: HAD
A9: =A8+1 -> 8 | B9: Smiggle | C9: IGL
A10: =A9+1 -> 9 | B10: Planet Sports | C10: PS

Sheet Warehosue mail
A1: No | B1: Email Address | C1: Full Name | D1: Display Name | E1: Hostname | G1: No | H1: Email Address | I1: Full Name | J1: Display Name | K1: Hostname
A2: 1 | B2: vnwh.admininbound1@mapactive.vn | C2: vnwh.admininbound1 | D2: DSV - Admin (Inbound) 1 | E2: AMMAVNWHD000001 | G2: 1 | H2: Geodis.cs1@mapactive.vn | I2: Geodis.cs1 | J2: Geodis cs1
A3: 2 | B3: vnwh.adminoutbound1@mapactive.vn | C3: vnwh.adminoutbound1 | D3: DSV - Admin (Outbound) 1 | G3: 2 | H3: Geodis.cs2@mapactive.vn | I3: Geodis.cs2 | J3: Geodis cs2
A4: 3 | B4: vnwh.inventory1@mapactive.vn | C4: vnwh.inventory1 | D4: DSV - Admin (Inventory) 1 | G4: 3 | H4: Geodis.cs3@mapactive.vn | I4: Geodis.cs3 | J4: Geodis cs3
A5: 4 | B5: vnwh.management1@mapactive.vn | C5: vnwh.management1 | D5: DSV - Management 1 | E5: AMMAVNWHC000008 | G5: 4 | H5: Geodis.inbound1@mapactive.vn | I5: Geodis.inbound1 | J5: Geodis inbound1
A6: 5 | B6: vnwh.operation1@mapactive.vn | C6: vnwh.operation1 | D6: DSV - Operation 1 | G6: 5 | H6: Geodis.inbound2@mapactive.vn | I6: Geodis.inbound2 | J6: Geodis inbound2
A7: 6 | B7: vnwh.operation2@mapactive.vn | C7: vnwh.operation2 | D7: DSV - Operation 2 | G7: 6 | H7: Geodis.outobund1@mapactive.vn | I7: Geodis.outobund1 | J7: Geodis outbound1
A8: 7 | B8: vnwh.operation3@mapactive.vn | C8: vnwh.operation3 | D8: DSV - Operation 3 | G8: 7 | H8: Geodis.outbound2@mapactive.vn | I8: Geodis.outbound2 | J8: Geodis outbound2
A9: 8 | B9: vnwh.operation4@mapactive.vn | C9: vnwh.operation4 | D9: DSV - Operation 4
A10: 9 | B10: vnwh.operation5@mapactive.vn | C10: vnwh.operation5 | D10: DSV - Operation 5
A11: 10
A12: 11
A13: 12
A14: 13
A15: 14

Sheet Store_Info_VN
A1: No. | B1: Store code | C1: Store Name | D1: Status | E1: Location | F1: City | G1: Region | H1: Brand Name | I1: Address | J1: PC Type | K1: Store Type | L1: FW status | M1: Internet Line | N1: ISP | O1: Shared PC detail | P1: O2O | Q1: O2O Multi Warehouse | R1: Traffic Counter | S1: Email | T1: Open date | U1: Total Area (sqm) | V1: Sell Area (sqm) | W1: Notes | X1: Notes - O2O | Y1: Ops Active Stores
A2: 1 | B2: PO02 | C2: PLANET SPORTS VINCOM DONG KHOI | D2: Close | E2: VINCOM DONG KHOI | F2: Ho Chi Minh City | G2: South | H2: Planet Sports | I2: B1 Vincom Dong Khoi , 72 Le Thanh Ton, Ben Nghe Ward , District 1 , Ho Chi Minh City | J2: MultiPC | K2: Stand Alone | L2: No Need | M2: Yes | R2: None | S2: hcmpo02@mapactive.vn | T2: 43586 | U2: 363.7 | V2: 226.7 | W2: IT BACKUP | Y2: =NOT(ISERROR(MATCH(B2,#REF!,0))) -> FALSE
A3: =A2+1 -> 2 | B3: VC01 | C3: CHAMPION VINCOM DONG KHOI | D3: Close | E3: VINCOM DONG KHOI | F3: Ho Chi Minh City | G3: South | H3: Champion | I3: B1 Vincom Dong Khoi , 72 Le Thanh Ton, Ben Nghe Ward , District 1 , Ho Chi Minh City | J3: Stand Alone | K3: Stand Alone | L3: Share (PO02) | M3: Share (PO02) | R3: None | S3: hcmvc01@mapactive.vn | T3: 44072 | U3: 100 | V3: 82.8 | W3: IT BACKUP | Y3: =NOT(ISERROR(MATCH(B3,#REF!,0))) -> FALSE
A4: =A3+1 -> 3 | B4: VF02 | C4: BIRKENSTOCK VINCOM DONG KHOI | D4: Close | E4: VINCOM DONG KHOI | F4: Ho Chi Minh City | G4: South | H4: Birkenstock | I4: B1 Vincom Dong Khoi , 72 Le Thanh Ton, Ben Nghe Ward , District 1 , Ho Chi Minh City | J4: Stand Alone | K4: Stand Alone | L4: Share (PO02) | M4: Share (PO02) | R4: None | S4: hcmvf02@mapactive.vn | T4: 43586 | U4: 90 | V4: 72 | W4: IT BACKUP | Y4: =NOT(ISERROR(MATCH(B4,#REF!,0))) -> FALSE
A5: =A4+1 -> 4 | B5: VC02 | C5: CHAMPION TAKASHIMAYA | D5: Close | E5: TAKASHIMAYA | F5: Ho Chi Minh City | G5: South | H5: Champion | I5: L3 No 92-94 Nam Ky Khoi Nghia, Ben Nghe Ward, District 1, Ho Chi Minh City | J5: SharedPC | K5: Store In Store | L5: No need | M5: Share (VI02) | O5: VC02-VI02-KN05 | R5: None | S5: hcmvc02@mapactive.vn | T5: 44111 | U5: 45.9 | V5: 40.9 | Y5: =NOT(ISERROR(MATCH(B5,#REF!,0))) -> FALSE
A6: =A5+1 -> 5 | B6: VN03 | C6: CONVERSE TAKASHIMAYA | D6: Open | E6: TAKASHIMAYA | F6: Ho Chi Minh City | G6: South | H6: Converse | I6: L3 No 92-94 Nam Ky Khoi Nghia, Ben Nghe Ward, District 1, Ho Chi Minh City | J6: SharedPC | K6: Store In Store | L6: Share (VI02) | M6: Share (VI02) | O6: VN03-VR02 | R6: None | S6: hcmvn03@mapactive.vn | T6: 44501 | U6: 54 | V6: 49 | Y6: =NOT(ISERROR(MATCH(B6,#REF!,0))) -> FALSE
A7: =A6+1 -> 6 | B7: VR02 | C7: ROOKIE TAKASHIMAYA | D7: Open | E7: TAKASHIMAYA | F7: Ho Chi Minh City | G7: South | H7: Rookie | I7: L3 No 92-94 Nam Ky Khoi Nghia, Ben Nghe Ward, District 1, Ho Chi Minh City | J7: SharedPC | K7: Store In Store | L7: Share (VI02) | M7: Share (VI02) | O7: VN03-VR02 | R7: None | S7: hcmvr02@mapactive.vn | T7: 44501 | U7: 23 | V7: 23 | Y7: =NOT(ISERROR(MATCH(B7,#REF!,0))) -> FALSE
A8: =A7+1 -> 7 | B8: VI02 | C8: SMIGGLE TAKASHIMAYA | D8: Open | E8: TAKASHIMAYA | F8: Ho Chi Minh City | G8: South | H8: Smiggle | I8: L3 No 92-94 Nam Ky Khoi Nghia, Ben Nghe Ward, District 1, Ho Chi Minh City | J8: SharedPC | K8: Store In Store | L8: Need to deploy (FG-40F) | M8: Share (VI02) | O8: VC02-VI02-KN05 | R8: None | S8: hcmvi02@mapactive.vn | T8: 44069 | U8: 12 | V8: 12 | Y8: =NOT(ISERROR(MATCH(B8,#REF!,0))) -> FALSE
A9: =A8+1 -> 8 | B9: KN05 | C9: BIRKENSTOCK TAKASHIMAYA | D9: Close | E9: TAKASHIMAYA | F9: Ho Chi Minh City | G9: South | H9: Birkenstock | I9: L3 No 92-94 Nam Ky Khoi Nghia, Ben Nghe Ward, District 1, Ho Chi Minh City | J9: SharedPC | K9: Store In Store | L9: Share (VI02) | M9: Share (VI02) | O9: VC02-VI02-KN05 | R9: None | S9: hcmkn05@mapactive.vn | T9: 44153 | U9: 68.73 | V9: 57.26 | Y9: =NOT(ISERROR(MATCH(B9,#REF!,0))) -> FALSE
A10: =A9+1 -> 9 | B10: VI01 | C10: SMIGGLE ROBINS CRESCENT MALL | D10: Close | E10: CRESCENT MALL | F10: Ho Chi Minh City | G10: South | H10: Smiggle | I10: L4 (4F-11) 101 Ton Dat Tien, Tan Phu Ward, District 7, Ho Chi Minh City | J10: Stand Alone | K10: Store In Store | L10: No | M10: Yes | R10: None | S10: hcmvi01@mapactive.vn | T10: 44062 | U10: 32 | V10: 30 | Y10: =NOT(ISERROR(MATCH(B10,#REF!,0))) -> FALSE
A11: =A10+1 -> 10 | B11: VN05 | C11: CONVERSE CRESCENT MALL | D11: Open | E11: CRESCENT MALL | F11: Ho Chi Minh City | G11: South | H11: Converse | I11: L3 101 Ton Dat Tien, Tan Phu Ward, District 7, Ho Chi Minh City | J11: Stand Alone | K11: Stand Alone | L11: Need to deploy (FG-40F) | M11: Yes | P11: Yes | R11: Active | S11: hcmvn05@mapactive.vn | T11: 44568 | U11: 90.4 | V11: 71.4 | X11: Change O2O from BIEN HOA (VN18 old) to CRESENT MALL (VN05) | Y11: =NOT(ISERROR(MATCH(B11,#REF!,0))) -> FALSE
A12: =A11+1 -> 11 | B12: VC05 | C12: CHAMPION CRESCENT MALL | D12: Close | E12: CRESCENT MALL | F12: Ho Chi Minh City | G12: South | H12: Champion | I12: L2 101 Ton Dat Tien, Tan Phu Ward, District 7, Ho Chi Minh City | J12: Stand Alone | K12: Stand Alone | L12: Need to deploy (FG-40F) (missed budget) | M12: Yes | R12: None | S12: hcmvc05@mapactive.vn | T12: 44576 | U12: 83.42 | V12: 61.5 | Y12: =NOT(ISERROR(MATCH(B12,#REF!,0))) -> FALSE
A13: =A12+1 -> 12 | B13: VE05 | C13: NEW ERA CRESCENT MALL | D13: Close | E13: CRESCENT MALL | F13: Ho Chi Minh City | G13: South | H13: New Era | I13: L3 101 Ton Dat Tien, Tan Phu Ward, District 7, Ho Chi Minh City | J13: Stand Alone | K13: Stand Alone | L13: Need to deploy (FG-40F) | M13: Yes | R13: None | S13: Hcmve05@mapactive.vn | T13: 44576 | U13: 25.06 | V13: 25.06 | Y13: =NOT(ISERROR(MATCH(B13,#REF!,0))) -> FALSE
A14: =A13+1 -> 13 | B14: PO01 | C14: PLANET SPORTS VINCOM THAO DIEN | D14: Close | E14: VINCOM THAO DIEN | F14: Ho Chi Minh City | G14: South | H14: Planet Sports | I14: L1 161 Ha Noi Highway, Thao Dien Ward, District 2, Ho Chi Minh City | J14: MultiPC | K14: Stand Alone | L14: No need | M14: Yes | R14: None | S14: hcmpo01@mapactive.vn | T14: 43446 | U14: 363 | V14: 302 | Y14: =NOT(ISERROR(MATCH(B14,#REF!,0))) -> FALSE
A15: =A14+1 -> 14 | B15: KN01 | C15: BIRKENSTOCK ESTELLA | D15: Open | E15: ESTELLA | F15: Ho Chi Minh City | G15: South | H15: Birkenstock | I15: Floor 2-13B , 88 Song Hanh,An Phu Ward, Estella Place, District 2, Ho Chi Minh City | J15: Stand Alone | K15: Stand Alone | L15: Yes | M15: Yes | P15: Preparing | Q15: Lazada Planetsports Asia VN | R15: None | S15: hcmkn01@mapactive.vn | T15: 44153 | U15: 68.73 | V15: 57.26 | Y15: =NOT(ISERROR(MATCH(B15,#REF!,0))) -> FALSE
A16: =A15+1 -> 15 | B16: VI03 | C16: SMIGGLE ESTELLA | D16: Open | E16: ESTELLA | F16: Ho Chi Minh City | G16: South | H16: Smiggle | I16: Floor 1 , 88 Song Hanh,An Phu Ward, Estella Place, District 2, Ho Chi Minh City | J16: Stand Alone | K16: Stand Alone | L16: Need to deploy (FG-40F) | M16: Yes | R16: None | S16: hcmvi03@mapactive.vn | T16: 44226 | U16: 25 | V16: 25 | Y16: =NOT(ISERROR(MATCH(B16,#REF!,0))) -> FALSE
A17: =A16+1 -> 16 | B17: VC06 | C17: PLANET SPORTS GOLDCOAST NHA TRANG | D17: Close | E17: GOLDCOAST NHA TRANG | F17: NHA TRANG | G17: South | H17: Planet Sports | I17: Floor G, GoldCoast Mall, 01 Tran Hung Dao, Loc Tho, Nha Trang, Khanh Hoa | J17: Stand Alone | K17: Store In Store | M17: No | R17: None | S17: ntvc06@mapactive.vn | T17: 44211 | U17: 132.5 | V17: 117.5 | Y17: =NOT(ISERROR(MATCH(B17,#REF!,0))) -> FALSE
A18: =A17+1 -> 17 | B18: VN19 | C18: CONVERSE GOLDCOAST NHA TRANG | D18: Open | E18: GOLDCOAST NHA TRANG | F18: NHA TRANG | G18: South | H18: Converse | I18: Floor 2, GoldCoast Mall, 01 Tran Hung Dao, Loc Tho, Nha Trang, Khanh Hoa | J18: SharedPC | K18: Store In Store | L18: Need to deploy (FG-40F) | M18: Yes | O18: VI04-VN19 | R18: None | S18: ntvn19@mapactive.vn | T18: 44763 | U18: 82.2 | V18: 62.2 | Y18: =NOT(ISERROR(MATCH(B18,#REF!,0))) -> FALSE
A19: =A18+1 -> 18 | B19: VI04 | C19: SMIGGLE GOLDCOAST NHA TRANG | D19: Open | E19: GOLDCOAST NHA TRANG | F19: NHA TRANG | G19: South | H19: Smiggle | I19: Floor 2, GoldCoast Mall, 01 Tran Hung Dao, Loc Tho, Nha Trang, Khanh Hoa | J19: SharedPC | K19: Store In Store | M19: Share (VA04) | O19: VI04-VN19 | R19: None | S19: ntvi04@mapactive.vn | T19: 44763 | Y19: =NOT(ISERROR(MATCH(B19,#REF!,0))) -> FALSE
A20: =A19+1 -> 19 | B20: VN07 | C20: CONVERSE NGUYEN TRAI | D20: Open | E20: NGUYEN TRAI | F20: Ho Chi Minh City | G20: South | H20: Converse | I20: 124 Nguyen Trai, Ben Thanh Ward, District 1, Ho Chi Minh City | J20: Stand Alone | K20: Stand Alone | L20: Need to deploy (FG-40F) | M20: Yes | P20: Yes | R20: Active | S20: hcmvn07@mapactive.vn | T20: 44576 | U20: 98 | V20: 62 | Y20: =NOT(ISERROR(MATCH(B20,#REF!,0))) -> FALSE
A21: =A20+1 -> 20 | B21: VN02 | C21: CONVERSE LE VAN SY | D21: Close | E21: LE VAN SY | F21: Ho Chi Minh City | G21: South | H21: Converse | I21: 485 Le Van Sy ,Ward 12 , District 3, Ho Chi Minh City | J21: Stand Alone | K21: Stand Alone | L21: Need to deploy (FG-40F) | M21: Yes | P21: Yes | R21: Active | S21: hcmvn02@mapactive.vn | T21: 44562 | U21: 32 | V21: 32 | Y21: =NOT(ISERROR(MATCH(B21,#REF!,0))) -> FALSE
A22: =A21+1 -> 21 | B22: VN16 | C22: CONVERSE BA THANG HAI | D22: Open | E22: BA THANG HAI | F22: Ho Chi Minh City | G22: South | H22: Converse | I22: 152 Ba Thang Hai ,Ward 12, District 10, Ho Chi Minh City | J22: Stand Alone | K22: Stand Alone | L22: Need to deploy (FG-40F) | M22: Yes | P22: Yes | R22: Active | S22: hcmvn16@mapactive.vn | T22: 44652 | U22: 88 | V22: 54.7 | X22: Change O2O from PHAN VAN TRI (VN20 old) to BA THANG HAI (VN16) | Y22: =NOT(ISERROR(MATCH(B22,#REF!,0))) -> FALSE
A23: =A22+1 -> 22 | B23: VN09 | C23: CONVERSE AEON BINH DUONG | D23: Open | E23: AEON BINH DUONG | F23: Binh Duong | G23: South | H23: Converse | I23: Aeon Canary 01 Binh Duong Boulevard, Thuan An Town, Binh Duong | J23: Stand Alone | K23: Stand Alone | L23: Need to deploy (FG-40F) | M23: Yes | R23: Active | S23: hcmvn09@mapactive.vn | T23: 44666 | U23: 95.5 | V23: 74.2 | Y23: =NOT(ISERROR(MATCH(B23,#REF!,0))) -> FALSE
A24: =A23+1 -> 23 | B24: VN10 | C24: CONVERSE AEON BINH TAN | D24: Open | E24: AEON BINH TAN | F24: Ho Chi Minh City | G24: South | H24: Converse | I24: F26 , 1 Floor , Aeon Mall Binh Tan (01, 17A Street, Binh Tri Dong B Ward, Binh Tan District, Ho Chi Minh City) | J24: Stand Alone | K24: Stand Alone | L24: Need to deploy (FG-40F) | M24: Yes | R24: Active | S24: hcmvn10@mapactive.vn | T24: 44679 | U24: 60.27 | V24: 48.6 | Y24: =NOT(ISERROR(MATCH(B24,#REF!,0))) -> FALSE
A25: =A24+1 -> 24 | B25: VN13 | C25: CONVERSE VINCOM MY THO | D25: Close | E25: VINCOM MY THO TIEN GIANG | F25: My Tho City | G25: South | H25: Converse | I25: 1A Hung Vuong, Ward 1, My Tho City - Tien Giang | J25: Stand Alone | K25: Stand Alone | L25: No | M25: Yes | P25: Canceled | R25: Active | S25: tgvn13@mapactive.vn | T25: 44722 | U25: 72.6 | Y25: =NOT(ISERROR(MATCH(B25,#REF!,0))) -> FALSE
A26: =A25+1 -> 25 | B26: VN08 | C26: CONVERSE HAI BA TRUNG | D26: Open | E26: HAI BA TRUNG | F26: Ho Chi Minh City | G26: South | H26: Converse | I26: 243 Hai Ba Trung, Vo Thi Sau Ward, District 3, Ho Chi Minh City | J26: Stand Alone | K26: Stand Alone | L26: Need to deploy (FG-40F) | M26: Yes | P26: Yes | R26: Active | S26: hcmvn08@mapactive.vn | T26: 44736 | Y26: =NOT(ISERROR(MATCH(B26,#REF!,0))) -> FALSE
A27: =A26+1 -> 26 | B27: VC03 | C27: CHAMPION AEON HAI PHONG | D27: Close | E27: AEON HAI PHONG | F27: Hai Phong | G27: North | H27: Champion | I27: Floor 2 Aeon Mall Le Chan, 10 Vo Nguyen Giap, Du Hang Kenh, Le Chan, Hai Phong | J27: Stand Alone | K27: Store In Store | L27: No | M27: Yes | R27: None | S27: hpvc03@mapactive.vn | T27: 44179 | U27: 100 | V27: 84 | W27: IT BACKUP | Y27: =NOT(ISERROR(MATCH(B27,#REF!,0))) -> FALSE
A28: =A27+1 -> 27 | B28: VE01 | C28: NEW ERA AEON HAI PHONG | D28: Close | E28: AEON HAI PHONG | F28: Hai Phong | G28: North | H28: New Era | I28: Floor 2 Aeon Mall Le Chan, 10 Vo Nguyen Giap, Du Hang Kenh, Le Chan, Hai Phong | J28: Stand Alone | K28: Store In Store | L28: Share (VC03) | M28: Share (VC03) | R28: None | S28: hpve01@mapactive.vn | T28: 44179 | U28: 37 | V28: 30 | W28: IT BACKUP | Y28: =NOT(ISERROR(MATCH(B28,#REF!,0))) -> FALSE
A29: =A28+1 -> 28 | B29: VC04 | C29: PLANET SPORTS LOTTE HA NOI DEPARTMENT | D29: Open | E29: LOTTE HA NOI DEPARTMENT | F29: Ha Noi | G29: North | H29: Planet Sports | I29: Floor 3 54 Lieu Giai Street, Ngoc Khanh Ward, Ba Dinh District, Ha Noi | J29: Stand Alone | K29: Store In Store | L29: Need to deploy (FG-40F) | M29: Yes | R29: None | S29: hnvc04@mapactive.vn | T29: 44217 | U29: 127 | V29: 98.45 | Y29: =NOT(ISERROR(MATCH(B29,#REF!,0))) -> FALSE
A30: =A29+1 -> 29 | B30: VN06 | C30: CONVERSE LOTTE HA NOI DEPARTMENT | D30: Open | E30: LOTTE HA NOI DEPARTMENT | F30: Ha Noi | G30: North | H30: Converse | I30: Floor 3 54 Lieu Giai Street, Ngoc Khanh Ward, Ba Dinh District, Ha Noi | J30: Stand Alone | K30: Store In Store | L30: Share (VC04) | M30: Share (VC04) | R30: None | S30: hnvn06@mapactive.vn | T30: 44576 | U30: 57.1 | V30: 57.1 | Y30: =NOT(ISERROR(MATCH(B30,#REF!,0))) -> FALSE
A31: =A30+1 -> 30 | B31: VC08 | C31: CHAMPION AEON LONG BIEN | D31: Close | E31: AEON LONG BIEN | F31: Ha Noi | G31: North | H31: Champion | I31: T218 Aeon Mall Long Bien, No. 27 Co Linh Street, Long Bien Ward, Long Bien District, Ha Noi | J31: Stand Alone | K31: Store In Store | L31: No | M31: Yes | R31: None | S31: hnvc08@mapactive.vn | T31: 44548 | U31: 82.12 | V31: 56.8 | Y31: =NOT(ISERROR(MATCH(B31,#REF!,0))) -> FALSE
A32: =A31+1 -> 31 | B32: VE04 | C32: NEW ERA AEON LONG BIEN | D32: Close | E32: AEON LONG BIEN | F32: Ha Noi | G32: North | H32: New Era | I32: T218 Aeon Mall Long Bien, No. 27 Co Linh Street, Long Bien Ward, Long Bien District, Ha Noi | J32: Stand Alone | K32: Store In Store | M32: Share (VC08) | P32: No | R32: None | S32: hnve04@mapactive.vn | T32: 44548 | U32: 50 | V32: 40.5 | Y32: =NOT(ISERROR(MATCH(B32,#REF!,0))) -> FALSE
A33: =A32+1 -> 32 | B33: VN01 | C33: CONVERSE AEON LONG BIEN | D33: Close | E33: AEON LONG BIEN | F33: Ha Noi | G33: North | H33: Converse | I33: T217 Aeon Mall Long Bien, No. 27 Co Linh Street, Long Bien Ward, Long Bien District, Ha Noi | J33: Stand Alone | K33: Store In Store | L33: Need to deploy (FG-40F) | M33: Yes | R33: Active | S33: hnvn01@mapactive.vn | T33: 44533 | U33: 128.14 | V33: 90.68 | Y33: =NOT(ISERROR(MATCH(B33,#REF!,0))) -> FALSE
A34: =A33+1 -> 33 | B34: VE03 | C34: NEW ERA AEON HA DONG | D34: Open | E34: AEON HA DONG | F34: Ha Noi | G34: North | H34: New Era | I34: T228 Aeon Ha Dong, Hoang Van Thu Residential Area, Duong Noi Ward, Ha Dong District, Ha Noi | J34: Stand Alone | K34: Store In Store | L34: Need to deploy (FG-40F) | M34: Yes | P34: No | R34: None | S34: hnve03@mapactive.vn | T34: 44554 | U34: 40.77 | V34: 30.1 | Y34: =NOT(ISERROR(MATCH(B34,#REF!,0))) -> FALSE
A35: =A34+1 -> 34 | B35: VN04 | C35: CONVERSE AEON HA DONG | D35: Open | E35: AEON HA DONG | F35: Ha Noi | G35: North | H35: Converse | I35: T228 Aeon Ha Dong, Hoang Van Thu Residential Area, Duong Noi Ward, Ha Dong District, Ha Noi | J35: Stand Alone | K35: Store In Store | L35: Share (VE03) | M35: Share (VE03) | R35: Active | S35: hnvn04@mapactive.vn | T35: 44554 | U35: 70 | V35: 53.4 | Y35: =NOT(ISERROR(MATCH(B35,#REF!,0))) -> FALSE
A36: =A35+1 -> 35 | B36: VN17 | C36: CONVERSE SMART CITY | D36: Close | E36: VINCOM SMART CITY HN | F36: Ha Noi | G36: North | H36: Converse | I36: L1-24 Vincom Mega Mall Smart City, Tay Mo Ward,Nam Từ Liêm District, Ha Noi | J36: Stand Alone | K36: Stand Alone | L36: No | M36: Yes | R36: Inactive | S36: hnvn17@mapactive.vn | T36: 44679 | U36: 104.9 | V36: 84.4 | Y36: =NOT(ISERROR(MATCH(B36,#REF!,0))) -> FALSE
A37: =A36+1 -> 36 | B37: VN14 | C37: CONVERSE VINCOM ROYAL CITY | D37: Close | E37: VINCOM ROYAL CITY | F37: Ha Noi | G37: North | H37: Converse | I37: B1-R6-40 72A Nguyen Trai, Thanh Xuan, Hanoi | J37: Stand Alone | K37: Stand Alone | L37: Need to deploy (FG-40F) | M37: Yes | P37: Yes | R37: Active | S37: hnvn14@mapactive.vn | T37: 44742 | U37: 86.4 | V37: 67.9 | Y37: =NOT(ISERROR(MATCH(B37,#REF!,0))) -> FALSE
A38: =A37+1 -> 37 | B38: PO03 | C38: SPORT BAZAAR PHAM VAN THUAN DONG NAI | D38: Close | E38: BIEN HOA DONG NAI | F38: Vậy | G38: South | H38: SPORT BAZAAR | I38: 1324 Pham Van Thuan, Neighborhood 1, Tan Tien Ward, Bien Hoa, Dong Nai | J38: Stand Alone | K38: Stand Alone | L38: No need | M38: Yes | P38: Preparing | Q38: Lazada Planetsports Asia VN | R38: Active | S38: bhvn18@mapactive.vn | T38: 44865 | U38: 95 | V38: 65.5 | W38: At first (since 01 Sep 2023), changed from VN18 (CONVERSE PHAM VAN THUAN - bhvn18@mapactive.vn) to PO03 (PLANET SPORT PHAM VAN THUAN BH) Now need to change from PO03 (PLANET SPORT PHAM VAN THUAN BH) to ZV13 (SPORT BAZAAR PHAM VAN THUAN DONG NAI - VTZVZV13) | X38: Change O2O from BIEN HOA (VN18 old) to CRESENT MALL (VN05) | Y38: =NOT(ISERROR(MATCH(B38,#REF!,0))) -> FALSE
A39: =A38+1 -> 38 | B39: ZV14 | C39: SPORT BAZAAR PHAN VAN TRI HO CHI MINH | D39: Close | E39: PHAN VAN TRI | F39: Ho Chi Minh City | G39: South | H39: SPORT BAZAAR | I39: 356B Phan Van Tri, Ward 11, Binh Thanh District, Ho Chi Minh City | J39: Stand Alone | K39: Stand Alone | L39: No need | M39: Yes | P39: No | R39: Active | S39: hcmvn20@mapactive.vn | T39: 44890 | U39: 63.4 | V39: 54.4 | W39: At first (since 01 Sep 2023), changed from VN20 (CONVERSE PHAN VAN TRI - hcmvn20@mapactive.vn) to PO04 (PLANET SPORT PHAN VAN TRI) Now need to change from PO04 (PLANET SPORT PHAN VAN TRI) to ZV14 (SPORT BAZAAR PHAN VAN TRI HO CHI MINH - VTZVZV14) | X39: Change O2O from PHAN VAN TRI (VN20 old) to BA THANG HAI (VN16) | Y39: =NOT(ISERROR(MATCH(B39,#REF!,0))) -> FALSE
A40: =A39+1 -> 39 | B40: ZV07 | C40: Planet Sport Aeon Long Bien | D40: Open | E40: AEON LONG BIEN | F40: Ha Noi | G40: North | H40: SPORT BAZAAR | J40: Stand Alone (Laptop) | K40: Stand Alone | R40: None | S40: hanzv07@mapactive.vn | T40: 45444 | U40: #N/A | W40: Changed from POPUP EVENT (Gold Coast Nha Trang) | Y40: =NOT(ISERROR(MATCH(B40,#REF!,0))) -> FALSE
A41: =A40+1 -> 40 | B41: ZV08 | C41: PRIVATE SALE (Aeon Mall Binh Tan) | D41: Close | G41: South | I41: 11-13 Quang Trung, Quận Gò Vấp, Thành Phố Hồ Chí Minh | J41: Stand Alone | K41: PRIVATE SALE | L41: No need | M41: 4G | R41: None | Y41: =NOT(ISERROR(MATCH(B41,#REF!,0))) -> FALSE
A42: =A41+1 -> 41 | B42: ZV09 | C42: POPUP EVENT (Crescent Mall) | D42: Close | G42: South | I42: VN Head Office - 14th Floor, Lottery Tower, 77 Tran Nhan Ton, Ward 9, District 5, Ho Chi Minh City | J42: Stand Alone | K42: Event | L42: No need | M42: 4G | R42: None | U42: #N/A | Y42: =NOT(ISERROR(MATCH(B42,#REF!,0))) -> FALSE
A43: =A42+1 -> 42 | B43: H101 | C43: Head Office ARENA VN | D43: Open | G43: South | I43: VN Head Office - 14th Floor, Lottery Tower, 77 Tran Nhan Ton, Ward 9, District 5, Ho Chi Minh City | J43: SharedPC | K43: Bazaar | L43: SHARE OFFICE | M43: SHARE OFFICE | O43: H101-H102 | R43: None | U43: #N/A | Y43: =NOT(ISERROR(MATCH(B43,#REF!,0))) -> FALSE
A44: =A43+1 -> 43 | B44: H102 | C44: Head Office ARENA VN | D44: Open | G44: South | I44: VN Head Office - 14th Floor, Lottery Tower, 77 Tran Nhan Ton, Ward 9, District 5, Ho Chi Minh City | J44: SharedPC | K44: Bazaar | L44: SHARE OFFICE | M44: SHARE OFFICE | O44: H101-H102 | R44: None | U44: #N/A | Y44: =NOT(ISERROR(MATCH(B44,#REF!,0))) -> FALSE
A45: =A44+1 -> 44 | B45: ZW04 | C45: TIKI VF | D45: Open | G45: South | I45: VN Head Office - 14th Floor, Lottery Tower, 77 Tran Nhan Ton, Ward 9, District 5, Ho Chi Minh City | J45: SharedPC | K45: Bazaar | L45: SHARE OFFICE | M45: SHARE OFFICE | O45: ZW04-ZK04 | R45: None | U45: #N/A | Y45: =NOT(ISERROR(MATCH(B45,#REF!,0))) -> FALSE
A46: =A45+1 -> 45 | B46: ZK04 | C46: TIKI VK | D46: Open | F46: Ho Chi Minh City | G46: South | I46: VN Head Office - 14th Floor, Lottery Tower, 77 Tran Nhan Ton, Ward 9, District 5, Ho Chi Minh City | J46: SharedPC | K46: Bazaar | L46: SHARE OFFICE | M46: SHARE OFFICE | O46: ZW04-ZK04 | R46: None | U46: #N/A | Y46: =NOT(ISERROR(MATCH(B46,#REF!,0))) -> FALSE
A47: =A46+1 -> 46 | B47: ZK06 | C47: SHOPPEE VK | D47: Open | G47: South | I47: VN Head Office - 14th Floor, Lottery Tower, 77 Tran Nhan Ton, Ward 9, District 5, Ho Chi Minh City | J47: SharedPC | K47: Bazaar | L47: SHARE OFFICE | M47: SHARE OFFICE | O47: ZK06-ZV06-ZW06 | R47: None | U47: #N/A | Y47: =NOT(ISERROR(MATCH(B47,#REF!,0))) -> FALSE
A48: =A47+1 -> 47 | B48: ZV06 | C48: SHOPPEE VT | D48: Open | G48: South | I48: VN Head Office - 14th Floor, Lottery Tower, 77 Tran Nhan Ton, Ward 9, District 5, Ho Chi Minh City | J48: SharedPC | K48: Bazaar | L48: SHARE OFFICE | M48: SHARE OFFICE | O48: ZK06-ZV06-ZW06 | R48: None | U48: #N/A | Y48: =NOT(ISERROR(MATCH(B48,#REF!,0))) -> FALSE
A49: =A48+1 -> 48 | B49: ZW06 | C49: SHOPPEE VF | D49: Open | G49: South | I49: VN Head Office - 14th Floor, Lottery Tower, 77 Tran Nhan Ton, Ward 9, District 5, Ho Chi Minh City | J49: SharedPC | K49: Bazaar | L49: SHARE OFFICE | M49: SHARE OFFICE | O49: ZK06-ZV06-ZW06 | R49: None | U49: #N/A | Y49: =NOT(ISERROR(MATCH(B49,#REF!,0))) -> FALSE
A50: =A49+1 -> 49 | B50: ZV01 | C50: Tiki Consignment | D50: Open | G50: South | I50: VN Head Office - 14th Floor, Lottery Tower, 77 Tran Nhan Ton, Ward 9, District 5, Ho Chi Minh City | J50: SharedPC | K50: Bazaar | L50: SHARE OFFICE | M50: SHARE OFFICE | O50: ZV01-H103-H104 | R50: None | U50: #N/A | Y50: =NOT(ISERROR(MATCH(B50,#REF!,0))) -> FALSE
A51: =A50+1 -> 50 | B51: H103 | C51: MMA Head Office | D51: Open | G51: South | I51: VN Head Office - 14th Floor, Lottery Tower, 77 Tran Nhan Ton, Ward 9, District 5, Ho Chi Minh City | J51: SharedPC | K51: Bazaar | L51: SHARE OFFICE | M51: SHARE OFFICE | O51: ZV01-H103-H104 | R51: None | U51: #N/A | Y51: =NOT(ISERROR(MATCH(B51,#REF!,0))) -> FALSE
A52: =A51+1 -> 51 | B52: H104 | C52: SCRAP | D52: Open | G52: South | I52: VN Head Office - 14th Floor, Lottery Tower, 77 Tran Nhan Ton, Ward 9, District 5, Ho Chi Minh City | J52: SharedPC | K52: Bazaar | L52: SHARE OFFICE | M52: SHARE OFFICE | O52: ZV01-H103-H104 | R52: None | U52: #N/A | Y52: =NOT(ISERROR(MATCH(B52,#REF!,0))) -> FALSE
A53: =A52+1 -> 52 | B53: ZV05 | C53: LAZADA SPORT CONSIGNMENT VN | D53: Open | G53: South | I53: VN Head Office - 14th Floor, Lottery Tower, 77 Tran Nhan Ton, Ward 9, District 5, Ho Chi Minh City | J53: SharedPC | K53: Bazaar | L53: SHARE OFFICE | M53: SHARE OFFICE | O53: ZV05-H105-ZW05-ZK05 | R53: None | U53: #N/A | Y53: =NOT(ISERROR(MATCH(B53,#REF!,0))) -> FALSE
A54: =A53+1 -> 53 | B54: ZW05 | C54: LAZADA FASHION CONSIGNMENT VN | D54: Open | G54: South | I54: VN Head Office - 14th Floor, Lottery Tower, 77 Tran Nhan Ton, Ward 9, District 5, Ho Chi Minh City | J54: SharedPC | K54: Bazaar | L54: SHARE OFFICE | M54: SHARE OFFICE | O54: ZV05-H105-ZW05-ZK05 | R54: None | U54: #N/A | Y54: =NOT(ISERROR(MATCH(B54,#REF!,0))) -> FALSE
A55: =A54+1 -> 54 | B55: ZK05 | C55: LAZADA VK | D55: Open | G55: South | I55: VN Head Office - 14th Floor, Lottery Tower, 77 Tran Nhan Ton, Ward 9, District 5, Ho Chi Minh City | J55: SharedPC | K55: Bazaar | L55: SHARE OFFICE | M55: SHARE OFFICE | O55: ZV05-H105-ZW05-ZK05 | R55: None | U55: #N/A | Y55: =NOT(ISERROR(MATCH(B55,#REF!,0))) -> FALSE
A56: =A55+1 -> 55 | B56: H105 | C56: GWP A&P | D56: Open | G56: South | I56: VN Head Office - 14th Floor, Lottery Tower, 77 Tran Nhan Ton, Ward 9, District 5, Ho Chi Minh City | J56: SharedPC | K56: Bazaar | L56: SHARE OFFICE | M56: SHARE OFFICE | O56: ZV05-H105-ZW05-ZK05 | R56: None | U56: #N/A | Y56: =NOT(ISERROR(MATCH(B56,#REF!,0))) -> FALSE
A57: =A56+1 -> 56 | B57: VN24 | C57: CONVERSE BA CU VUNG TAU | D57: Close | E57: BA CU | F57: Vung Tau | G57: South | H57: Converse | I57: 179 Ba Cu, Ward 4, Vung Tau, Ba Ria - Vung Tau | J57: Stand Alone | K57: Stand Alone | L57: Need to deploy (FG-40F) | M57: YES | R57: Active | S57: vtgvn24@mapactive.vn | T57: 45000 | U57: 100 | Y57: =NOT(ISERROR(MATCH(B57,#REF!,0))) -> FALSE
A58: =A57+1 -> 57 | B58: VI06 | C58: SMIGGLE VAN HANH MALL | D58: Close | E58: VAN HANH MALL | F58: Ho Chi Minh City | G58: South | H58: Smiggle | I58: 11 Su Van Hanh, Ward 12, District 10, Ho Chi Minh City | J58: Stand Alone | K58: Stand Alone | L58: No | M58: YES | R58: None | S58: hcmvi06@mapactive.vn | T58: 44995 | Y58: =NOT(ISERROR(MATCH(B58,#REF!,0))) -> FALSE
A59: =A58+1 -> 58 | B59: VA02 | C59: NEW BALANCE TAKASHIMAYA | D59: Close | E59: TAKASHIMAYA | F59: Ho Chi Minh City | G59: South | H59: New Balance | I59: Unit #329-2 Level 3 - TAKASHIMAYA (No. 92-94 Nam Ky Khoi Nghia, Ben Nghe ward, district 1, Ho Chi Minh city) | J59: Stand Alone | K59: Store In Store | L59: Need to deploy (FG-40F) | M59: YES | R59: None | S59: Hcmva02@mapactive.vn | T59: 45017 | Y59: =NOT(ISERROR(MATCH(B59,#REF!,0))) -> FALSE
A60: =A59+1 -> 59 | B60: VA10 | C60: NEW BALANCE LOTTE HA NOI DEPARTMENT | D60: Open | E60: LOTTE HA NOI DEPARTMENT | F60: Ha Noi | G60: North | H60: New Balance | I60: B14.4F - LOTTE DEPARTMENT STORE (No. 54 Lieu Giai, Cong Vi Ward, Ba Dinh district, Ha Noi city) | J60: Stand Alone | K60: Store In Store | L60: Need to deploy (FG-40F) | M60: YES | R60: None | S60: Hanva10@mapactive.vn | T60: 45017 | U60: 56.6 | Y60: =NOT(ISERROR(MATCH(B60,#REF!,0))) -> FALSE
A61: =A60+1 -> 60 | B61: VE06 | C61: NEW ERA DIAMOND PLAZA | D61: Open | E61: DIAMOND PLAZA | F61: Ho Chi Minh City | G61: South | H61: New Era | I61: XA-32238 Level 3 - Diamond Plaza (No. 34 Le Duan street, Ben Nghe ward, district 1, Ho Chi Minh city) | J61: Stand Alone | K61: Store In Store | L61: Need to deploy (FG-40F) | M61: Yes | N61: VNPT | R61: None | S61: hcmve06@mapactive.vn | T61: 45029 | U61: 17.2 | Y61: =NOT(ISERROR(MATCH(B61,#REF!,0))) -> FALSE
A62: =A61+1 -> 61 | B62: VA06 | C62: NEW BALANCE CRESCENT MALL | D62: Open | E62: CRESCENT MALL | F62: Ho Chi Minh City | G62: South | H62: New Balance | I62: 3F-33 - Crescent Mall, 101 Tôn Dật Tiên, Phường Tân Hưng, Quận 7, Thành Phố Hồ Chí Minh. | J62: Stand Alone | K62: Store In Store | L62: Need to deploy (FG-40F) | M62: Yes | N62: VNPT | P62: Yes | Q62: New Balance Shopee MWH | R62: None | S62: hcmva06@mapactive.vn | T62: 45043 | Y62: =NOT(ISERROR(MATCH(B62,#REF!,0))) -> FALSE
A63: =A62+1 -> 62 | B63: VN27 | C63: CONVERSE CFS QUANG TRUNG | D63: Open | E63: 11-13 QUANG TRUNG GV | F63: Ho Chi Minh City | G63: South | H63: Converse | I63: 11-13 Quang Trung, Quận Gò Vấp, Thành Phố Hồ Chí Minh | J63: Stand Alone | K63: Multicashier | L63: Need to deploy (FG-40F) | M63: Yes | N63: VNPT | P63: Yes | R63: Active | S63: sgnvn27@mapactive.vn | T63: 45026 | Y63: =NOT(ISERROR(MATCH(B63,#REF!,0))) -> FALSE
A64: =A63+1 -> 63 | B64: VA22 | C64: NEW BALANCE 78 NGUYEN TRAI CAN THO | D64: Open | E64: 78 NGUYEN TRAI | F64: Can Tho | G64: South | H64: New Balance | I64: 78 Nguyen Trai Can Tho | J64: Stand Alone | K64: Stand Alone | L64: Need to deploy (FG-40F) | M64: Yes | P64: Preparing | Q64: Shopee Planetsports Asia VN | R64: Active | S64: Vcava22@mapactive.vn | U64: 100 | Y64: =NOT(ISERROR(MATCH(B64,#REF!,0))) -> FALSE
A65: =A64+1 -> 64 | B65: VN22 | C65: CONVERSE 78 NGUYEN TRAI CAN THO | D65: Open | E65: 78 NGUYEN TRAI | F65: Can Tho | G65: South | H65: Converse | I65: 78 Nguyen Trai Can Tho | K65: Stand Alone | L65: Share (VA22) | M65: Share (VA22) | R65: Active | S65: Vtgvn22@mapactive.vn | U65: 100 | Y65: =NOT(ISERROR(MATCH(B65,#REF!,0))) -> FALSE
A66: =A65+1 -> 65 | B66: VN11 | C66: CONVERSE IPH HN MALL | D66: Close | E66: IPH MALL | F66: Ha Noi | G66: North | H66: Converse | I66: 2-228 Indochina Plaza Hà Nội (IPH Mall) | J66: Stand Alone | K66: Stand Alone | L66: Need to deploy (FG-40F) | P66: Yes (to be Canceled) | R66: Active | S66: Hanvn11@mapactive.vn | U66: 96.41 | Y66: =NOT(ISERROR(MATCH(B66,#REF!,0))) -> FALSE
A67: =A66+1 -> 66 | B67: VA08 | C67: NEW BALANCE DIAMOND PLAZA | D67: Open | E67: DIAMOND PLAZA | F67: Ho Chi Minh City | G67: South | H67: New Balance | I67: XA-32239 Diamond Plaza (No. 34 Le Duan street, Ben Nghe ward, district 1, Ho Chi Minh city) | J67: Stand Alone | K67: Stand Alone | L67: Need to deploy (FG-40F) | R67: None | S67: Hcmva08@mapactive.vn | U67: 76.2 | Y67: =NOT(ISERROR(MATCH(B67,#REF!,0))) -> FALSE
A68: =A67+1 -> 67 | B68: KN09 | C68: BIRKENSTOCK CRESCENT MALL | D68: Open | E68: CRESCENT MALL | F68: Ho Chi Minh City | G68: South | H68: Birkenstock | I68: 2F-18B Crescent Mall (No. 101 Ton Dat Tien, Tan Phu Ward, District 7) | J68: Stand Alone | K68: Stand Alone | L68: Need to deploy (FG-40F) | P68: Preparing | Q68: Shopee Planetsports Asia VN | R68: None | S68: Sgnkn09@mapactive.vn | Y68: =NOT(ISERROR(MATCH(B68,#REF!,0))) -> FALSE
A69: =A68+1 -> 68 | B69: VA01 | C69: NEW BALANCE VAN HANH MALL | D69: Open | E69: VAN HANH MALL | F69: Ho Chi Minh City | G69: South | H69: New Balance | I69: 2-07B Van Hanh Mall | J69: Stand Alone | K69: Stand Alone | L69: Need to deploy (FG-40F) | P69: Yes | Q69: New Balance Shopee MWH | R69: None | S69: sgnva01@mapactive.vn | U69: 80.7 | Y69: =NOT(ISERROR(MATCH(B69,#REF!,0))) -> FALSE
A70: =A69+1 -> 69 | B70: VE12 | C70: NEW ERA LOTTE MALL | D70: Open | E70: LOTTE MALL | F70: Ha Noi | G70: North | H70: New Era | I70: 2F-240,241 lot - Lotte Mall (No. 683 Lac Long Quan street, Phu Thuong ward, Tay Ho district) | J70: Stand Alone | K70: Stand Alone | L70: Need to deploy (FG-40F) | P70: No | R70: None | S70: Hanve12@mapactive.vn | U70: 52 | Y70: =NOT(ISERROR(MATCH(B70,#REF!,0))) -> FALSE
A71: =A70+1 -> 70 | B71: VR12 | C71: ROOKIE LOTTE MALL | D71: Open | E71: LOTTE MALL | F71: Ha Noi | G71: North | H71: Rookie | I71: 3F-333 lot - Lotte Mall (No. 683 Lac Long Quan street, Phu Thuong ward, Tay Ho district) | J71: Stand Alone | K71: Stand Alone | L71: Need to deploy (FG-40F) | R71: None | S71: Hanvr12@mapactive.vn | U71: 65 | Y71: =NOT(ISERROR(MATCH(B71,#REF!,0))) -> FALSE
A72: =A71+1 -> 71 | B72: VN12 | C72: CONVERSE LOTTE MALL | D72: Open | E72: LOTTE MALL | F72: Ha Noi | G72: North | H72: Converse | I72: 2F-228 lot - Lotte Mall (No. 683 Lac Long Quan street, Phu Thuong ward, Tay Ho district) | J72: Stand Alone | K72: Stand Alone | L72: Need to deploy (FG-40F) | R72: Active | S72: Hanvn12@mapactive.vn | U72: 135 | Y72: =NOT(ISERROR(MATCH(B72,#REF!,0))) -> FALSE
A73: =A72+1 -> 72 | B73: VA12 | C73: NEW BALANCE LOTTE MALL | D73: Open | E73: LOTTE MALL | F73: Ha Noi | G73: North | H73: New Balance | I73: 2F-229 lot - Lotte Mall (No. 683 Lac Long Quan street, Phu Thuong ward, Tay Ho district) | J73: Stand Alone | K73: Stand Alone | L73: Need to deploy (FG-40F) | P73: No | R73: None | S73: Hanva12@mapactive.vn | U73: 96 | Y73: =NOT(ISERROR(MATCH(B73,#REF!,0))) -> FALSE
A74: =A73+1 -> 73 | B74: VA09 | C74: NEW BALANCE IPH MALL | D74: Close | E74: IPH MALL | F74: Ha Noi | G74: North | H74: New Balance | I74: Toà nhà IPH số 241 Xuân Thuỷ, phường Dịch Vọng Hậu, quận Cầu Giấy, Hà Nội | J74: Stand Alone | K74: Stand Alone | L74: Need to deploy (FG-40F) (missed budget) | P74: Canceled | R74: None | S74: HANVA09@mapactive.vn | U74: 121 | Y74: =NOT(ISERROR(MATCH(B74,#REF!,0))) -> FALSE
A75: =A74+1 -> 74 | B75: VO02 | C75: FOOTLOCKER LOTTE MALL | D75: Open | E75: LOTTE MALL | F75: Ha Noi | G75: North | H75: Foot Locker | I75: 2F-227 lot - Lotte Mall (No. 683 Lac Long Quan street, Phu Thuong ward, Tay Ho district) | J75: MultiPC | K75: Multicashier | L75: Yes | P75: Yes | R75: None | S75: hanvo02@mapactive.vn | U75: 654 | Y75: =NOT(ISERROR(MATCH(B75,#REF!,0))) -> FALSE
A76: =A75+1 -> 75 | B76: KN12 | C76: BIRKENSTOCK LOTTE MALL | D76: Open | E76: LOTTE MALL | F76: Ha Noi | G76: North | H76: Birkenstock | I76: 2F-233 lot - Lotte Mall (No. 683 Lac Long Quan street, Phu Thuong ward, Tay Ho district) | J76: Stand Alone | K76: Stand Alone | L76: Need to deploy (FG-40F) | R76: None | S76: HANKN12@mapactive.vn | Y76: =NOT(ISERROR(MATCH(B76,#REF!,0))) -> FALSE
A77: =A76+1 -> 76 | B77: VA11 | C77: NEW BALANCE 89 NGUYEN TRAI | D77: Open | E77: 89 NGUYỄN TRÃI | F77: Ho Chi Minh City | G77: South | H77: New Balance | I77: 89 Nguyen Trai Street, Ben Thanh Ward, District 1 | J77: Stand Alone | K77: Stand Alone | L77: Need to deploy (FG-40F) | P77: Yes | Q77: New Balance Lazada MWH | R77: None | S77: SGNVA11@mapactive.vn | U77: 102 | Y77: =NOT(ISERROR(MATCH(B77,#REF!,0))) -> FALSE
A78: =A77+1 -> 77 | B78: VA03 | C78: NEW BALANCE AEON HAI PHONG | D78: Open | E78: AEON HAI PHONG | F78: Hai Phong | G78: North | H78: Champion | I78: Floor 2 Aeon Mall Le Chan, 10 Vo Nguyen Giap, Du Hang Kenh, Le Chan, Hai Phong | J78: Stand Alone | K78: Stand Alone | L78: Need to deploy (FG-40F) | P78: No | R78: None | S78: HPHVA03@mapactive.vn | U78: 123.91 | Y78: =NOT(ISERROR(MATCH(B78,#REF!,0))) -> FALSE
A79: =A78+1 -> 78 | B79: VR05 | C79: ROOKIE LOTTE HA NOI DEPARTMENT | D79: Close | E79: LOTTE HA NOI DEPARTMENT | F79: Ha Noi | G79: North | H79: Rookie | I79: Floor 5, No 54 Lieu Giai Street, Ngoc Khanh Ward, Ba Dinh District, Ha Noi | K79: Store In Store | M79: 4G (Share with VI05) | R79: None | U79: 20 | Y79: =NOT(ISERROR(MATCH(B79,#REF!,0))) -> FALSE
A80: =A79+1 -> 79 | B80: VI05 | C80: SMIGGLE LOTTE HA NOI DEPARTMENT | D80: Close | E80: LOTTE HA NOI DEPARTMENT | F80: Ha Noi | G80: North | H80: Smiggle | I80: Floor 5, No 54 Lieu Giai Street, Ngoc Khanh Ward, Ba Dinh District, Ha Noi | K80: Store In Store | M80: 4G (Share with VR05) | R80: None | U80: 20 | Y80: =NOT(ISERROR(MATCH(B80,#REF!,0))) -> FALSE
A81: =A80+1 -> 80 | B81: KN08 | C81: BIRKEN DIAMOND PLAZA | D81: Open | E81: DIAMOND PLAZA | F81: Ho Chi Minh City | G81: South | H81: Birkenstock | I81: XA-32240 (34 Le Duan street, Ben Nghe ward, district 1, Ho Chi Minh city) | J81: Stand Alone | K81: Stand Alone | R81: None | S81: sgnkn08@mapactive.vn | T81: 45282 | U81: 40 | W81: ĐIỀU CHUYỂN TỪ PC VE01 | Y81: =NOT(ISERROR(MATCH(B81,#REF!,0))) -> FALSE
A82: =A81+1 -> 81 | B82: ZV11 | C82: Go Vap UIH | D82: Close | E82: Ung Van Khiem | F82: Ho Chi Minh City | G82: South | I82: VN Head Office - 14th Floor, Lottery Tower, 77 Tran Nhan Ton, Ward 9, District 5, Ho Chi Minh City | J82: SharedPC | K82: Bazaar | L82: SHARE OFFICE | M82: 4G | R82: None | U82: #N/A | Y82: =NOT(ISERROR(MATCH(B82,#REF!,0))) -> FALSE
A83: =A82+1 -> 82 | B83: KN10 | C83: BIRKEN STOCK GOLDCOAST NHA TRANG | D83: Open | E83: GOLDCOAST NHA TRANG | F83: NHA TRANG | G83: South | H83: Birkenstock | I83: Floor G, GoldCoast Mall, 01 Tran Hung Dao, Loc Tho, Nha Trang, Khanh Hoa | J83: Stand Alone | K83: Store In Store | M83: Share (VA04) | N83: VNPT | R83: None | S83: vfknkn10@mapactive.vn | T83: 45315 | Y83: =NOT(ISERROR(MATCH(B83,#REF!,0))) -> FALSE
A84: =A83+1 -> 83 | B84: VA04 | C84: NEW BALANCE GOLDCOAST NHA TRANG | D84: Open | E84: GOLDCOAST NHA TRANG | F84: NHA TRANG | G84: South | H84: New Balance | I84: Floor G, GoldCoast Mall, 01 Tran Hung Dao, Loc Tho, Nha Trang, Khanh Hoa | J84: Stand Alone | K84: Store In Store | L84: Need to deploy (FG-40F) | M84: Yes | N84: VNPT | R84: None | S84: vtvava04@mapactive.vn | T84: 45315 | Y84: =NOT(ISERROR(MATCH(B84,#REF!,0))) -> FALSE
A85: =A84+1 -> 84 | B85: VA05 | C85: NEW BALANCE VINCOM THAO DIEN | D85: Open | E85: VINCOM THAO DIEN | F85: Ho Chi Minh City | G85: South | H85: New Balance | I85: Floor 2, No. 161 Hanoi road, Thao Dien ward, Thu Duc city | J85: Stand Alone | K85: Stand Alone | P85: Yes | Q85: New Balance Lazada MWH | R85: Active | S85: sgnva05@mapactive.vn | U85: 115.7 | Y85: =NOT(ISERROR(MATCH(B85,#REF!,0))) -> FALSE
A86: =A85+1 -> 85 | B86: ZV12 | C86: Event Diamond Plaza | D86: Open | I86: VN Head Office - 14th Floor, Lottery Tower, 77 Tran Nhan Ton, Ward 9, District 5, Ho Chi Minh City | K86: Event | U86: #N/A | Y86: =NOT(ISERROR(MATCH(B86,#REF!,0))) -> FALSE
A87: =A86+1 -> 86 | B87: ZV10 | C87: Event Count down | D87: Close | G87: South | K87: Event | U87: #N/A | Y87: =NOT(ISERROR(MATCH(B87,#REF!,0))) -> FALSE
A88: =A87+1 -> 87 | B88: VA15 | C88: New Balance Sai Gon Center | D88: Open | E88: Saigon Center | F88: Ho Chi Minh City | G88: South | H88: New Balance | I88: 65 Le Loi, Ben Nghe Ward, District 1, HCMC, Viet Nam | J88: Stand Alone | K88: Stand Alone | L88: Yes | M88: Yes | N88: RVC | S88: sgnva15@mapactive.vn | T88: 45519 | U88: 125
A89: =A88+1 -> 88 | B89: VA16 | C89: New Balance Quang Trung | D89: Open | E89: Street shop | F89: Ho Chi Minh City | G89: South | H89: New Balance | I89: 159-161 Quang Trung, Ward 11, Go Vap District, HCMC, Viet Nam | J89: MultiPC | K89: Multicashier | L89: Yes | M89: Yes | N89: RVC | S89: sgnva16@mapactive.vn | T89: 45512 | U89: 296
A90: =A89+1 -> 89 | B90: VA13 | C90: New Balance Parc Mall | D90: Open | E90: Parc Mall | F90: Ho Chi Minh City | G90: South | H90: New Balance | I90: L2-09 Parc Mall - 549 Ta Quang Buu, Ward 4, District 8, HCMC, Viet Nam | J90: Stand Alone | K90: Stand Alone | L90: Yes | M90: Yes | N90: RVC | S90: sgnva13@mapactive.vn | T90: 45539 | U90: 87
A91: =A90+1 -> 90 | B91: VA20 | C91: New Balance Vincom Lotte Nam Sai Gon | D91: Open | E91: Lotte Mall Nam Sai Gon | F91: Ho Chi Minh City | G91: South | H91: New Balance | I91: Lotte Mart, 469 Đ. Nguyễn Hữu Thọ, Tân Hưng, Quận 7, Hồ Chí Minh 700000 | J91: MultiPC | K91: Multicashier | L91: Yes | M91: Yes | S91: sgnva20@mapactive.vn | T91: 45576
A92: =A91+1 -> 91 | B92: VA14 | C92: New Balance Vincom Vincom Dong Khoi | D92: Open | E92: Lotte Vincome Dong Khơi | F92: Ho Chi Minh City | G92: South | H92: New Balance | I92: 72 Le Thanh Ton, Ben Nghe Ward, District 1, HCMC, Viet Nam | J92: Stand Alone | K92: Stand Alone | L92: Yes | M92: Yes | S92: sgnva14mapactive.vn | T92: 45361 | U92: 100
B93: VA23 | C93: New Balance Lotte Lieu Giai | D93: Open | E93: Lotte Lieu Giai | F93: Ho Chi Minh City | G93: North | H93: New Balance | J93: SIS | K93: SIS | S93: hanva23@mapactive.vn

Sheet Lost Device

Sheet Naming_Policy
A1: No. | B1: Guideline Category | C1: Country | D1: Naming Category | E1: Device Category | F1: Template | G1: Example | H1: Notes
A2: 1 | B2: Naming invention | C2: Vietnam (VN) | D2: IT Asset ID | E2: Computer (Laptop/Desktop) | F2: 22VN0000XXXX
A3: =A2+1 -> 2 | E3: Store devices | F3: 22VN0011XXXX
A4: =A3+1 -> 3 | D4: Hostname | E4: Laptop - Windows | F4: AMMAVNZZCXXXXXX | G4: AMMAVNAMC000001 | H4: ZZ: Department Code XXXXXX: must match with last 6 digits of IT Asset ID
A5: =A4+1 -> 4 | E5: Desktop - Windows | F5: AMMAVNZZDXXXXXX | G5: AMMAVNAMD000001
A6: =A5+1 -> 5 | E6: Store devices | F6: VVVV-WWWWW | H6: VVVV: Store Code WWWWW: Device Code (SERVER, ADMIN, POS01, TABLET01, MPOS01, PDT01). Use ADMIN if the store only has 1 POS PC
A7: =A6+1 -> 6 | C7: Cambodia (KH) | D7: IT Asset ID | E7: Computer (Laptop/Desktop)
E8: Store devices
A9: =A7+1 -> 7 | D9: Hostname

Sheet Department_Code
A1: Department Code | B1: Department
A2: AC | B2: Accounting, Licensing, Tax
A3: AL | B3: Allocation
A4: AM | B4: Active Management
A5: AP | B5: Advertising and Promotion
A6: BD | B6: Business Development
A7: BP | B7: Business Process
A8: CE | B8: CoE
A9: CH | B9: Children
A10: CO | B10: Compliance
A11: CS | B11: Corporate Secretary
A12: DI | B12: Digital Initiatives
... A44: WS | B44: Wholesale

Sheet KH_Emails
A1: No. | B1: Email Address | C1: Assigned Asset | D1: Full Name | E1: Display Name | F1: English Name | G1: Department | H1: JOB TITLE | I1: O365 license | J1: Country | K1: Type | L1: Onboarding Date | M1: Request email | N1: Purchasing Request | O1: Laptop model | P1: Laptop delivery | Q1: Handover to user | R1: Notes | S1: MAP Level
A2: 1 | B2: ho.to@map.co.id | D2: To Ho | E2: To Ho | G2: HR | H2: Assistant HR Manager | I2: E3 | J2: KH | K2: Office | M2: Done | P2: Done | Q2: Done | R2: Deliver by SATATECH
A3: =A2+1 -> 2 | B3: ratheany.seng@map.co.id | D3: Seng Ratheany | E3: Seng Ratheany | G3: Operations | H3: General Operations Manager | I3: E3 | J3: KH | K3: Office | M3: Done | P3: Done | Q3: Done | R3: Deliver by SATATECH
A4: =A3+1 -> 3 | B4: sokim.thav@map.co.id | D4: Thav Sokim | E4: Thav Sokim | G4: IT | H4: IT Infrastructure Supervisor | I4: E3 | J4: KH | K4: Office | M4: Done | P4: Done | Q4: Done | R4: Deliver by SATATECH
A5: =A4+1 -> 4 | B5: panha.nol@map.co.id | D5: Nol Panha | E5: Nol Panha | G5: SCM | H5: Logistic Supervisor | I5: E3 | J5: KH | K5: Office | M5: Done | P5: Done
A6: =A5+1 -> 5 | B6: david.dy@map.co.id | D6: Dy David | E6: Dy David | G6: Project | H6: Assistant Project Manager | I6: E3 | J6: KH | K6: Office | M6: Done | P6: Done
A7: =A6+1 -> 6 | B7: Sreynoch.Sem@mapactive.kh | D7: Sem Sreynoch | E7: Sem Sreynoch | G7: Accounting | H7: Assistant Accountant Manager | I7: E3 | J7: KH | K7: Office | M7: Done | P7: No Need | Q7: Done
A8: 7 | B8: sin.kaknika@mapactive.kh | D8: Kaknika Sin | E8: Kaknika Sin | G8: Operation | H8: Operation Manager | I8: E3 | J8: VN | K8: Office | L8: 45509 | M8: Done
A9: =A8+1 -> 8 | J9: KH | K9: Warehouse
A10: =A9+1 -> 9 | J10: KH
A11: 8 | J11: KH

Sheet Asset_Warehouse
A1: No. | B1: Asset ID | C1: Status (formula) | D1: Assigned To (formula) | E1: JOB TITLE (formula) | F1: Hostname | G1: Old Hostname | H1: Location | I1: Asset Name (formula) | J1: Asset Type (formula) | K1: Brand | L1: Model | M1: S/N | N1: RAM (GB) | O1: Hard Disk (GB) | P1: Hard Disk Type | Q1: CPU | R1: Purchase Date | S1: Vendor/Supplier | T1: Note | U1: Assignment History | V1: Status BIGFIX | W1: STATUS Crowdstrike
A2: 1 | C2: In Use | D2: DSV VN | F2: MMA-DSV-001 | H2: Warehouse | I2: =K2&" "&L2 -> HP Prodesk 400 G7 | J2: Desktop | K2: HP | L2: Prodesk 400 G7 | M2: 4CE234DC94 | N2: 8 | O2: 512 | P2: SSD INTEL | Q2: Intel Core i5 10505 3.20ghz | V2: DONE | W2: DONE
A3: =A2+1 -> 2 | C3: In Use | D3: DSV VN | F3: MMA-DSV-002 | H3: Warehouse | I3: =K3&" "&L3 -> HP Prodesk 400 G7 | J3: Desktop | K3: HP | L3: Prodesk 400 G7 | M3: 4CE234DC8C | N3: 8 | O3: 512 | P3: SSD INTEL | Q3: Intel Core i5 10505 3.20ghz | V3: DONE | W3: DONE
A4: =A3+1 -> 3 | C4: In Use | D4: DSV VN | F4: MMA-DSV-003 | H4: Warehouse | I4: =K4&" "&L4 -> HP Prodesk 400 G7 | J4: Desktop | K4: HP | L4: Prodesk 400 G7 | M4: 4CE234DC6P | N4: 8 | O4: 512 | P4: SSD INTEL | Q4: Intel Core i5 10505 3.20ghz | V4: DONE | W4: DONE
A5: =A4+1 -> 4 | C5: In Use | D5: DSV VN | F5: MMA-DSV-004 | H5: Warehouse | I5: =K5&" "&L5 -> HP Prodesk 400 G7 | J5: Desktop | K5: HP | L5: Prodesk 400 G7 | M5: 4CE234DC92 | N5: 8 | O5: 512 | P5: SSD INTEL | Q5: Intel Core i5 10505 3.20ghz | V5: DONE | W5: DONE
A6: =A5+1 -> 5 | C6: In Use | D6: DSV VN | F6: MMA-DSV-005 | H6: Warehouse | I6: =K6&" "&L6 -> HP Prodesk 400 G7 | J6: Desktop | K6: HP | L6: Prodesk 400 G7 | M6: 4CE234DC5T | N6: 8 | O6: 512 | P6: SSD INTEL | Q6: Intel Core i5 10505 3.20ghz | V6: DONE | W6: DONE
A7: =A6+1 -> 6 | C7: In Use | D7: DSV VN | F7: MMA-DSV-006 | H7: Warehouse | I7: =K7&" "&L7 -> HP Prodesk 400 G7 | J7: Desktop | K7: HP | L7: Prodesk 400 G7 | M7: 4CE234DC9C | N7: 8 | O7: 512 | P7: SSD INTEL | Q7: Intel Core i5 10505 3.20ghz | V7: DONE | W7: DONE
A8: =A7+1 -> 7 | C8: In Use | D8: DSV VN | F8: MMA-DSV-007 | H8: Warehouse | I8: =K8&" "&L8 -> HP Prodesk 400 G7 | J8: Desktop | K8: HP | L8: Prodesk 400 G7 | M8: 4CE234DC69 | N8: 8 | O8: 512 | P8: SSD INTEL | Q8: Intel Core i5 10505 3.20ghz | V8: DONE | W8: DONE
A9: =A8+1 -> 8 | C9: In Use | D9: DSV VN | F9: MMA-DSV-008 | H9: Warehouse | I9: =K9&" "&L9 -> Dell Latitude 5430 | J9: Laptop | K9: Dell | L9: Latitude 5430 | M9: DFHLRQ3 | N9: 16 | O9: 500 | P9: SSDM2 PCLE | Q9: Intel Core i5 1235U 3.20ghz | V9: DONE | W9: DONE
A10: =A9+1 -> 9 | C10: In Use | D10: DSV VN | F10: MMA-DSV-009 | H10: Warehouse | I10: =K10&" "&L10 -> HP Prodesk 400 G7 | J10: Desktop | K10: HP | L10: Prodesk 400 G7 | M10: 4CE234DC77 | N10: 8 | O10: 512 | P10: SSD WDC PC SN530 | Q10: Intel Core i5 10505 3.20ghz | V10: DONE | W10: DONE

Sheet MeetingRoom
A1: No. | B1: Display Name | C1: Room Email Account | D1: Presentation device | E1: Delegation | F1: Capacity | G1: Remarks
A2: 1 | B2: 14 Active VN 1 Meeting Room | C2: 14.ActiveVN1.Room@mapactive.vn | D2: Using TV and webcam | E2: VN HR Manager: • van.luugiangcam@mapactive.vn VN HR Admins: • binh.ngotieu@mapactive.vn • ni.ksormahhko@mapactive.vn | F2: 10 | G2: Large Meeting Room
A3: =A2+1 -> 2 | B3: 14 Active VN 2 Meeting Room | C3: 14.ActiveVN2.Room@mapactive.vn | D3: Using Projector | F3: 5 | G3: Small Meeting Room (Converse)
A4: =A3+1 -> 3 | B4: 14 Active VN 3 Meeting Room | C4: 14.ActiveVN3.Room@mapactive.vn | D4: Using TV | F4: 6 | G4: Small Meeting Room (NB)

Sheet Store Laptops-Mini Pc
A1: No. | B1: status new change host | C1: Device Hostname | D1: Device | E1: User | F1: Store name | G1: S/n | H1: Ram (MB) | I1: Hard Disk | J1: CPU | K1: Note
A2: 1 | B2: done | C2: KN01-ADMIN | D2: HP ProDesk 400 G4 DM | E2: PIC_KN01 | F2: BIRKENSTOCK ESTELLA | G2: 8CC90102Q1 | H2: 8032 | I2: 473291 | J2: 2100 MHz Core i5-8500T
A3: 2 | B3: done | C3: PO02-ADMIN | D3: HP ProDesk 400 G3 DM | E3: PIC | F3: Planent Sport Vincom Đồng Khởi | G3: 8CG8105N1T | H3: 8096 | I3: 476318 | J3: 2700 MHz Core i5-7500T | K3: 5/7/2023, 3:37:26 PM (need double check)
A4: 3 | B4: done | C4: PO02-Server | D4: HP ProDesk 400 G3 DM | E4: PIC | F4: Planent Sport Vincom Đồng Khởi
A5: 4 | B5: done | C5: PO02-POS1 | D5: HP ProDesk 400 G3 DM | E5: PIC | F5: Planent Sport Vincom Đồng Khởi
A6: 5 | B6: done | C6: PO02-POS1 | D6: HP ProDesk 400 G3 DM | E6: PIC | F6: Planent Sport Vincom Đồng Khởi
A7: 3 | B7: done | C7: VA02-ADMIN | D7: HP ProBook 440 14 inch G9 Notebook PC | E7: VA02 | F7: New Balance Takashimaya | G7: 5CD250F9ZW | H7: 16000 | I7: 487749 | J7: 2500 MHz 12th Gen Intel Core i5-1235U
A8: 4 | B8: done | C8: VA10-ADMIN | D8: HP ProBook 440 14 inch G9 Notebook PC | E8: VA10 | F8: New Balance Lotte HN | G8: 5CD250F9QZ | H8: 16000 | I8: 487757 | J8: 2500 MHz 12th Gen Intel Core i5-1235U
A9: 5 | B9: check | C9: VC01-ADMIN | D9: HP ProDesk 400 G3 DM | E9: PIC | F9: CHAMPION VINCOM DONG KHOI | G9: 8CG8105MSQ | H9: 8096 | I9: 475773 | J9: 2700 MHz Core i5-7500T
A10: 6 | B10: check | C10: VC02-VI02-ADMIN | D10: HP Laptop 14s-cf2xxx | E10: PIC | F10: CHAMPION-SMIGGLE TAKASHIMAYA | G10: 5CG11088PT | H10: 7968 | I10: 243034 | J10: 1100 MHz Pentium Silver N5030
A11: 7 | B11: done | C11: VC03-ADMIN | D11: HP ProDesk 400 G3 DM | E11: VC03 | F11: CHAMPION AEON HAI PHONG | G11: 8CG75206VW | H11: 8096 | I11: 444427 | J11: 2700 MHz Core i5-7500T
A12: 8 | C12: VC04-ADMIN | D12: Inspiron 3505 | E12: VC04 | F12: PLANET SPORTS LOTTE HN | G12: HRBPK73 | H12: 6016 | I12: 227320 | J12: 2600 MHz Ryzen 3 3250U with Radeon Graphics
A13: 9 | C13: VC05-ADMIN | D13: HP ProDesk 400 G3 DM | E13: PIC | F13: CHAMPION CRESCENT MALL | G13: 8CG75234Q7 | H13: 8096 | I13: 475772 | J13: 2700 MHz Core i5-7500T
A14: 10 | C14: VC06-ADMIN | D14: Inspiron 3505 | E14: VC06 | F14: PLANET SPORTS GOLD COAST NHA TRANG | G14: JS90L73 | H14: 6016 | I14: 227320 | J14: 2600 MHz Ryzen 3 3250U with Radeon Graphics
A15: 11 | C15: VC08-ADMIN | D15: HP 280 G3 MT | E15: PIC | F15: CHAMPION AEON LONG BIEN HN | G15: 4CE7385WV3 | H15: 8096 | I15: 853298 | J15: 3400 MHz Core i5-7500
A16: 12 | C16: VE01-ADMIN | D16: HP ProDesk 400 G3 DM | E16: VE01 | F16: NEWERA AEON HAI PHONG | G16: 8CG75234QC | H16: 8096 | I16: 476323 | J16: 2700 MHz Core i5-7500T
A17: 13 | C17: VE03-ADMIN | D17: HP ProDesk 400 G3 MT | E17: PIC_VE03 | F17: NEWERA AEON HA DONG HN | G17: SGH649PK2B | H17: 8096 | I17: 476315 | J17: 3200 MHz Core i5-6500
A18: 14 | C18: VE04-ADMIN | D18: HP ProDesk 400 G3 DM | E18: PIC-VE04 | F18: NEWERA AEON LONG BIEN HN | G18: 8CG8105N35 | H18: 8096 | I18: 476293 | J18: 2700 MHz Core i5-7500T
A19: 15 | C19: VE06-ADMIN | D19: HP ProBook 440 14 inch G9 Notebook PC | E19: VE06 | F19: New Era Diamond Plaza | G19: 5CD250F9PD | H19: 16000 | I19: 487757 | J19: 2500 MHz 12th Gen Intel Core i5-1235U
A20: 16 | C20: VF02-ADMIN | D20: HP ProDesk 400 G3 DM | E20: PIC | F20: BIRKENSTOCK VINCOM DONG KHOI | G20: 8CG8052W2H | H20: 8096 | I20: 476356 | J20: 2700 MHz Core i5-7500T
A21: 17 | C21: VI01_ADMIN | D21: Lenovo 81FV | E21: VI01-Admin | F21: SMIGGLE ROBINS CRESCENT MALL | G21: PF1MDA7C | H21: 8064 | I21: 1075228 | J21: 2200 MHz Core i7-8750H
A22: 18 | C22: VI03-ADMIN | D22: HP ProDesk 400 G3 DM | E22: PIC | F22: SMIGGLE ESTELLA | G22: 8CG8105MTB | H22: 8096 | I22: 476323 | J22: 2700 MHz Core i5-7500T
A23: 19 | C23: VI04-VN19ADMIN | D23: HP ProBook 440 G2 | E23: VN19 | F23: CONVERSE-SMIGGLE GOLD COAST NHA TRANG | G23: CND53878ZC | H23: 12160 | I23: 476416 | J23: 2200 MHz Core i5-5200U
... A27: 23 | C27: VN03-VR02-ADMIN | D27: Latitude 3520 | E27: VR02 | F27: Converse - ROOKIE TAKASHIMAYA | G27: H4K0BG3 | H27: 7936 | I27: 243574 | J27: 2200 MHz 11th Gen Intel Core i3-1115G4 @ 3.00GHz
A28: 24 | C28: VN04-ADMIN | D28: HP ProDesk 400 G3 DM | E28: PIC-VN04 | F28: CONVERSE AEON HA DONG HN | G28: 8CG8105N2V | H28: 7552 | I28: 476216 | J28: 2700 MHz Core i5-7500T | K28: Điều chuyển tài sản thay thế 1 mày G9 ra cho store với S/N: 8CG8105N2Q
A29: 25 | C29: VN05-ADMIN | D29: HP ProDesk 400 G3 DM | E29: PIC | F29: CONVERSE CRESCENT MALL | G29: 8CG75234RC | H29: 8096 | I29: 476323 | J29: 2700 MHz Core i5-7500T
A30: 26 | C30: VN06-ADMIN | D30: Lenovo 20KFS01900 | E30: PIC | F30: CONVERSE LOTTE HN | G30: PC0VT5R6 | H30: 8096 | I30: 243995 | J30: 1800 MHz Core i5-8250U
A31: 27 | C31: VN07-ADMIN | D31: HP ProDesk 400 G3 DM | E31: PIC | F31: CONVERSE NGUYEN TRAI | G31: 8CG75234Q3 | H31: 8096 | I31: 476323 | J31: 2700 MHz Core i5-7500T
A32: 28 | C32: VN08-ADMIN | D32: HP ProDesk 400 G3 DM | E32: VN08 | F32: CONVERSE HAI BA TRUNG | G32: 8CG8105N2P | H32: 8096 | I32: 476260 | J32: 2700 MHz Core i5-7500T
A33: 29 | C33: VN09-ADMIN | D33: HP ProDesk 400 G3 DM | E33: VN09 | F33: CONVERSE AEON BINH DUONG | G33: 8CG75234R6 | H33: 8096 | I33: 476305 | J33: 2700 MHz Core i5-7500T
A34: 30 | C34: VN10-ADMIN | D34: HP ProDesk 400 G3 DM | E34: VN10 | F34: CONVERSE AEON BINH TAN | G34: 8CG8105N38 | H34: 8096 | I34: 476323 | J34: 2700 MHz Core i5-7500T
A35: 31 | C35: VN13-ADMIN | D35: HP ProDesk 400 G3 DM | E35: PIC | F35: CONVERSE VINCOM MY THO TIEN GIANG | G35: 8CG8052W2J | H35: 8096 | I35: 476294 | J35: 2700 MHz Core i5-7500T
A36: 32 | C36: VN14-ADMIN | D36: HP Pavilion 550-170l | E36: PIC | F36: CONVERSE ROYAL CITY | G36: 4CE61005V3 | H36: 8096 | I36: 953251 | J36: 3700 MHz Core i3-6100
A37: 33 | C37: VN16-ADMIN | D37: HP ProDesk 400 G3 DM | E37: PIC | F37: CONVERSE BA THANG HAI | G37: 8CG8105N2C | H37: 8096 | I37: 476322 | J37: 2700 MHz Core i5-7500T
A38: 34 | C38: VN17-ADMIN | D38: HP ProDesk 400 G3 DM | E38: PIC | F38: CONVERSE VINCOM SMART CITY HN | G38: 8CG8052XG7 | H38: 7904 | I38: 487751 | J38: 790 MHz Core i5-10500T
A39: 35 | C39: VN18-PO03-ADMIN | D39: OptiPlex 3090 | E39: VN18 | F39: CONVERSE BIEN HOA DONG NAI | G39: BGC4LQ3 | H39: 7904 | I39: 487751 | J39: 790 MHz Core i5-10500T
A40: 36 | C40: VN20-PO04-ADMIN | D40: OptiPlex 3090 | E40: VN20 | F40: CONVERSE PHAN VAN TRI | G40: DHC4LQ3 | H40: 7904 | I40: 488283 | J40: 2300 MHz Core i5-10500T
A41: 37 | C41: VN24-ADMIN | D41: OptiPlex 3090 | E41: VN24 | F41: Converse Ba Cu Vung Tau | G41: L | H41: 7904 | I41: 487751 | J41: 2300 MHz Core i5-10500T
A42: 38 | C42: ZK04-ZW04-ADMIN | D42: unknown | E42: unknown | F42: Bazaar | G42: unknown | H42: unknown | I42: unknown | J42: unknown
A43: 39 | C43: ZV07-ADMIN | D43: Lenovo 81FV | E43: PIC | F43: Event | G43: PF1FV71U | H43: 8064 | I43: 1073784 | J43: 2200 MHz Core i7-8750H
A44: 40 | C44: ZV08-ADMIN | D44: HP ProDesk 400 G3 DM | E44: ZV08 | F44: Event | G44: 8CG8105N2J | H44: 8096 | I44: 475773 | J44: 2700 MHz Core i5-7500T
A45: 41 | C45: ZV09-ZV12-ADMIN | D45: Lenovo - 20N8S0CJ00 | E45: ZV12 | F45: Event | G45: PF1JSUP7 | H45: 8032 | I45: 1181938 | J45: 1800 MHz Core i5-8265U
A46: 42 | C46: ZV10-ADMIN | D46: LAPTOP HP PROBOOK 440 G9 | E46: ZV10 | F46: Event | G46: PF1JSUP7 | H46: 16000 | I46: 512000 | J46: CORE I5-1235U
A47: 43 | C47: ZV11-ADMIN | D47: LAPTOP HP PROBOOK 440 G9 | E47: ZV11 | F47: Event | G47: 5CD236BCSY | H47: 16000 | I47: 512000 | J47: CORE I5-1235U
A48: 44 | C48: ZV01-H103-H104 | D48: HP ProDesk 400 G3 DM | E48: PIC | F48: Bazaar | G48: 8CG8105MSK | H48: 8096 | I48: 248681 | J48: 2700 MHz Core i5-7500T
A49: 45 | C49: VA06-Admin | D49: HP ProBook 440 14 inch G9 Notebook PC | E49: PIC | F49: New Balance Cresent Mall | G49: 5CD250F9PY | H49: 16000 | I49: 512000 | J49: Core I5-1235U
A50: 46 | C50: VE05-Admin | D50: Laptop Thinkpad x280 | E50: PIC | F50: New Era Crensent Mall | G50: PC0VSNXT | H50: 8096 | I50: 248681 | J50: Intel(R) Core(TM) i5-8250U CPU @ 1.60GHz 1.80 GHz
A51: 47 | C51: VN27-POS1 | D51: PC PRO MINI 400G6 HP | E51: POS 1 | F51: Converse Quang Trung | G51: 8CC22011GD | H51: 16000 | I51: 512000 | J51: Intel(R) Core(TM) i5-10500T CPU @ 2.30GHz 2.30 GHz
A52: 48 | C52: VN27-POS2 | D52: PC PRO MINI 400G6 HP | E52: POS 2 | F52: Converse Quang Trung | G52: 8CC2231CY7 | H52: 16000 | I52: 512000 | J52: Intel(R) Core(TM) i5-10500T CPU @ 2.30GHz 2.30 GHz
A53: 49 | C53: VN27-ADMIN | D53: PC PRO MINI 400G6 HP | E53: ADMIN | F53: Converse Quang Trung | G53: 8CC22011BC | H53: 16000 | I53: 512000 | J53: Intel(R) Core(TM) i5-10500T CPU @ 2.30GHz 2.30 GHz
A54: 50 | C54: VN27-SERVER | D54: PC PRO MINI 400G6 HP | E54: SERVER | F54: Converse Quang Trung | G54: 8CC22011BS | H54: 16000 | I54: 512000 | J54: Intel(R) Core(TM) i5-10500T CPU @ 2.30GHz 2.30 GHz
... A69: 65 | C69: VO02-POS03 | D69: HP Elite Mini 600 G9 | E69: POS 3 | F69: FL Lotte Mall HN | G69: 8CC323166B | H69: 16000 | I69: 512000 | J69: Intel Core i7 12700

Sheet  DASHBOARD BIGFIX & Crowdstrike
A1: DASHBOARD BIGFIX & Crowdstrike
A2: STORE-WAREHOUSER | F2: OFFICE-MMA STT
A3: STT | B3: Store code-hostname | C3: Bigfix | D3: Crowdstrike | F3: STT | G3: NEW -HOSTNAME | H3: User | I3: BIGfix Office | J3: Crowdstrike
A4: 1 | B4: KN01-Admin | C4: DONE | D4: DONE | F4: 1 | G4: AMMAVN_C000001 | H4: PEACOCK DARRYL JAMES | I4: DONE | J4: DONE
A5: 2 | B5: PO02-server | C5: DONE | D5: DONE | F5: 2 | G5: AMMAVN_C000002 | H5: Nguyễn Hà Phượng Uyên | I5: DONE | J5: DONE
A6: 3 | B6: PO02-Admin | C6: DONE | D6: DONE | F6: 3 | G6: AMMAVNACCC000003 | H6: Nguyễn Thị Huỳnh Mai | I6: DONE | J6: DONE
A7: 4 | B7: PO02-POS1 | C7: DONE | D7: DONE | F7: 4 | G7: AMMAVNACCC000004 | H7: HUỲNH MỸ DANH | I7: DONE | J7: DONE
A8: 5 | B8: PO02-POS2 | C8: DONE | D8: DONE | F8: 5 | G8: AMMAVNACCC000005 | H8: MAI NGUYỄN DIỄM QUỲNH | I8: DONE | J8: DONE
A9: 6 | B9: VC01-Admin | C9: DONE | D9: DONE | F9: 6 | G9: AMMAVNACCC000006 | H9: NGUYỄN HOÀNG ANH THY | I9: DONE | J9: DONE
A10: 7 | B10: VC02-VI02-Admin | C10: DONE | D10: DONE | F10: 7 | G10: AMMAVNACCC000007 | H10: VĂN HUỲNH TÚ TRINH | I10: DONE | J10: DONE
A11: 8 | B11: VC03-Admin | C11: DONE | D11: DONE | F11: 8 | G11: AMMAVNBPCC000008 | H11: LÊ THỊ ÁNH TUYẾT | I11: DONE | J11: DONE
A12: 9 | B12: VC04-Admin | C12: DONE | D12: DONE | F12: 9 | G12: AMMAVNACCC000009 | H12: MAI LÊ CẨM HÒA | I12: DONE | J12: DONE
A13: 10 | B13: VC05-Admin | C13: DONE | D13: DONE | F13: 10 | G13: AMMAVNROC000010 | H13: HUỲNH THỊ MỸ TRANG | I13: DONE | J13: DONE
A14: 11 | B14: VC06-Admin | C14: DONE | D14: DONE | F14: 11 | G14: AMMAVNHRC000011 | H14: LƯU GIANG CẨM VÂN | I14: DONE | J14: DONE
A15: 12 | B15: VC08-Admin | C15: DONE | D15: DONE | F15: 12 | G15: AMMAVNHRC000012 | H15: NGÔ TIỂU BÌNH | I15: DONE | J15: DONE
... A69: 66 | B69: KN12-ADMIN | C69: DONE | D69: DONE | F69: 66 | G69: AMMAVNLOC000066 | H69: NGUYỄN THỊ BÍCH TRÂM | I69: DONE | J69: DONE
F70: 67 | G70: AMMAVNMDC000067 | H70: Syed Umair | I70: DONE | J70: DONE
B71: STORE EVENT | F71: 68 | G71: AMMAVNMPC000068 | H71: TRẦN THỊ TOÀN MỸ | I71: DONE | J71: DONE
A72: 67 | B72: ZV07-ADMIN(NHA TRANG) | C72: DONE | D72: DONE | F72: 69 | G72: AMMAVNITC000069 | H72: Lương Hữu Quân | I72: DONE | J72: DONE
A73: 68 | B73: ZV08-ADMIN | C73: DONE | D73: DONE | F73: 70 | G73: AMMAVNACC000070 | H73: Nguyễn Thị Quí | I73: DONE | J73: DONE
A74: 69 | B74: ZV09-ZV12 | C74: DONE | D74: DONE | F74: 71 | G74: AMMAVNITC000071 | H74: Nguyễn Hữu An | I74: DONE | J74: DONE
A75: 70 | B75: ZV10-ADMIN | C75: DONE | D75: DONE | F75: 72 | G75: AMMAVNTAC000072 | H75: Đào Thị Hồng Lê | I75: DONE | J75: DONE
A76: 71 | B76: ZV11-ADMIN | C76: DONE | D76: DONE | F76: 73 | G76: AMMAVNMDC000073 | H76: Nguyễn Quốc Huy | I76: DONE | J76: DONE
B77: BAZZA STORE | F77: 74 | G77: AMMAVNMRC000074 | H77: Pham Thi My Dung | I77: DONE | J77: DONE
A78: 72 | B78: H101-102- ADMIN | C78: DONE | D78: DONE | F78: 75 | G78: AMMAVNOPC000075 | H78: PHÙNG NHƯ QUỲNH | I78: DONE | J78: DONE
A79: 73 | B79: ZK04-ZV04-ZW04-ADMIN | C79: DONE | D79: DONE | F79: 76 | G79: AMMAVNECC000076 | H79: Vũ Bá Minh | I79: DONE | J79: DONE
A80: 74 | B80: ZK06-ZV06-ZW06-ADMIN | C80: DONE | D80: DONE | F80: 77 | G80: AMMAVNMDC000077 | H80: Nguyễn Đỗ Hiền | I80: DONE | J80: DONE
A81: 75 | B81: ZK05-ZV05-ZW5-ADMIN | C81: DONE | D81: DONE | F81: 78 | G81: AMMAVNGDC000078 | H81: NGUYỄN NGỌC LAN ANH | I81: DONE | J81: DONE
A82: 76 | B82: ZV01-H103-H104-ADMIN | C82: DONE | D82: DONE | F82: 79 | G82: AMMAVNGDD000079 | H82: Lê Thanh Duyên | I82: DONE | J82: DONE
B83: DSV | F83: 80 | G83: AMMAVNMDC000080 | H83: Nguyễn Thanh Anh Thư | I83: DONE | J83: DONE
A84: 77 | B84: MMA-DSV-001 | C84: DONE | D84: DONE | F84: 81 | G84: AMMAVNOPC000081 | H84: Đào Đức Huy | I84: DONE | J84: DONE
A85: 78 | B85: MMA-DSV-002 | C85: DONE | D85: DONE | F85: 82 | G85: AMMAVNMDC000082 | H85: Lê Huỳnh Duy | I85: DONE | J85: DONE
A86: 79 | B86: MMA-DSV-003 | C86: DONE | D86: DONE | F86: 83 | G86: AMMAVNMPC000083 | H86: Nguyễn Thị Tuyết Nhung | I86: DONE | J86: DONE
A87: 80 | B87: MMA-DSV-004 | C87: DONE | D87: DONE | F87: 84 | G87: AMMAVNTAC000084 | H87: LÊ NAM HUÂN | I87: DONE | J87: DONE
A88: 81 | B88: MMA-DSV-005 | C88: DONE | D88: DONE | F88: 85 | G88: AMMAVNMRC000085 | H88: Nguyễn Vũ Trung Hiếu | I88: DONE | J88: DONE
A89: 82 | F89: 86 | G89: AMMAVN_C000086 | H89: Nguyễn Như Quỳnh | I89: DONE | J89: DONE
A90: 83 | F90: 87 | G90: AMMAVNMDC000087 | H90: HUỲNH KIM DUNG | I90: DONE | J90: DONE
A91: 84 | F91: 88 | G91: AMMAVNHRD000088 | H91: Nguyễn Bảo Du | I91: DONE | J91: DONE
A92: 85 | F92: 89 | G92: AMMAVNACD000089 | H92: Đinh Lê Gia Bảo | I92: DONE | J92: DONE
F93: 90 | G93: AMMAVNMRD000090 | H93: Hoàng Thân Bảo Phúc | I93: DONE | J93: DONE
F94: 91 | G94: AMMAVNITC000091 | H94: IT BACKUP(LAPTOP X280 CŨ NI(HR) | I94: DONE | J94: DONE
A95: Total | B95: 81 | F95: 92 | G95: AMMAVNICC000092 | H95: TRẦN DUY ĐIỀN | I95: DONE | J95: DONE
F96: 94

Sheet TEMP
A1: DEVICES | B1: TYPE | C1: QTY | D1: SERI NUMBER | E1: STOREAGE | F1: NOTE | H1: check list Store
A2: Lenovo TB 8505X 3G +32 GGR9-VN-GOV | B2: TABLET | C2: 2 | D2: HA1JYS7A-HA1K0KWK | E2: LOGISTIC | F2: ĐÃ BÀN GIAO | H2: KN01-ADMIN
A3: Lenovo TB 8505X 3G +32 GGR9-VN-GOV | B3: TABLET | C3: 1 | E3: QUAN TEST | H3: PO02-ADMIN
A4: Lenovo TB 8505X 3G +32 GGR9-VN-GOV | B4: TABLET | C4: 1 | E4: KHO IT | H4: PO02-Server
A5: Lenovo TB 8505X 3G +32 GGR9-VN-GOV | B5: TABLET | C5: 5 | E5: KHO IT | H5: PO02-POS1
A6: PRINTER POSTEK -IQ200 203DPI-BLUETOOTH | B6: PRINTER | C6: 3 | D6: I1622C001(VN13)-002(VO02)-003(I1622C0003-VN18) | E6: Store | H6: PO02-POS1
A7: PRINTER POSTEK -IQ200 203DPI-BLUETOOTH | B7: PRINTER | C7: 2 | D7: I1622F0004-I1622F0005 | E7: Logistic | F7: ĐÃ BÀN GIAO | H7: VA02-ADMIN
A8: PRINTER POSTEK -IQ200 203DPI-BLUETOOTH | B8: PRINTER | C8: 5 | E8: IT SERVER ROOM(I1623H0001-2-3-4-5) | H8: VA10-ADMIN
A9: GALAXY TAB S6 LITE | B9: TABLET | C9: 8 | E9: vo02 | F9: ĐÃ BÀN GIAO | H9: VC01-ADMIN
H10: VC02-VI02-ADMIN
H11: VC03-ADMIN
H12: VC04-ADMIN
H13: VC05-ADMIN
H14: VC06-ADMIN
H15: VC08-ADMIN
H16: VE01-ADMIN
H17: VE03-ADMIN
H18: VE04-ADMIN
H19: VE06-ADMIN
H20: VF02-ADMIN
H21: VI01_ADMIN
... H69: VO02-POS03

Sheet SDWAN_Project
A1: Est Month | B1: Est Phase | C1: Store | D1: Store Code | E1: Status | F1: Location | G1: City | H1: Address
A2: Mar | B2: =IF(A2="Mar",1,IF(A2="Jun",2,IF(A2="Sep",3,""))) -> 1 | C2: Birkenstock Crescent mall, HCMC | D2: KN09 | E2: =VLOOKUP(D2,Store_Info_VN!B:M,3,FALSE) -> Open | F2: =VLOOKUP(D2,Store_Info_VN!B:M,4,FALSE) -> CRESCENT MALL | G2: =VLOOKUP(D2,Store_Info_VN!B:M,5,FALSE) -> Ho Chi Minh City | H2: =VLOOKUP(D2,Store_Info_VN!B:M,8,FALSE) -> 2F-18B Crescent Mall (No. 101 Ton Dat Tien, Tan Phu Ward, District 7)
A3: Mar | B3: =IF(A3="Mar",1,IF(A3="Jun",2,IF(A3="Sep",3,""))) -> 1 | C3: Birkenstock Lotte Mall Westlake, Hanoi | D3: KN12 | E3: =VLOOKUP(D3,Store_Info_VN!B:M,3,FALSE) -> Open | F3: =VLOOKUP(D3,Store_Info_VN!B:M,4,FALSE) -> LOTTE MALL | G3: =VLOOKUP(D3,Store_Info_VN!B:M,5,FALSE) -> Ha Noi | H3: =VLOOKUP(D3,Store_Info_VN!B:M,8,FALSE) -> 2F-233 lot - Lotte Mall (No. 683 Lac Long Quan street, Phu Thuong ward, Tay Ho district)
A4: Jun | B4: =IF(A4="Mar",1,IF(A4="Jun",2,IF(A4="Sep",3,""))) -> 2 | C4: Birkenstock Goldcoast Nha Trang | D4: KN10 | E4: =VLOOKUP(D4,Store_Info_VN!B:M,3,FALSE) -> Open | F4: =VLOOKUP(D4,Store_Info_VN!B:M,4,FALSE) -> GOLDCOAST NHA TRANG | G4: =VLOOKUP(D4,Store_Info_VN!B:M,5,FALSE) -> NHA TRANG | H4: =VLOOKUP(D4,Store_Info_VN!B:M,8,FALSE) -> Floor G, GoldCoast Mall, 01 Tran Hung Dao, Loc Tho, Nha Trang, Khanh Hoa
A5: Mar | B5: =IF(A5="Mar",1,IF(A5="Jun",2,IF(A5="Sep",3,""))) -> 1 | C5: Rookie Lotte Mall Westlake, Hanoi | D5: VR12 | E5: =VLOOKUP(D5,Store_Info_VN!B:M,3,FALSE) -> Open | F5: =VLOOKUP(D5,Store_Info_VN!B:M,4,FALSE) -> LOTTE MALL | G5: =VLOOKUP(D5,Store_Info_VN!B:M,5,FALSE) -> Ha Noi | H5: =VLOOKUP(D5,Store_Info_VN!B:M,8,FALSE) -> 3F-333 lot - Lotte Mall (No. 683 Lac Long Quan street, Phu Thuong ward, Tay Ho district)
A6: Mar | B6: =IF(A6="Mar",1,IF(A6="Jun",2,IF(A6="Sep",3,""))) -> 1 | C6: New Era Lotte Mall Westlake, Hanoi | D6: VE12 | E6: =VLOOKUP(D6,Store_Info_VN!B:M,3,FALSE) -> Open | F6: =VLOOKUP(D6,Store_Info_VN!B:M,4,FALSE) -> LOTTE MALL | G6: =VLOOKUP(D6,Store_Info_VN!B:M,5,FALSE) -> Ha Noi | H6: =VLOOKUP(D6,Store_Info_VN!B:M,8,FALSE) -> 2F-240,241 lot - Lotte Mall (No. 683 Lac Long Quan street, Phu Thuong ward, Tay Ho district)
A7: Mar | B7: =IF(A7="Mar",1,IF(A7="Jun",2,IF(A7="Sep",3,""))) -> 1 | C7: Converse Aeon Long Bien, Hanoi | D7: VN01 | E7: =VLOOKUP(D7,Store_Info_VN!B:M,3,FALSE) -> Close | F7: =VLOOKUP(D7,Store_Info_VN!B:M,4,FALSE) -> AEON LONG BIEN | G7: =VLOOKUP(D7,Store_Info_VN!B:M,5,FALSE) -> Ha Noi | H7: =VLOOKUP(D7,Store_Info_VN!B:M,8,FALSE) -> T217 Aeon Mall Long Bien, No. 27 Co Linh Street, Long Bien Ward, Long Bien District, Ha Noi
A8: Mar | B8: =IF(A8="Mar",1,IF(A8="Jun",2,IF(A8="Sep",3,""))) -> 1 | C8: Converse NGUYEN TRAI D1, HCMC | D8: VN07 | E8: =VLOOKUP(D8,Store_Info_VN!B:M,3,FALSE) -> Open | F8: =VLOOKUP(D8,Store_Info_VN!B:M,4,FALSE) -> NGUYEN TRAI | G8: =VLOOKUP(D8,Store_Info_VN!B:M,5,FALSE) -> Ho Chi Minh City | H8: =VLOOKUP(D8,Store_Info_VN!B:M,8,FALSE) -> 124 Nguyen Trai, Ben Thanh Ward, District 1, Ho Chi Minh City
A9: Mar | B9: =IF(A9="Mar",1,IF(A9="Jun",2,IF(A9="Sep",3,""))) -> 1 | C9: Converse Crescent mall, HCMC | D9: VN05 | E9: =VLOOKUP(D9,Store_Info_VN!B:M,3,FALSE) -> Open | F9: =VLOOKUP(D9,Store_Info_VN!B:M,4,FALSE) -> CRESCENT MALL | G9: =VLOOKUP(D9,Store_Info_VN!B:M,5,FALSE) -> Ho Chi Minh City | H9: =VLOOKUP(D9,Store_Info_VN!B:M,8,FALSE) -> L3 101 Ton Dat Tien, Tan Phu Ward, District 7, Ho Chi Minh City
A10: Jun | B10: =IF(A10="Mar",1,IF(A10="Jun",2,IF(A10="Sep",3,""))) -> 2 | C10: Converse Aeon Ha Dong, Hanoi | D10: VN04 | E10: =VLOOKUP(D10,Store_Info_VN!B:M,3,FALSE) -> Open | F10: =VLOOKUP(D10,Store_Info_VN!B:M,4,FALSE) -> AEON HA DONG | G10: =VLOOKUP(D10,Store_Info_VN!B:M,5,FALSE) -> Ha Noi | H10: =VLOOKUP(D10,Store_Info_VN!B:M,8,FALSE) -> T228 Aeon Ha Dong, Hoang Van Thu Residential Area, Duong Noi Ward, Ha Dong District, Ha Noi
A11: Sep | B11: =IF(A11="Mar",1,IF(A11="Jun",2,IF(A11="Sep",3,""))) -> 3 | C11: Converse BA THANG HAI D10, HCMC | D11: VN16 | E11: =VLOOKUP(D11,Store_Info_VN!B:M,3,FALSE) -> Open | F11: =VLOOKUP(D11,Store_Info_VN!B:M,4,FALSE) -> BA THANG HAI | G11: =VLOOKUP(D11,Store_Info_VN!B:M,5,FALSE) -> Ho Chi Minh City | H11: =VLOOKUP(D11,Store_Info_VN!B:M,8,FALSE) -> 152 Ba Thang Hai ,Ward 12, District 10, Ho Chi Minh City
A12: Sep | B12: =IF(A12="Mar",1,IF(A12="Jun",2,IF(A12="Sep",3,""))) -> 3 | C12: Converse HAI BA TRUNG D3, HCMC | D12: VN08 | E12: =VLOOKUP(D12,Store_Info_VN!B:M,3,FALSE) -> Open | F12: =VLOOKUP(D12,Store_Info_VN!B:M,4,FALSE) -> HAI BA TRUNG | G12: =VLOOKUP(D12,Store_Info_VN!B:M,5,FALSE) -> Ho Chi Minh City | H12: =VLOOKUP(D12,Store_Info_VN!B:M,8,FALSE) -> 243 Hai Ba Trung, Vo Thi Sau Ward, District 3, Ho Chi Minh City
A13: Mar | B13: =IF(A13="Mar",1,IF(A13="Jun",2,IF(A13="Sep",3,""))) -> 1 | C13: Converse Aeon Binh Tan, HCMC | D13: VN10 | E13: =VLOOKUP(D13,Store_Info_VN!B:M,3,FALSE) -> Open | F13: =VLOOKUP(D13,Store_Info_VN!B:M,4,FALSE) -> AEON BINH TAN | G13: =VLOOKUP(D13,Store_Info_VN!B:M,5,FALSE) -> Ho Chi Minh City | H13: =VLOOKUP(D13,Store_Info_VN!B:M,8,FALSE) -> F26 , 1 Floor , Aeon Mall Binh Tan (01, 17A Street, Binh Tri Dong B Ward, Binh Tan District, Ho Chi Minh City)
... A19: Mar | B19: =IF(A19="Mar",1,IF(A19="Jun",2,IF(A19="Sep",3,""))) -> 1 | C19: Converse Quang Trung CFS, HCMC | D19: VN27 | E19: =VLOOKUP(D19,Store_Info_VN!B:M,3,FALSE) -> Open | F19: =VLOOKUP(D19,Store_Info_VN!B:M,4,FALSE) -> 11-13 QUANG TRUNG GV | G19: =VLOOKUP(D19,Store_Info_VN!B:M,5,FALSE) -> Ho Chi Minh City | H19: =VLOOKUP(D19,Store_Info_VN!B:M,8,FALSE) -> 11-13 Quang Trung, Quận Gò Vấp, Thành Phố Hồ Chí Minh
A20: Sep | B20: =IF(A20="Mar",1,IF(A20="Jun",2,IF(A20="Sep",3,""))) -> 3 | C20: Converse Parc mall, HCMC | E20: =VLOOKUP(D20,Store_Info_VN!B:M,3,FALSE) -> #N/A | F20: =VLOOKUP(D20,Store_Info_VN!B:M,4,FALSE) -> #N/A | G20: =VLOOKUP(D20,Store_Info_VN!B:M,5,FALSE) -> #N/A | H20: =VLOOKUP(D20,Store_Info_VN!B:M,8,FALSE) -> #N/A
A21: Jun | B21: =IF(A21="Mar",1,IF(A21="Jun",2,IF(A21="Sep",3,""))) -> 2 | C21: Converse Vincom Thao Dien, HCMC | E21: =VLOOKUP(D21,Store_Info_VN!B:M,3,FALSE) -> #N/A | F21: =VLOOKUP(D21,Store_Info_VN!B:M,4,FALSE) -> #N/A | G21: =VLOOKUP(D21,Store_Info_VN!B:M,5,FALSE) -> #N/A | H21: =VLOOKUP(D21,Store_Info_VN!B:M,8,FALSE) -> #N/A
A22: Jun | B22: =IF(A22="Mar",1,IF(A22="Jun",2,IF(A22="Sep",3,""))) -> 2 | C22: Converse CFS, Hanoi | E22: =VLOOKUP(D22,Store_Info_VN!B:M,3,FALSE) -> #N/A | F22: =VLOOKUP(D22,Store_Info_VN!B:M,4,FALSE) -> #N/A | G22: =VLOOKUP(D22,Store_Info_VN!B:M,5,FALSE) -> #N/A | H22: =VLOOKUP(D22,Store_Info_VN!B:M,8,FALSE) -> #N/A
A23: Mar | B23: =IF(A23="Mar",1,IF(A23="Jun",2,IF(A23="Sep",3,""))) -> 1 | C23: New Balance Nguyen Trai, HCMC | D23: VA11 | E23: =VLOOKUP(D23,Store_Info_VN!B:M,3,FALSE) -> Open | F23: =VLOOKUP(D23,Store_Info_VN!B:M,4,FALSE) -> 89 NGUYỄN TRÃI | G23: =VLOOKUP(D23,Store_Info_VN!B:M,5,FALSE) -> Ho Chi Minh City | H23: =VLOOKUP(D23,Store_Info_VN!B:M,8,FALSE) -> 89 Nguyen Trai Street, Ben Thanh Ward, District 1
A24: Jun | B24: =IF(A24="Mar",1,IF(A24="Jun",2,IF(A24="Sep",3,""))) -> 2 | C24: New Balance Aeon Hai Phong | E24: =VLOOKUP(D24,Store_Info_VN!B:M,3,FALSE) -> #N/A | F24: =VLOOKUP(D24,Store_Info_VN!B:M,4,FALSE) -> #N/A | G24: =VLOOKUP(D24,Store_Info_VN!B:M,5,FALSE) -> #N/A | H24: =VLOOKUP(D24,Store_Info_VN!B:M,8,FALSE) -> #N/A
A25: Mar | B25: =IF(A25="Mar",1,IF(A25="Jun",2,IF(A25="Sep",3,""))) -> 1 | C25: New Balance Crescent mall, HCMC | D25: VA06 | E25: =VLOOKUP(D25,Store_Info_VN!B:M,3,FALSE) -> Open | F25: =VLOOKUP(D25,Store_Info_VN!B:M,4,FALSE) -> CRESCENT MALL | G25: =VLOOKUP(D25,Store_Info_VN!B:M,5,FALSE) -> Ho Chi Minh City | H25: =VLOOKUP(D25,Store_Info_VN!B:M,8,FALSE) -> 3F-33 - Crescent Mall, 101 Tôn Dật Tiên, Phường Tân Hưng, Quận 7, Thành Phố Hồ Chí Minh.
A26: Mar | B26: =IF(A26="Mar",1,IF(A26="Jun",2,IF(A26="Sep",3,""))) -> 1 | C26: New Balance Lotte Mall Westlake, Hanoi | D26: VA12 | E26: =VLOOKUP(D26,Store_Info_VN!B:M,3,FALSE) -> Open | F26: =VLOOKUP(D26,Store_Info_VN!B:M,4,FALSE) -> LOTTE MALL | G26: =VLOOKUP(D26,Store_Info_VN!B:M,5,FALSE) -> Ha Noi | H26: =VLOOKUP(D26,Store_Info_VN!B:M,8,FALSE) -> 2F-229 lot - Lotte Mall (No. 683 Lac Long Quan street, Phu Thuong ward, Tay Ho district)
A27: Mar | B27: =IF(A27="Mar",1,IF(A27="Jun",2,IF(A27="Sep",3,""))) -> 1 | C27: New Balance Diamond, HCMC | D27: VA08 | E27: =VLOOKUP(D27,Store_Info_VN!B:M,3,FALSE) -> Open | F27: =VLOOKUP(D27,Store_Info_VN!B:M,4,FALSE) -> DIAMOND PLAZA | G27: =VLOOKUP(D27,Store_Info_VN!B:M,5,FALSE) -> Ho Chi Minh City | H27: =VLOOKUP(D27,Store_Info_VN!B:M,8,FALSE) -> XA-32239 Diamond Plaza (No. 34 Le Duan street, Ben Nghe ward, district 1, Ho Chi Minh city)
A28: Sep | B28: =IF(A28="Mar",1,IF(A28="Jun",2,IF(A28="Sep",3,""))) -> 3 | C28: New Balance IPH, Hanoi | D28: VA09 | E28: =VLOOKUP(D28,Store_Info_VN!B:M,3,FALSE) -> Close | F28: =VLOOKUP(D28,Store_Info_VN!B:M,4,FALSE) -> IPH MALL | G28: =VLOOKUP(D28,Store_Info_VN!B:M,5,FALSE) -> Ha Noi | H28: =VLOOKUP(D28,Store_Info_VN!B:M,8,FALSE) -> Toà nhà IPH số 241 Xuân Thuỷ, phường Dịch Vọng Hậu, quận Cầu Giấy, Hà Nội
A29: Mar | B29: =IF(A29="Mar",1,IF(A29="Jun",2,IF(A29="Sep",3,""))) -> 1 | C29: New Balance Van Hanh mall, HCMC | D29: VA01 | E29: =VLOOKUP(D29,Store_Info_VN!B:M,3,FALSE) -> Open | F29: =VLOOKUP(D29,Store_Info_VN!B:M,4,FALSE) -> VAN HANH MALL | G29: =VLOOKUP(D29,Store_Info_VN!B:M,5,FALSE) -> Ho Chi Minh City | H29: =VLOOKUP(D29,Store_Info_VN!B:M,8,FALSE) -> 2-07B Van Hanh Mall
A30: Jun | B30: =IF(A30="Mar",1,IF(A30="Jun",2,IF(A30="Sep",3,""))) -> 2 | C30: New Balance Gold Coast, Nha Trang | D30: VA04 | E30: =VLOOKUP(D30,Store_Info_VN!B:M,3,FALSE) -> Open | F30: =VLOOKUP(D30,Store_Info_VN!B:M,4,FALSE) -> GOLDCOAST NHA TRANG | G30: =VLOOKUP(D30,Store_Info_VN!B:M,5,FALSE) -> NHA TRANG | H30: =VLOOKUP(D30,Store_Info_VN!B:M,8,FALSE) -> Floor G, GoldCoast Mall, 01 Tran Hung Dao, Loc Tho, Nha Trang, Khanh Hoa
A31: Jun | B31: =IF(A31="Mar",1,IF(A31="Jun",2,IF(A31="Sep",3,""))) -> 2 | C31: New Balance Vincom Thao Dien, HCMC | D31: VA05 | E31: =VLOOKUP(D31,Store_Info_VN!B:M,3,FALSE) -> Open | F31: =VLOOKUP(D31,Store_Info_VN!B:M,4,FALSE) -> VINCOM THAO DIEN | G31: =VLOOKUP(D31,Store_Info_VN!B:M,5,FALSE) -> Ho Chi Minh City | H31: =VLOOKUP(D31,Store_Info_VN!B:M,8,FALSE) -> Floor 2, No. 161 Hanoi road, Thao Dien ward, Thu Duc city
A32: Sep | B32: =IF(A32="Mar",1,IF(A32="Jun",2,IF(A32="Sep",3,""))) -> 3 | C32: New Balance Nguyen Trai, Can Tho | D32: VA22 | E32: =VLOOKUP(D32,Store_Info_VN!B:M,3,FALSE) -> Open | F32: =VLOOKUP(D32,Store_Info_VN!B:M,4,FALSE) -> 78 NGUYEN TRAI | G32: =VLOOKUP(D32,Store_Info_VN!B:M,5,FALSE) -> Can Tho | H32: =VLOOKUP(D32,Store_Info_VN!B:M,8,FALSE) -> 78 Nguyen Trai Can Tho
A33: Sep | B33: =IF(A33="Mar",1,IF(A33="Jun",2,IF(A33="Sep",3,""))) -> 3 | C33: New Balance Parc mall, HCMC | E33: =VLOOKUP(D33,Store_Info_VN!B:M,3,FALSE) -> #N/A | F33: =VLOOKUP(D33,Store_Info_VN!B:M,4,FALSE) -> #N/A | G33: =VLOOKUP(D33,Store_Info_VN!B:M,5,FALSE) -> #N/A | H33: =VLOOKUP(D33,Store_Info_VN!B:M,8,FALSE) -> #N/A
